Workbook
Name Print_Area: Dashboard!$B$2:$N$60

Sheet Dashboard
B2: RESTAURANTE CHOCLOS Y ASADOS LA FINCA
B3: DASHBOARD GERENCIAL DE COSTOS Y GASTOS - INFORME MENSUAL Y DIARIO SEPTIEMBRE 2026
B5: TOTAL COMPRAS DEL MES | E5: TOTAL COSTOS DIRECTOS (COGS) | I5: TOTAL GASTOS OPERACIONALES (OPEX) | L5: INVENTARIO INICIAL (APERTURA)
B6: 2.1168322e+08 | E6: 1.1635363e+08 | I6: 95329592 | L6: 12243950
B7: COGS: $ 116,353,629.71 | OPEX: $ 95,329,591.71 | E7: 55% de compras del mes | I7: 45% de compras del mes | L7: Stock Inicial (No es categoría)
B9: 1. COSTOS DIRECTOS (COGS: MATERIA PRIMA E INSUMOS) | I9: 2. GASTOS OPERACIONALES Y ADMINISTRATIVOS (OPEX)
B10: Categoría / Insumo | C10: Tipo | D10: N° Compras | E10: Total Mes ($) | F10: % Costos | G10: Prom. Día | I10: Concepto / Categoría | J10: Tipo | K10: N° Pagos | L10: Total Mes ($) | M10: % Gastos | N10: Prom. Día
B11: Carnes y Proteínas | C11: Directo | D11: 179 | E11: 67613773 | F11: 0.58110583 | G11: 2414777.6 | I11: Servicios (Personal y Planta) | J11: Gasto Oper. | K11: 83 | L11: 51133382 | M11: 0.5363852 | N11: 1826192.2
B12: Verduras y Frutas | C12: Directo | D12: 240 | E12: 16098719 | F12: 0.13836026 | G12: 574954.25 | I12: Mantenimiento y Adecuaciones | J12: Gasto Oper. | K12: 17 | L12: 4364978.7 | M12: 0.045788287 | N12: 155892.1
B13: Desechables y Empaques | C13: Directo | D13: 193 | E13: 10394477 | F13: 0.089335223 | G13: 371231.34 | I13: Servicios Públicos (Energía y TV) | J13: Gasto Oper. | K13: 6 | L13: 6232420 | M13: 0.065377601 | N13: 222586.43
B14: Granos y Harinas | C14: Directo | D14: 103 | E14: 7578719 | F14: 0.065135217 | G14: 270668.53 | I14: Otros Gastos Operacionales (Admin y Varios) | J14: Gasto Admin. | K14: 79 | L14: 33598811 | M14: 0.35244891 | N14: 1199957.5
B15: Bebidas y Licores | C15: Directo | D15: 134 | E15: 7593154.9 | F15: 0.065259287 | G15: 271184.11 | I15: SUBTOTAL GASTOS OPERACIONALES | J15: Operativo | K15: 185 | L15: 95329592 | M15: 1 | N15: 3404628.3
B16: Otros Insumos (Abarrotes y Cocina) | C16: Directo | D16: 97 | E16: 7074786.6 | F16: 0.060804176 | G16: 252670.95
B17: SUBTOTAL COSTOS DIRECTOS | C17: Materia Prima | D17: 946 | E17: 1.1635363e+08 | F17: 1 | G17: 4155486.8
B20: RESUMEN CONSOLIDADO: COSTOS DIRECTOS VS GASTOS OPERACIONALES
B21: Costos Directos (COGS) | D21: 946 | E21: 1.1635363e+08 | F21: 0.5496592 | G21: 4155486.8
B22: Gastos Operacionales (OPEX) | D22: 185 | E22: 95329592 | F22: 0.4503408 | G22: 3404628.3
B23: SUBTOTAL COMPRAS DEL MES | D23: 1131 | E23: 2.1168322e+08 | F23: 1 | G23: 7560115.1
B24: (+) Inventario Inicial (Stock Apertura) | D24: 1 | E24: 12243950 | F24: Inversión Inicial | G24: -
B25: TOTAL GENERAL CONSOLIDADO | D25: 1132 | E25: 2.2392717e+08 | F25: 100% Acumulado | G25: -
B26: 3. TOTALIZACIÓN DIARIA: COSTOS Y GASTOS DÍA A DÍA (SEPTIEMBRE 2026)
B27: Día | C27: Costos ($) | D27: Gastos ($) | E27: Total Día ($) | F27: % Costo | G27: % Gasto | H27: Carnes ($) | I27: Verduras ($) | J27: Grano ($) | K27: Bebidas ($) | L27: Desechables ($) | M27: Servicios ($) | N27: N° Compras
B28: 1 | C28: 8325595 | D28: 1051345 | E28: 9376940 | F28: 0.88787973 | G28: 0.11212027 | H28: 6130295 | I28: 132400 | J28: 229750 | K28: 411700 | L28: 1036350 | M28: 130000 | N28: 61
B29: 2 | C29: 1355351 | D29: 30000 | E29: 1385351 | F29: 0.97834484 | G29: 0.021655162 | H29: 528586 | I29: 126240 | J29: 392505 | K29: 162100 | L29: 145920 | M29: 30000 | N29: 26
B30: 3 | C30: 4239440 | D30: 60500 | E30: 4299940 | F30: 0.98593004 | G30: 0.014069964 | H30: 1808790 | I30: 355500 | J30: 1047950 | K30: 970600 | L30: 56600 | M30: 60500 | N30: 40
B31: 4 | C31: 4457519 | D31: 30000 | E31: 4487519 | F31: 0.99331479 | G31: 0.0066852085 | H31: 2218844 | I31: 0 | J31: 256850 | K31: 140975 | L31: 1840850 | M31: 30000 | N31: 60
B32: 5 | C32: 8935184.1 | D32: 0 | E32: 8935184.1 | F32: 1 | G32: 0 | H32: 7713980 | I32: 524200 | J32: 247500 | K32: 386504.07 | L32: 63000 | M32: 0 | N32: 37
B33: 6 | C33: 434000 | D33: 90000 | E33: 524000 | F33: 0.82824427 | G33: 0.17175573 | H33: 0 | I33: 285000 | J33: 0 | K33: 0 | L33: 149000 | M33: 90000 | N33: 7
B34: 7 | C34: 2376803 | D34: 970900 | E34: 3347703 | F34: 0.70998025 | G34: 0.29001975 | H34: 2135215 | I34: 124155 | J34: 0 | K34: 73000 | L34: 29433 | M34: 970900 | N34: 29
B35: 8 | C35: 3875920 | D35: 762810.71 | E35: 4638730.7 | F35: 0.83555616 | G35: 0.16444384 | H35: 966050 | I35: 1392220 | J35: 389300 | K35: 29000 | L35: 1069350 | M35: 578112 | N35: 87
B36: 9 | C36: 11460335 | D36: 2763902 | E36: 14224237 | F36: 0.80569067 | G36: 0.19430933 | H36: 5707282 | I36: 793450 | J36: 1214910 | K36: 1723770 | L36: 1887973 | M36: 2280870 | N36: 80
B37: 10 | C37: 3218466 | D37: 464000 | E37: 3682466 | F37: 0.87399748 | G37: 0.12600252 | H37: 1387295 | I37: 208000 | J37: 441200 | K37: 918471 | L37: 263500 | M37: 464000 | N37: 45
B38: 11 | C38: 9568706 | D38: 47019700 | E38: 56588406 | F38: 0.16909305 | G38: 0.83090695 | H38: 4088560 | I38: 2802750 | J38: 1523150 | K38: 34000 | L38: 535300 | M38: 45390000 | N38: 92
B39: 12 | C39: 10515730 | D39: 1489300 | E39: 12005030 | F39: 0.87594367 | G39: 0.12405633 | H39: 7776020 | I39: 937770 | J39: 0 | K39: 83000 | L39: 0 | M39: 750000 | N39: 56
... B57: 30 | C57: 0 | D57: 0 | E57: 0 | F57: 0 | G57: 0 | H57: 0 | I57: 0 | J57: 0 | K57: 0 | L57: 0 | M57: 0 | N57: 0
B58: TOTAL MES | C58: 1.1635363e+08 | D58: 95329592 | E58: 2.1168322e+08 | F58: 0.5496592 | G58: 0.4503408 | H58: 67613773 | I58: 16098719 | J58: 7578719 | K58: 7593154.9 | L58: 10394477 | M58: 51133382 | N58: 1131
B59: PROMEDIO DIARIO | C59: 4155486.8 | D59: 3404628.3 | E59: 7560115.1 | F59: 0.5496592 | G59: 0.4503408 | H59: 2414777.6 | I59: 574954.25 | J59: 270668.53 | K59: 271184.11 | L59: 371231.34 | M59: 1826192.2 | N59: 40.392857
B60: MÁXIMO DIARIO (PICO) | C60: 11460335 | D60: 47019700 | E60: 56588406 | F60: - | G60: - | H60: 7776020 | I60: 3068320 | J60: 1523150 | K60: 1723770 | L60: 3115501.4 | M60: 45390000 | N60: 92
B61: MÍNIMO DIARIO | C61: 0 | D61: 0 | E61: 0 | F61: - | G61: - | H61: 0 | I61: 0 | J61: 0 | K61: 0 | L61: 0 | M61: 0 | N61: 0

Sheet Dashboard Ventas
B2: DASHBOARD EJECUTIVO DE VENTAS - SEPTIEMBRE 2026
B3: Restaurante Choclos y Asados La Finca - Seguimiento diario de facturación, volumen, mezcla de productos y rentabilidad
B5: TOTAL FACTURADO (GRAN TOTAL) | E5: VENTA NETA TOTAL (BASE) | G5: IMPOCONSUMO (8%) | I5: DESCUENTOS OTORGADOS | K5: TOTAL PLATOS / UNID. VENDIDAS | M5: PROMEDIO VENTA DIARIA (20 DÍAS) | O5: DÍA PICO FACTURACIÓN
B6: 174371548 | E6: 161455142 | G6: 12916408 | I6: 109958 | K6: 9362 | M6: 8718577.4 | O6: Día 6 ($20.262.800)
B9: 1. SEGUIMIENTO DIARIO DE VENTAS - SEPTIEMBRE 2026 | K9: 2. PARTICIPACIÓN Y FACTURACIÓN POR CATEGORÍA
B10: Día | C10: Fecha | D10: Platos / Unid. | E10: Venta Neta ($) | F10: Impoconsumo ($) | G10: Gran Total ($) | H10: Ticket / Ítem | I10: % Mes | K10: Categoría de Venta | L10: Unid. Vendidas | M10: Venta Neta ($) | N10: Gran Total ($) | O10: Ticket / Ítem | P10: % Facturación
B11: 1 | C11: 01/09/2026 | D11: 411 | E11: 6282219 | F11: 502578 | G11: 6784797 | H11: 16508.022 | I11: 0.03891 | K11: Platos Fuertes / Carnes | L11: 2737 | M11: 78987200 | N11: 85306163 | O11: 31167.761 | P11: 0.48922066
B12: 2 | C12: 02/09/2026 | D12: 374 | E12: 5447496 | F12: 435805 | G12: 5883301 | H12: 15730.751 | I12: 0.033740029 | K12: Especialidades Típicas | L12: 2170 | M12: 46528029 | N12: 50250270 | O12: 23156.806 | P12: 0.2881793
B13: 3 | C13: 03/09/2026 | D13: 408 | E13: 5692967 | F13: 455433 | G13: 6148400 | H13: 15069.608 | I13: 0.03526034 | K13: Bebidas | L13: 2196 | M13: 15049167 | N13: 16253094 | O13: 7401.2268 | P13: 0.093209553
B14: 4 | C14: 04/09/2026 | D14: 400 | E14: 5913241 | F14: 473060 | G14: 6386301 | H14: 15965.753 | I14: 0.036624673 | K14: Pescados y Mariscos | L14: 350 | M14: 13269959 | N14: 14331561 | O14: 40947.317 | P14: 0.082189791
B15: 5 | C15: 05/09/2026 | D15: 519 | E15: 10334818 | F15: 826782 | G15: 11161600 | H15: 21505.973 | I15: 0.064010443 | K15: Acompañamientos y Adicionales | L15: 1154 | M15: 5645737 | N15: 6097406 | O15: 5283.714 | P15: 0.034967895
B16: 6 | C16: 06/09/2026 | D16: 842 | E16: 18761854 | F16: 1500947 | G16: 20262801 | H16: 24065.084 | I16: 0.11620474 | K16: Sopas y Entradas | L16: 388 | M16: 1635341 | N16: 1766168 | O16: 4551.9794 | P16: 0.010128763
B17: 7 | C17: 07/09/2026 | D17: 349 | E17: 5144910 | F17: 411590 | G17: 5556500 | H17: 15921.203 | I17: 0.031865864 | K17: Otros / Empaques | L17: 367 | M17: 339709 | N17: 366886 | O17: 999.68937 | P17: 0.0021040474
B18: 8 | C18: 08/09/2026 | D18: 402 | E18: 5927405 | F18: 474199 | G18: 6401604 | H18: 15924.388 | I18: 0.036712434 | K18: TOTAL CATEGORÍAS | L18: 9362 | M18: 161455142 | N18: 174371548 | O18: 18625.459 | P18: 1
B19: 9 | C19: 09/09/2026 | D19: 401 | E19: 6138790 | F19: 491108 | G19: 6629898 | H19: 16533.411 | I19: 0.038021673
B20: 10 | C20: 10/09/2026 | D20: 418 | E20: 6117773 | F20: 489425 | G20: 6607198 | H20: 15806.694 | I20: 0.037891491
B21: 11 | C21: 11/09/2026 | D21: 390 | E21: 5473329 | F21: 437870 | G21: 5911199 | H21: 15156.921 | I21: 0.03390002 | K21: 3. TOP 20 PRODUCTOS MÁS VENDIDOS (RANKING DE FACTURACIÓN)
B22: 12 | C22: 12/09/2026 | D22: 487 | E22: 9342039 | F22: 747361 | G22: 10089400 | H22: 20717.454 | I22: 0.057861504 | K22: Rank | L22: Código | M22: Producto | N22: Categoría | O22: Unid. Vendidas | P22: Gran Total ($) | Q22: % Venta Total
B23: 13 | C23: 13/09/2026 | D23: 727 | E23: 15770930 | F23: 1261670 | G23: 17032600 | H23: 23428.611 | I23: 0.097679927 | K23: #1 | L23: 119 | M23: Paisa especial | N23: Especialidades Típicas | O23: 231 | P23: 11088000 | Q23: 0.063588356
B24: 14 | C24: 14/09/2026 | D24: 310 | E24: 4323242 | F24: 345858 | G24: 4669100 | H24: 15061.613 | I24: 0.026776731 | K24: #2 | L24: 233 | M24: Frijolada chicha jun | N24: Especialidades Típicas | O24: 462 | P24: 9268833 | Q24: 0.05315565
B25: 15 | C25: 15/09/2026 | D25: 420 | E25: 6091664 | F25: 487336 | G25: 6579000 | H25: 15664.286 | I25: 0.037729779 | K25: #3 | L25: 117 | M25: Sobre domingo | N25: Platos Fuertes / Carnes | O25: 143 | P25: 6435000 | Q25: 0.036903956
B26: 16 | C26: 16/09/2026 | D26: 359 | E26: 4652685 | F26: 372215 | G26: 5024900 | H26: 13996.936 | I26: 0.028817201 | K26: #4 | L26: 93 | M26: Paisa economico | N26: Especialidades Típicas | O26: 271 | P26: 5958334 | Q26: 0.034170334
B27: 17 | C27: 17/09/2026 | D27: 403 | E27: 5916159 | F27: 473292 | G27: 6389450 | H27: 15854.715 | I27: 0.036642733 | K27: #5 | L27: 118 | M27: Lengua domingo | N27: Platos Fuertes / Carnes | O27: 131 | P27: 5895000 | Q27: 0.033807121
B28: 18 | C28: 18/09/2026 | D28: 380 | E28: 5661944 | F28: 452956 | G28: 6114899 | H28: 16091.839 | I28: 0.035068215 | K28: #6 | L28: 113 | M28: Tamal | N28: Especialidades Típicas | O28: 219 | P28: 5256000 | Q28: 0.030142532
B29: 19 | C29: 19/09/2026 | D29: 521 | E29: 10599814 | F29: 847986 | G29: 11447800 | H29: 21972.745 | I29: 0.065651766 | K29: #7 | L29: 88 | M29: Junior gallina | N29: Platos Fuertes / Carnes | O29: 141 | P29: 5005500 | Q29: 0.028705945
B30: 20 | C30: 20/09/2026 | D30: 841 | E30: 17861863 | F30: 1428937 | G30: 19290800 | H30: 22937.931 | I30: 0.11063043 | K30: #8 | L30: 215 | M30: Super de cerdo | N30: Platos Fuertes / Carnes | O30: 120 | P30: 4844500 | Q30: 0.027782629
B31: 21 | C31: 21/09/2026 | D31: 0 | E31: 0 | F31: 0 | G31: 0 | H31: 0 | I31: 0 | K31: #9 | L31: 44 | M31: Costilla c san luis | N31: Platos Fuertes / Carnes | O31: 150 | P31: 4575000 | Q31: 0.026237079
B32: 22 | C32: 22/09/2026 | D32: 0 | E32: 0 | F32: 0 | G32: 0 | H32: 0 | I32: 0 | K32: #10 | L32: 223 | M32: Promo cazuela | N32: Platos Fuertes / Carnes | O32: 56 | P32: 4200000 | Q32: 0.024086498
B33: 23 | C33: 23/09/2026 | D33: 0 | E33: 0 | F33: 0 | G33: 0 | H33: 0 | I33: 0 | K33: #11 | L33: 109 | M33: Limonada natural 1l | N33: Bebidas | O33: 283 | P33: 3962001 | Q33: 0.022721602
B34: 24 | C34: 24/09/2026 | D34: 0 | E34: 0 | F34: 0 | G34: 0 | H34: 0 | I34: 0 | K34: #12 | L34: 87 | M34: Cazuela frijol | N34: Especialidades Típicas | O34: 94 | P34: 3807000 | Q34: 0.02183269
... B40: 30 | C40: 30/09/2026 | D40: 0 | E40: 0 | F40: 0 | G40: 0 | H40: 0 | I40: 0 | K40: #18 | L40: 104 | M40: Bandeja sola | N40: Especialidades Típicas | O40: 162 | P40: 2796170 | Q40: 0.016035701
B41: TOTAL MES (DÍAS 1-30) | D41: 9362 | E41: 161455142 | F41: 12916408 | G41: 174371548 | H41: 18625.459 | I41: 1 | K41: #19 | L41: 41 | M41: Churrasco 400 gr apr | N41: Platos Fuertes / Carnes | O41: 51 | P41: 2703000 | Q41: 0.015501382
B42: PROMEDIO DIARIO | D42: 468.1 | E42: 8072757.1 | F42: 645820.4 | G42: 8718577.4 | H42: 18625.459 | I42: - | K42: #20 | L42: 214 | M42: Super de pollo | N42: Platos Fuertes / Carnes | O42: 65 | P42: 2632500 | Q42: 0.015097073
B43: MÁXIMO DIARIO (PICO) | D43: 842 | E43: 18761854 | F43: 1500947 | G43: 20262801 | H43: - | I43: - | K43: SUBTOTAL TOP 20 PRODUCTOS | O43: 3129 | P43: 94583770 | Q43: 0.54242662

Sheet Dashboard Carnes
B2: DASHBOARD Y SEGUIMIENTO DE CARNES - SEPTIEMBRE 2026
B3: Control analítico de cortes, kilogramos comprados, costos unitarios y participación de gasto
B5: TOTAL INVERSIÓN CARNES | D5: TOTAL KILOGRAMOS | F5: COSTO PROM. / KG | G5: N° COMPRAS | H5: % TOTAL RESTAURANTE
B6: 50250945 | D6: 2265.065 | F6: 22185.211 | G6: 133 | H6: 0.29509801
B8: 1. SEGUIMIENTO DIARIO DE COMPRAS DE CARNE | I8: 2. SEGUIMIENTO DETALLADO DÍA A DÍA - REGISTRO CRONOLÓGICO DE COMPRAS DE CARNES
B9: Día | C9: Total Comprado ($) | D9: Kilogramos (Kg) | E9: Costo Prom. ($/Kg) | F9: % del Mes | G9: N° Compras | I9: Día | J9: N° Comprobante / Factura | K9: Ítem / Corte (Nombre Exacto) | L9: Descripción Original / Proveedor | M9: Cantidad (kg) | N9: Costo Unitario | O9: Vr. Total Compra
B10: 1 | C10: 6130295 | D10: 277.28 | E10: 22108.681 | F10: 0.090666365 | G10: 13 | I10: 1 | J10: 01FZ70896 | K10: Pezuña | L10: PEZUÑA CERDO A GRANEL (Supertiendas Cañaveral - 01FZ70896) | M10: 4.755 | N10: 7900 | O10: ='Detalle Compras Septiembre 2026'!G2 -> 37565
B11: 2 | C11: 528586 | D11: 47.234 | E11: 11190.795 | F11: 0.0078177267 | G11: 4 | I11: 1 | J11: 01FZ70896 | K11: Pezuña | L11: PEZUÑA CERDO A GRANEL (Supertiendas Cañaveral - 01FZ70896) | M11: 3.365 | N11: 8915.3 | O11: ='Detalle Compras Septiembre 2026'!G3 -> 30000
B12: 3 | C12: 1808790 | D12: 65.46 | E12: 27631.989 | F12: 0.026751798 | G12: 9 | I12: 1 | J12: FAC-188 | K12: Bagre de mar | L12: BAGRE DE MAR (Gabriel Ramirez Cubillos - FAC-188) | M12: 20 | N12: 16500 | O12: ='Detalle Compras Septiembre 2026'!G7 -> 330000
B13: 4 | C13: 2218844 | D13: 106.76 | E13: 20783.477 | F13: 0.03281645 | G13: 8 | I13: 1 | J13: FAC-916 | K13: Filete de pollo x 120 | L13: Filete pollo 110g (Alexis Valencia - Factura 916) | M13: 4.58 | N13: 18500 | O13: ='Detalle Compras Septiembre 2026'!G8 -> 84730
B14: 5 | C14: 7713980 | D14: 316.15 | E14: 24399.747 | F14: 0.11408889 | G14: 9 | I14: 1 | J14: FAC-916 | K14: Filete de pollo x 350 | L14: Filete pollo 350g (Alexis Valencia - Factura 916) | M14: 15.1 | N14: 18500 | O14: ='Detalle Compras Septiembre 2026'!G9 -> 279350
B15: 6 | C15: 0 | D15: 0 | E15: 0 | F15: 0 | G15: 0 | I15: 1 | J15: FVE-121 | K15: Salmon | L15: Filete de Salmon Grande (Frio Sabor FVE-121) | M15: 9.87 | N15: 55000 | O15: ='Detalle Compras Septiembre 2026'!G10 -> 542850
B16: 7 | C16: 2135215 | D16: 100.007 | E16: 21350.656 | F16: 0.031579587 | G16: 9 | I16: 1 | J16: FVE-121 | K16: Tilapia y truchas | L16: Tilapia Roja (Frio Sabor FVE-121) | M16: 19.81 | N16: 18000 | O16: ='Detalle Compras Septiembre 2026'!G11 -> 356580
B17: 8 | C17: 966050 | D17: 67.25 | E17: 14365.056 | F17: 0.014287769 | G17: 11 | I17: 1 | J17: RCM-01-Sep-2026 | K17: Tilapia y truchas | L17: 6 lbs cabeza Tilapia (Recibo Caja Menor 01-Sep-2026) | M17: 6 | N17: 3666.67 | O17: ='Detalle Compras Septiembre 2026'!G17 -> 22000
B18: 9 | C18: 5707282 | D18: 325.94 | E18: 17510.223 | F18: 0.084410051 | G18: 12 | I18: 1 | J18: YP24140 | K18: Costilla de cerdo especial | L18: COSTILLA DE CERDO IBP 244M (Carnes Los Monos - YP24140) | M18: 28.6 | N18: 14900 | O18: ='Detalle Compras Septiembre 2026'!G23 -> 426140
B19: 10 | C19: 1387295 | D19: 115.505 | E19: 12010.692 | F19: 0.020517935 | G19: 7 | I19: 1 | J19: YP24140 | K19: Lengua de res | L19: LENGUA DE RES IMP X KL (Carnes Los Monos - YP24140) | M19: 27.65 | N19: 23900 | O19: ='Detalle Compras Septiembre 2026'!G24 -> 660835
B20: 11 | C20: 4088560 | D20: 68.97 | E20: 59280.267 | F20: 0.060469337 | G20: 9 | I20: 1 | J20: YP24140 | K20: Sobaco | L20: SOBACO (Carnes Los Monos - YP24140) | M20: 28.7 | N20: 25900 | O20: ='Detalle Compras Septiembre 2026'!G25 -> 743330
B21: 12 | C21: 7776020 | D21: 297.35 | E21: 26151.068 | F21: 0.11500645 | G21: 13 | I21: 1 | J21: YP24140 | K21: Sobrebarriga delgada | L21: SOBREBARRIGA DELGADA (Carnes Los Monos - YP24140) | M21: 18.5 | N21: 34500 | O21: ='Detalle Compras Septiembre 2026'!G26 -> 638250
B22: 13 | C22: 866150.02 | D22: 86.9 | E22: 9967.2039 | F22: 0.01281026 | G22: 6 | I22: 1 | J22: YP24152 | K22: Tocino barril | L22: TOCINETA BARRIL (Carnes Los Monos - YP24152) | M22: 90.35 | N22: 21900 | O22: ='Detalle Compras Septiembre 2026'!G27 -> 1978665
B23: 14 | C23: 2403203.8 | D23: 112.894 | E23: 21287.259 | F23: 0.03554311 | G23: 7 | I23: SUBTOTAL DÍA 1 (13 compras) | M23: =SUM(M10:M22) -> 277.28 | N23: =IF(M23>0, O23/M23, 0) -> 22108.681 | O23: =SUM(O10:O22) -> 6130295
B24: 15 | C24: 234700 | D24: 2 | E24: 117350 | F24: 0.0034711863 | G24: 2 | I24: 2 | J24: FAC-917 | K24: Pernil de pollo | L24: Pernil pollo campo (Alexis Valencia - Factura 917) | M24: 34.7 | N24: 7500 | O24: ='Detalle Compras Septiembre 2026'!G46 -> 260250
B25: 16 | C25: 1322675 | D25: 31.905 | E25: 41456.668 | F25: 0.019562213 | G25: 5 | I25: 2 | J25: DESP-0444 | K25: Higado | L25: HIGADO DE RES (Poblado Despacho 0444) | M25: 5 | N25: 21500 | O25: ='Detalle Compras Septiembre 2026'!G47 -> 107500
B26: 17 | C26: 5398439 | D26: 261.18 | E26: 20669.42 | F26: 0.079842298 | G26: 12 | I26: 2 | J26: 03FH104321 | K26: Alas de pollo | L26: ALAS POLLO MACPOLLO CONGELADO (Supertiendas Cañaveral - 03FH104321) | M26: 2.77 | N26: 19900 | O26: ='Detalle Compras Septiembre 2026'!G51 -> 55123
B27: 18 | C27: 1106000 | D27: 65 | E27: 17015.385 | F27: 0.016357614 | G27: 2 | I27: 2 | J27: 03FH104321 | K27: Alas de pollo | L27: ALAS POLLO MACPOLLO CONGELADO (Supertiendas Cañaveral - 03FH104321) | M27: 4.764 | N27: 22190 | O27: ='Detalle Compras Septiembre 2026'!G52 -> 105713
B28: 19 | C28: 5243054 | D28: 18970.47 | E28: 276.37976 | F28: 0.077544172 | G28: 7 | I28: SUBTOTAL DÍA 2 (4 compras) | M28: =SUM(M24:M27) -> 47.234 | N28: =IF(M28>0, O28/M28, 0) -> 11190.795 | O28: =SUM(O24:O27) -> 528586
B29: 20 | C29: 0 | D29: 0 | E29: 0 | F29: 0 | G29: 0 | I29: 3 | J29: FE01576 | K29: Caderita | L29: CADERITA DE RES (MYC - FE01576) | M29: 5.96 | N29: 34000 | O29: ='Detalle Compras Septiembre 2026'!G80 -> 202640
B30: 21 | C30: 0 | D30: 0 | E30: 0 | F30: 0 | G30: 0 | I30: 3 | J30: FE01576 | K30: Callo | L30: CALLO DE RES (MYC - FE01576) | M30: 7 | N30: 20000 | O30: ='Detalle Compras Septiembre 2026'!G81 -> 140000
B31: 22 | C31: 2693444 | D31: 140.194 | E31: 19212.263 | F31: 0.03983573 | G31: 12 | I31: 3 | J31: FE01570 | K31: Higado | L31: HIGADO DE RES (MYC - FE01570) | M31: 5.8 | N31: 22000 | O31: ='Detalle Compras Septiembre 2026'!G82 -> 127600
B32: 23 | C32: 3368820 | D32: 143.155 | E32: 23532.674 | F32: 0.049824464 | G32: 5 | I32: 3 | J32: FE01570 | K32: Lomo viche | L32: LOMO VICHE ESPECIAL DE RES (MYC - FE01570) | M32: 7.35 | N32: 54000 | O32: ='Detalle Compras Septiembre 2026'!G83 -> 396900
B33: 24 | C33: 168188 | D33: 18.432 | E33: 9124.783 | F33: 0.0024874814 | G33: 2 | I33: 3 | J33: FE01569 | K33: Caderita | L33: CADERITA DE RES (MYC - FE01569) | M33: 4.05 | N33: 33000 | O33: ='Detalle Compras Septiembre 2026'!G84 -> 133650
B34: 25 | C34: 2061250 | D34: 103.45 | E34: 19925.085 | F34: 0.030485653 | G34: 8 | I34: 3 | J34: FE01569 | K34: Costilla Especial | L34: COSTILLA ESPECIAL DE RES (MYC - FE01569) | M34: 10.3 | N34: 20000 | O34: ='Detalle Compras Septiembre 2026'!G85 -> 206000
B35: 26 | C35: 1966882 | D35: 17598.63 | E35: 111.76336 | F35: 0.029089961 | G35: 6 | I35: 3 | J35: 0000006666 | K35: Chorizo | L35: CHORIZO COCTELERO 4 PAQ (Carnicos Montero FAC-0000006666) | M35: 4 | N35: 48000 | O35: ='Detalle Compras Septiembre 2026'!G92 -> 192000
B36: 27 | C36: 320050 | D36: 17.3 | E36: 18500 | F36: 0.004733503 | G36: 1 | I36: 3 | J36: 0000006666 | K36: Chorizo | L36: CHORIZO PREMIUM 1 PAQ (Carnicos Montero FAC-0000006666) | M36: 1 | N36: 46000 | O36: ='Detalle Compras Septiembre 2026'!G93 -> 46000
B37: 28 | C37: 0 | D37: 0 | E37: 0 | F37: 0 | G37: 0 | I37: 3 | J37: FE1-49657 | K37: Costilla de cerdo | L37: COSTILLA CERDO ESP CR (BS) X 4 KG (ARMAR ALIMENTOS S.A.S.) | M37: 20 | N37: 18200 | O37: ='Detalle Compras Septiembre 2026'!G504 -> 364000
B38: 29 | C38: 0 | D38: 0 | E38: 0 | F38: 0 | G38: 0 | I38: SUBTOTAL DÍA 3 (9 compras) | M38: =SUM(M29:M37) -> 65.46 | N38: =IF(M38>0, O38/M38, 0) -> 27631.989 | O38: =SUM(O29:O37) -> 1808790
B39: 30 | C39: 0 | D39: 0 | E39: 0 | F39: 0 | G39: 0 | I39: 4 | J39: FEBF-33 | K39: Lomo de cerdo | L39: LOMO DE CERDO (Fabian Bonilla - FEBF-33) | M39: 26.5 | N39: 19500 | O39: ='Detalle Compras Septiembre 2026'!G142 -> 516750
B40: TOTAL MES | C40: 67613773 | D40: 39339.416 | E40: 1718.7284 | F40: 1 | G40: 179 | I40: 4 | J40: FAC-920 | K40: Filete de pollo x 350 | L40: Filete pollo 350g (Alexis Valencia - Factura 920) | M40: 23.5 | N40: 18500 | O40: ='Detalle Compras Septiembre 2026'!G143 -> 434750
I41: 4 | J41: FAC-8118 | K41: Morcilla | L41: 10 lb Libra de morcilla (La Morcilla Jamundeña Factura 8118) | M41: 10 | N41: 10000 | O41: ='Detalle Compras Septiembre 2026'!G144 -> 100000
I42: 4 | J42: 05FZ91332 | K42: Pechuga macpollo | L42: PECHUGA MACPOLLO BLANCO REFRI MARIN GK (Supertiendas Canaveral 05FZ91332) | M42: 3.095 | N42: 13980 | O42: ='Detalle Compras Septiembre 2026'!G147 -> 43269
I43: 4 | J43: FVE 130 | K43: Tilapia Roja | L43: Tilapia Roja (Gerson Alexander Valencia Angel) | M43: 20.74 | N43: 18000 | O43: ='Detalle Compras Septiembre 2026'!G529 -> 373320
I44: 4 | J44: FVE 130 | K44: Filete de Salmón Grande | L44: Filete de Salmon Grande (Gerson Alexander Valencia Angel) | M44: 6.765 | N44: 55000 | O44: ='Detalle Compras Septiembre 2026'!G530 -> 372075
I45: 4 | J45: FVE 130 | K45: Trucha Arcoíris | L45: Trucha arcoiris (Gerson Alexander Valencia Angel) | M45: 9.16 | N45: 23000 | O45: ='Detalle Compras Septiembre 2026'!G531 -> 210680
I46: 4 | J46: FVE 130 | K46: Mix de Mariscos | L46: Mix de Mariscos (Gerson Alexander Valencia Angel) | M46: 7 | N46: 24000 | O46: ='Detalle Compras Septiembre 2026'!G532 -> 168000
I47: SUBTOTAL DÍA 4 (8 compras) | M47: =SUM(M39:M46) -> 106.76 | N47: =IF(M47>0, O47/M47, 0) -> 20783.477 | O47: =SUM(O39:O46) -> 2218844
I48: 5 | J48: YP24244 | K48: Camaron precocido | L48: CAMARON DE CULTIVO PRECOCIDO 91-110P (Carnes Los Monos - YP24244) | M48: 19.7 | N48: 22900 | O48: ='Detalle Compras Septiembre 2026'!G149 -> 451130
I49: 5 | J49: YP24244 | K49: Costilla de res | L49: COSTILLA DE RES DELANTERA (Carnes Los Monos - YP24244) | M49: 26.1 | N49: 18500 | O49: ='Detalle Compras Septiembre 2026'!G150 -> 482850
I50: 5 | J50: YP24244 | K50: Costilla san luis jr | L50: COSTILLA SAN LUIS JUNIOR T/M (Carnes Los Monos - YP24244) | M50: 30.66 | N50: 18900 | O50: ='Detalle Compras Septiembre 2026'!G151 -> 579474
I51: 5 | J51: YP24244 | K51: Lomo de caracho | L51: LOMO CARACHO PORCIONADO PARRILLA (Carnes Los Monos - YP24244) | M51: 21.55 | N51: 42000 | O51: ='Detalle Compras Septiembre 2026'!G152 -> 905100
I52: 5 | J52: YP24244 | K52: Punta de anca | L52: PUNTA DE ANCA IMP PORC. PARRILLA (Carnes Los Monos - YP24244) | M52: 18 | N52: 44000 | O52: ='Detalle Compras Septiembre 2026'!G153 -> 792000
I53: 5 | J53: YP24244 | K53: Sobaco | L53: SOBACO (Carnes Los Monos - YP24244) | M53: 20.24 | N53: 25900 | O53: ='Detalle Compras Septiembre 2026'!G154 -> 524216
I54: 5 | J54: YP24244 | K54: Sobrebarriga delgada | L54: SOBREBARRIGA DELGADA (Carnes Los Monos - YP24244) | M54: 9 | N54: 34500 | O54: ='Detalle Compras Septiembre 2026'!G155 -> 310500
I55: 5 | J55: YP24244 | K55: Tocineta barril | L55: TOCINETA BARRIL (Carnes Los Monos - YP24244) | M55: 150.9 | N55: 21900 | O55: ='Detalle Compras Septiembre 2026'!G156 -> 3304710
I56: 5 | J56: FE1-49726 | K56: Costilla de cerdo | L56: COSTILLA CERDO ESP CR (BS) X 4 KG (ARMAR ALIMENTOS S.A.S.) | M56: 20 | N56: 18200 | O56: ='Detalle Compras Septiembre 2026'!G505 -> 364000
I57: SUBTOTAL DÍA 5 (9 compras) | M57: =SUM(M48:M56) -> 316.15 | N57: =IF(M57>0, O57/M57, 0) -> 24399.747 | O57: =SUM(O48:O56) -> 7713980
I58: 7 | J58: SEV-07SEP | K58: Espinazo de cerdo | L58: ESPINAZO DE CERDO A GRANEL (Agropecuaria La Sevillana SAS) | M58: 3.32 | N58: 8974.59 | O58: ='Detalle Compras Septiembre 2026'!G180 -> 29795.64
I59: 7 | J59: SEV-07SEP | K59: Pezuña | L59: PEZUNA GRANEL (Agropecuaria La Sevillana SAS) | M59: 3.93 | N59: 7984.07 | O59: ='Detalle Compras Septiembre 2026'!G181 -> 31377.4
I60: 7 | J60: REM-07-Sep-2026 | K60: Gallina | L60: GALLINAS GIGANTES 9 UND (Remision s/n 07-09-2026) | M60: 38.6 | N60: 11500 | O60: ='Detalle Compras Septiembre 2026'!G182 -> 443900
I61: 7 | J61: REM-07-09-2026 | K61: Morcilla | L61: Combo Morcilla CL (Remision 07-09-2026) | M61: 1 | N61: 130000 | O61: ='Detalle Compras Septiembre 2026'!G183 -> 130000
I62: 7 | J62: MY8683 | K62: Morrillo | L62: MORRILLO DE RES (Carnes Los Monos - MY8683) | M62: 5.592 | N62: 26900 | O62: ='Detalle Compras Septiembre 2026'!G186 -> 150425
I63: 7 | J63: MY8683 | K63: Sobaco | L63: SOBACO (Carnes Los Monos - MY8683) | M63: 21.61 | N63: 25900 | O63: ='Detalle Compras Septiembre 2026'!G187 -> 559699
I64: 7 | J64: MY8683 | K64: Sobrebarriga delgada | L64: SOBREBARRIGA DELGADA (Carnes Los Monos - MY8683) | M64: 20.565 | N64: 34500 | O64: ='Detalle Compras Septiembre 2026'!G188 -> 709493
I65: 7 | J65: 11FH128829 | K65: Alas de pollo | L65: ALAS MACPOLLO CAMPO C/COS MARIN A GRAN (Supertiendas Cañaveral 11FH128829) | M65: 3.39 | N65: 17500 | O65: ='Detalle Compras Septiembre 2026'!G197 -> 59325
I66: 7 | J66: 11FH128829 | K66: Mortadela | L66: 2 MORTADELA RICA*450g (Supertiendas Cañaveral 11FH128829) | M66: 2 | N66: 10600 | O66: ='Detalle Compras Septiembre 2026'!G198 -> 21200
I67: SUBTOTAL DÍA 7 (9 compras) | M67: =SUM(M58:M66) -> 100.007 | N67: =IF(M67>0, O67/M67, 0) -> 21350.656 | O67: =SUM(O58:O66) -> 2135215
I68: 8 | J68: REM-08-09-2026 | K68: Filete de pollo x 350 | L68: Filete x 350g - 40 und (Alexis Valencia Remision 08-09-2026) | M68: 14.1 | N68: 18500 | O68: ='Detalle Compras Septiembre 2026'!G244 -> 260850
I69: 8 | J69: FEBF-34 / REM-08-09-2026 | K69: Lomo de cerdo | L69: Lomo cerdo (Pappyer Remision 08-09-2026) | M69: 13.6 | N69: 19500 | O69: ='Detalle Compras Septiembre 2026'!G245 -> 265200
I70: 8 | J70: REM-08-09-2026 | K70: Pernil de pollo | L70: Perniles Campo - 25 und (Alexis Valencia Remision 08-09-2026) | M70: 14.9 | N70: 7500 | O70: ='Detalle Compras Septiembre 2026'!G246 -> 111750
I71: 8 | J71: FE01598 / DESP-0493 | K71: Caderita | L71: Caderita (Poblado Despacho 0493) | M71: 5 | N71: 33000 | O71: ='Detalle Compras Septiembre 2026'!G249 -> 165000
I72: 8 | J72: FE01598 / DESP-0493 | K72: Pezuña | L72: Pezuña (Poblado Despacho 0493) | M72: 8.65 | N72: 7000 | O72: ='Detalle Compras Septiembre 2026'!G250 -> 60550
I73: 8 | J73: CUADERNO CAJA / NO REGISTRADO | K73: Visceras Domicilios (Neymar) | L73: Visceras Domicilios (Neymar) | M73: 1 | N73: 72200 | O73: ='Detalle Compras Septiembre 2026'!G255 -> 72200
I74: 8 | J74: 08FH337898 | K74: Víscera de pollo | L74: VISCERA BUCANERO*und BOLSA (SUPERTIENDAS CAÑAVERAL S.A.S.) | M74: 2 | N74: 3050 | O74: ='Detalle Compras Septiembre 2026'!G558 -> 6100
I75: 8 | J75: 08FH337898 | K75: Víscera de pollo | L75: VISCERA BUCANERO*und BOLSA (SUPERTIENDAS CAÑAVERAL S.A.S.) | M75: 2 | N75: 3050 | O75: ='Detalle Compras Septiembre 2026'!G559 -> 6100
I76: 8 | J76: 08FH337898 | K76: Víscera de pollo | L76: VISCERA BUCANERO*und BOLSA (SUPERTIENDAS CAÑAVERAL S.A.S.) | M76: 2 | N76: 3050 | O76: ='Detalle Compras Septiembre 2026'!G560 -> 6100
I77: 8 | J77: 08FH337898 | K77: Víscera de pollo | L77: VISCERA BUCANERO*und BOLSA (SUPERTIENDAS CAÑAVERAL S.A.S.) | M77: 2 | N77: 3050 | O77: ='Detalle Compras Septiembre 2026'!G561 -> 6100
I78: 8 | J78: 08FH337898 | K78: Víscera de pollo | L78: VISCERA BUCANERO*und BOLSA (SUPERTIENDAS CAÑAVERAL S.A.S.) | M78: 2 | N78: 3050 | O78: ='Detalle Compras Septiembre 2026'!G562 -> 6100
I79: SUBTOTAL DÍA 8 (11 compras) | M79: =SUM(M68:M78) -> 67.25 | N79: =IF(M79>0, O79/M79, 0) -> 14365.056 | O79: =SUM(O68:O78) -> 966050
I80: 9 | J80: YP24314 | K80: Camaron precocido | L80: CAMARON DE CULTIVO PRECOCIDO 91-110P (Carnes Los Monos - YP24314) | M80: 20.2 | N80: 22900 | O80: ='Detalle Compras Septiembre 2026'!G274 -> 462580
I81: 9 | J81: YP24314 | K81: Costilla de cerdo especial | L81: COSTILLA DE CERDO IBP 244L (Carnes Los Monos - YP24314) | M81: 28.6 | N81: 15900 | O81: ='Detalle Compras Septiembre 2026'!G275 -> 454740
I82: 9 | J82: YP24314 | K82: Lengua de res | L82: LENGUA DE RES IMP X KL (Carnes Los Monos - YP24314) | M82: 24.7 | N82: 23900 | O82: ='Detalle Compras Septiembre 2026'!G276 -> 590330
I83: 9 | J83: YP24314 | K83: Sobaco | L83: SOBACO (Carnes Los Monos - YP24314) | M83: 22.18 | N83: 25900 | O83: ='Detalle Compras Septiembre 2026'!G277 -> 574462
I84: 9 | J84: YP24314 | K84: Tocineta barril | L84: TOCINETA BARRIL (Carnes Los Monos - YP24314) | M84: 68.7 | N84: 21900 | O84: ='Detalle Compras Septiembre 2026'!G278 -> 1504530
I85: 9 | J85: YP24314 | K85: Trozos e pechuga | L85: TROZOS DE PECHUGA (Carnes Los Monos - YP24314) | M85: 17.26 | N85: 11500 | O85: ='Detalle Compras Septiembre 2026'!G279 -> 198490
I86: 9 | J86: REM-09-Sep-2026 | K86: Gallina | L86: GALLINAS GIGANTES 9 UND (Remision s/n 09.09.2026) | M86: 38.4 | N86: 11000 | O86: ='Detalle Compras Septiembre 2026'!G290 -> 422400
I87: 9 | J87: REM-09-09-2026 | K87: Filete de pollo x 350 | L87: Filete x 350g - 40 und (Alexis Valencia Remision 09-09-2026) | M87: 13.6 | N87: 18500 | O87: ='Detalle Compras Septiembre 2026'!G292 -> 251600
I88: 9 | J88: REM-09-09-2026 | K88: Pernil de pollo | L88: Pernil Camp. (Alexis Valencia Remision 09-09-2026) | M88: 43.4 | N88: 7500 | O88: ='Detalle Compras Septiembre 2026'!G293 -> 325500
I89: 9 | J89: FE01591 / FAC-2860 | K89: Lomo de cerdo | L89: Lomo de Cerdo (Carnes de Res y Cerdo Factura 2860) | M89: 27.9 | N89: 18500 | O89: ='Detalle Compras Septiembre 2026'!G312 -> 516150
I90: 9 | J90: FAC191 | K90: Bagre de mar | L90: BAGRE DE MAR (Acuatica Factura FAC 191) | M90: 20 | N90: 16500 | O90: ='Detalle Compras Septiembre 2026'!G313 -> 330000
I91: 9 | J91: CUADERNO CAJA / NO REGISTRADO | K91: Espinazo, Cuchuco, Salchicha Principal (Johanna) | L91: Espinazo, Cuchuco, Salchicha Principal (Johanna) | M91: 1 | N91: 76500 | O91: ='Detalle Compras Septiembre 2026'!G317 -> 76500
I92: SUBTOTAL DÍA 9 (12 compras) | M92: =SUM(M80:M91) -> 325.94 | N92: =IF(M92>0, O92/M92, 0) -> 17510.223 | O92: =SUM(O80:O91) -> 5707282
I93: 10 | J93: REM-10-Sep-2026 | K93: Pernil de pollo | L93: PERNIL POLLO (Alexis Valencia Remision 10-09-2026) | M93: 87.3 | N93: 7500 | O93: ='Detalle Compras Septiembre 2026'!G334 -> 654750
I94: 10 | J94: RCM-10-Sep-2026-6 | K94: Chorizo | L94: CHORIZOS (Recibo Caja Menor 10/09/26) | M94: 1 | N94: 18000 | O94: ='Detalle Compras Septiembre 2026'!G336 -> 18000
I95: 10 | J95: RCM-10-Sep-2026-6 | K95: Costilla | L95: COSTILLA (Recibo Caja Menor 10/09/26) | M95: 1 | N95: 5000 | O95: ='Detalle Compras Septiembre 2026'!G337 -> 5000
I96: 10 | J96: 06FZ47115 | K96: Mortadela | L96: MORTADELA RICA 1 UN (Supertiendas Canaveral 06FZ47115) | M96: 1 | N96: 8950 | O96: ='Detalle Compras Septiembre 2026'!G362 -> 8950
I97: 10 | J97: FE01599 / 0515 | K97: Lomo de cerdo | L97: LOMO CERDO (Carnes El Poblado Despacho 0515) | M97: 16.15 | N97: 18500 | O97: ='Detalle Compras Septiembre 2026'!G364 -> 298775
I98: 10 | J98: FE01599 / 0515 | K98: Lomo viche | L98: LOMO VICHE (Carnes El Poblado Despacho 0515) | M98: 4.905 | N98: 54000 | O98: ='Detalle Compras Septiembre 2026'!G365 -> 264870
I99: 10 | J99: FE01592 | K99: Caderita de res | L99: CADERITA DE RES (DISTRIBUIDORA M Y C S.A.S.) | M99: 4.15 | N99: 33000 | O99: ='Detalle Compras Septiembre 2026'!G511 -> 136950
I100: SUBTOTAL DÍA 10 (7 compras) | M100: =SUM(M93:M99) -> 115.505 | N100: =IF(M100>0, O100/M100, 0) -> 12010.692 | O100: =SUM(O93:O99) -> 1387295
I101: 11 | J101: CUADERNO DON ARTURO / NO REGISTRADO | K101: Costilla ahumada | L101: Costilla ahumada | M101: 1 | N101: 364000 | O101: ='Detalle Compras Septiembre 2026'!G380 -> 364000
I102: 11 | J102: CUADERNO DON ARTURO / NO REGISTRADO | K102: Costilla ahumada | L102: Costilla ahumada | M102: 1 | N102: 364000 | O102: ='Detalle Compras Septiembre 2026'!G381 -> 364000
I103: 11 | J103: CUADERNO DON ARTURO / NO REGISTRADO | K103: Mariscos | L103: Mariscos | M103: 1 | N103: 1124100 | O103: ='Detalle Compras Septiembre 2026'!G382 -> 1124100
...

Sheet Dashboard Bebidas
B2: DASHBOARD Y SEGUIMIENTO DE BEBIDAS - SEPTIEMBRE 2026
B3: Control analítico exclusivo de bebidas de tomar (cervezas, gaseosas, aguas, hidratantes, maltas)
B5: TOTAL INVERSIÓN BEBIDAS | D5: TOTAL UNIDADES / CAJAS | F5: COSTO PROM. / UND | G5: N° PEDIDOS | H5: % TOTAL RESTAURANTE
B6: 5929256.1 | D6: 1478 | F6: 4011.6753 | G6: 95 | H6: 0.034819478
B8: 1. SEGUIMIENTO DIARIO DE BEBIDAS | I8: 2. SEGUIMIENTO DETALLADO DÍA A DÍA - REGISTRO CRONOLÓGICO DE COMPRAS DE BEBIDAS
B9: Día | C9: Total Comprado ($) | D9: Cantidad (Caj/Und) | E9: Costo Prom. ($) | F9: % del Mes | G9: N° Pedidos | I9: Día | J9: N° Comprobante / Factura | K9: Ítem / Bebida (Nombre Exacto) | L9: Descripción Original (PDF) | M9: Cajas Compradas | N9: Costo Unitario Caja ($) | O9: Unid. x Caja | P9: Total Botellas / Unid. | Q9: Costo Unit. Botella ($) | R9: Vr. Total Compra ($)
B10: 1 | C10: 411700 | D10: 5 | E10: 82340 | F10: 0.054219887 | G10: 4 | I10: 1 | J10: VC242247 | K10: Cerv Stel Artois | L10: CERV.STEL ARTOIS*300ml BOT (Global Liquors VC242247) | M10: 1 | N10: 92200 | O10: 1 | P10: =M10*O10 -> 1 | Q10: =IF(P10>0, R10/P10, 0) -> 92200 | R10: ='Detalle Compras Septiembre 2026'!G18 -> 92200
B11: 2 | C11: 162100 | D11: 4 | E11: 40525 | F11: 0.021348175 | G11: 3 | I11: 1 | J11: VC242247 | K11: Club colombia | L11: CERV.CLUB DOR LATA*330 (Global Liquors VC242247) | M11: 1 | N11: 77500 | O11: 1 | P11: =M11*O11 -> 1 | Q11: =IF(P11>0, R11/P11, 0) -> 77500 | R11: ='Detalle Compras Septiembre 2026'!G19 -> 77500
B12: 3 | C12: 970600 | D12: 360 | E12: 2696.1111 | F12: 0.12782565 | G12: 8 | I12: 1 | J12: VC242247 | K12: Corona | L12: CERV.CORONA*330ml (Global Liquors VC242247) | M12: 1 | N12: 93000 | O12: 1 | P12: =M12*O12 -> 1 | Q12: =IF(P12>0, R12/P12, 0) -> 93000 | R12: ='Detalle Compras Septiembre 2026'!G20 -> 93000
B13: 4 | C13: 140975 | D13: 7 | E13: 20139.286 | F13: 0.018566064 | G13: 2 | I13: 1 | J13: VC242247 | K13: Poker | L13: CERV.POKER*330 LATA (Global Liquors VC242247) | M13: 2 | N13: 74500 | O13: 1 | P13: =M13*O13 -> 2 | Q13: =IF(P13>0, R13/P13, 0) -> 74500 | R13: ='Detalle Compras Septiembre 2026'!G21 -> 149000
B14: 5 | C14: 386504.07 | D14: 4695 | E14: 82.322486 | F14: 0.050901644 | G14: 15 | I14: SUBTOTAL DÍA 1 (4 compras) | M14: =SUM(M10:M13) -> 5 | N14: =IF(M14>0, R14/M14, 0) -> 82340 | O14: - | P14: =SUM(P10:P13) -> 5 | Q14: =IF(P14>0, R14/P14, 0) -> 82340 | R14: =SUM(R10:R13) -> 411700
B15: 6 | C15: 0 | D15: 0 | E15: 0 | F15: 0 | G15: 0 | I15: 2 | J15: VC242401 | K15: Gatorade | L15: BEB.GATORADE*500ml SURT. (Global Liquors - VC242401) | M15: 2 | N15: 39000 | O15: 1 | P15: =M15*O15 -> 2 | Q15: =IF(P15>0, R15/P15, 0) -> 39000 | R15: ='Detalle Compras Septiembre 2026'!G29 -> 78000
B16: 7 | C16: 73000 | D16: 11 | E16: 6636.3636 | F16: 0.0096139221 | G16: 4 | I16: 2 | J16: VC242401 | K16: H2o | L16: AGUA H2O*600ml SURTIDA (Global Liquors VC242401 c/ NC NX8465) | M16: 1 | N16: 32500 | O16: 1 | P16: =M16*O16 -> 1 | Q16: =IF(P16>0, R16/P16, 0) -> 32500 | R16: ='Detalle Compras Septiembre 2026'!G30 -> 32500
B17: 8 | C17: 29000 | D17: 4 | E17: 7250 | F17: 0.0038192293 | G17: 2 | I17: 2 | J17: VC242401 | K17: Vive 100 | L17: BEB.EN.*380 VIVE100 (Global Liquors - VC242401) | M17: 1 | N17: 51600 | O17: 1 | P17: =M17*O17 -> 1 | Q17: =IF(P17>0, R17/P17, 0) -> 51600 | R17: ='Detalle Compras Septiembre 2026'!G31 -> 51600
B18: 9 | C18: 1723770 | D18: 8423 | E18: 204.65036 | F18: 0.22701631 | G18: 26 | I18: SUBTOTAL DÍA 2 (3 compras) | M18: =SUM(M15:M17) -> 4 | N18: =IF(M18>0, R18/M18, 0) -> 40525 | O18: - | P18: =SUM(P15:P17) -> 4 | Q18: =IF(P18>0, R18/P18, 0) -> 40525 | R18: =SUM(R15:R17) -> 162100
B19: 10 | C19: 918471 | D19: 37 | E19: 24823.541 | F19: 0.12096039 | G19: 9 | I19: 3 | J19: FEMSA-3390 | K19: Brisa 600 ml | L19: AGUA BRISA PET 600ML (24) (Coca-Cola FEMSA - 5571323390) | M19: 1 | N19: 32000 | O19: 24 | P19: =M19*O19 -> 24 | Q19: =IF(P19>0, R19/P19, 0) -> 1333.3333 | R19: ='Detalle Compras Septiembre 2026'!G71 -> 32000
B20: 11 | C20: 34000 | D20: 5 | E20: 6800 | F20: 0.0044777171 | G20: 2 | I20: 3 | J20: FEMSA-3390 | K20: Coca cola 1,5 lt pet (12) nvo | L20: COCA COLA 1.5LT PET(12) Nvo (Coca-Cola FEMSA - 5571323390) | M20: 2 | N20: 65000 | O20: 12 | P20: =M20*O20 -> 24 | Q20: =IF(P20>0, R20/P20, 0) -> 5416.6667 | R20: ='Detalle Compras Septiembre 2026'!G72 -> 130000
B21: 12 | C21: 83000 | D21: 4 | E21: 20750 | F21: 0.010930898 | G21: 4 | I21: 3 | J21: FEMSA-3390 | K21: Coca cola zero 1,5 ltrs | L21: COCA COLA ZERO 1.5LT PET(12)KZ (Coca-Cola FEMSA - 5571323390) | M21: 2 | N21: 65000 | O21: 12 | P21: =M21*O21 -> 24 | Q21: =IF(P21>0, R21/P21, 0) -> 5416.6667 | R21: ='Detalle Compras Septiembre 2026'!G73 -> 130000
B22: 13 | C22: 126500 | D22: 78 | E22: 1621.7949 | F22: 0.016659742 | G22: 2 | I22: 3 | J22: FEMSA-3390 | K22: Coca cola zero 400ml pet(12)kz | L22: COCA COLA ZERO 400ML PET(12)KZ (Coca-Cola FEMSA - 5571323390) | M22: 10 | N22: 28800 | O22: 12 | P22: =M22*O22 -> 120 | Q22: =IF(P22>0, R22/P22, 0) -> 2400 | R22: ='Detalle Compras Septiembre 2026'!G74 -> 288000
B23: 14 | C23: 0 | D23: 0 | E23: 0 | F23: 0 | G23: 0 | I23: 3 | J23: FEMSA-3390 | K23: Coca-cola 400 ml pet (24) | L23: COCA-COLA 400ML PET (12) (Coca-Cola FEMSA - 5571323390) | M23: 8 | N23: 30000 | O23: 12 | P23: =M23*O23 -> 96 | Q23: =IF(P23>0, R23/P23, 0) -> 2500 | R23: ='Detalle Compras Septiembre 2026'!G75 -> 240000
B24: 15 | C24: 38436 | D24: 6 | E24: 6406 | F24: 0.0050619275 | G24: 3 | I24: 3 | J24: FEMSA-3389 | K24: Gaseosa 400 ml | L24: QUATRO CHOICE 400ML NR (12) (Coca-Cola FEMSA - 5571323389) | M24: 2 | N24: 25100 | O24: 12 | P24: =M24*O24 -> 24 | Q24: =IF(P24>0, R24/P24, 0) -> 2091.6667 | R24: ='Detalle Compras Septiembre 2026'!G76 -> 50200
B25: 16 | C25: 34000 | D25: 1 | E25: 34000 | F25: 0.0044777171 | G25: 1 | I25: 3 | J25: FEMSA-3389 | K25: Gaseosa 400 ml | L25: PREMIO ROJO FNT 400 ML PET(12) (Coca-Cola FEMSA - 5571323389) | M25: 2 | N25: 25100 | O25: 12 | P25: =M25*O25 -> 24 | Q25: =IF(P25>0, R25/P25, 0) -> 2091.6667 | R25: ='Detalle Compras Septiembre 2026'!G77 -> 50200
B26: 17 | C26: 249000 | D26: 61 | E26: 4081.9672 | F26: 0.032792693 | G26: 3 | I26: 3 | J26: FEMSA-3389 | K26: Gaseosa 400 ml | L26: SPRITE 400 ML NR (12) (Coca-Cola FEMSA - 5571323389) | M26: 2 | N26: 25100 | O26: 12 | P26: =M26*O26 -> 24 | Q26: =IF(P26>0, R26/P26, 0) -> 2091.6667 | R26: ='Detalle Compras Septiembre 2026'!G78 -> 50200
B27: 18 | C27: 548200 | D27: 8 | E27: 68525 | F27: 0.072196604 | G27: 7 | I27: SUBTOTAL DÍA 3 (8 compras) | M27: =SUM(M19:M26) -> 29 | N27: =IF(M27>0, R27/M27, 0) -> 33468.966 | O27: - | P27: =SUM(P19:P26) -> 360 | Q27: =IF(P27>0, R27/P27, 0) -> 2696.1111 | R27: =SUM(R19:R26) -> 970600
B28: 19 | C28: 0 | D28: 0 | E28: 0 | F28: 0 | G28: 0 | I28: 4 | J28: A 1494 | K28: Extracto de Coco Premium 1000 ml | L28: Extrato de coco premium 1000 mL (COL COCO S.A.S.) | M28: 5 | N28: 24395 | O28: 1 | P28: =M28*O28 -> 5 | Q28: =IF(P28>0, R28/P28, 0) -> 24395 | R28: ='Detalle Compras Septiembre 2026'!G528 -> 121975
B29: 20 | C29: 0 | D29: 0 | E29: 0 | F29: 0 | G29: 0 | I29: 4 | J29: NV202395 | K29: Hielo en bloque | L29: BLOQUE MEDIA (INDUSTRIA HIELO EL NEVADO SAS) | M29: 2 | N29: 9500 | O29: 1 | P29: =M29*O29 -> 2 | Q29: =IF(P29>0, R29/P29, 0) -> 9500 | R29: ='Detalle Compras Septiembre 2026'!G568 -> 19000
B30: 21 | C30: 248000 | D30: 1512 | E30: 164.02116 | F30: 0.032660996 | G30: 6 | I30: SUBTOTAL DÍA 4 (2 compras) | M30: =SUM(M28:M29) -> 7 | N30: =IF(M30>0, R30/M30, 0) -> 20139.286 | O30: - | P30: =SUM(P28:P29) -> 7 | Q30: =IF(P30>0, R30/P30, 0) -> 20139.286 | R30: =SUM(R28:R29) -> 140975
B31: 22 | C31: 0 | D31: 0 | E31: 0 | F31: 0 | G31: 0 | I31: 5 | J31: JM07-1019725 | K31: H2OH! Maracuyá 600 ml | L31: MARACUYA H2OH! 600 ML PET X 15 (POSTOBON S.A.) | M31: 5 | N31: 1820.73 | O31: 1 | P31: =M31*O31 -> 5 | Q31: =IF(P31>0, R31/P31, 0) -> 1820.73 | R31: ='Detalle Compras Septiembre 2026'!G512 -> 9103.65
B32: 23 | C32: 0 | D32: 0 | E32: 0 | F32: 0 | G32: 0 | I32: 5 | J32: JM07-1019725 | K32: H2OH! Limoneto 600 ml | L32: LIMONATA H2OH! 600 ML PET X 15 (POSTOBON S.A.) | M32: 5 | N32: 1820.73 | O32: 1 | P32: =M32*O32 -> 5 | Q32: =IF(P32>0, R32/P32, 0) -> 1820.73 | R32: ='Detalle Compras Septiembre 2026'!G513 -> 9103.65
B33: 24 | C33: 285500 | D33: 174 | E33: 1640.8046 | F33: 0.037599654 | G33: 6 | I33: 5 | J33: JM07-1019725 | K33: H2OH! Manzana 600 ml | L33: MANZANA H2OH 600 ML PET X 15 (POSTOBON S.A.) | M33: 5 | N33: 1820.73 | O33: 1 | P33: =M33*O33 -> 5 | Q33: =IF(P33>0, R33/P33, 0) -> 1820.73 | R33: ='Detalle Compras Septiembre 2026'!G514 -> 9103.65
B34: 25 | C34: 672600 | D34: 16 | E34: 42037.5 | F34: 0.088579781 | G34: 16 | I34: 5 | J34: JM07-1019725 | K34: Mr Tea Durazno 500 ml | L34: DURAZNO MR TEA 500 ML PET X 12 (Postobón S.A.) | M34: 6 | N34: 1890.76 | O34: 12 | P34: =M34*O34 -> 72 | Q34: =IF(P34>0, R34/P34, 0) -> 157.56333 | R34: ='Detalle Compras Septiembre 2026'!G515 -> 11344.56
B35: 26 | C35: 457798.87 | D35: 4887 | E35: 93.676871 | F35: 0.060290995 | G35: 11 | I35: 5 | J35: JM07-1019725 | K35: Mr Tea Limón 500 ml | L35: LIMON MR TEA 500 ML PET X 12 (Postobón S.A.) | M35: 6 | N35: 1890.76 | O35: 12 | P35: =M35*O35 -> 72 | Q35: =IF(P35>0, R35/P35, 0) -> 157.56333 | R35: ='Detalle Compras Septiembre 2026'!G516 -> 11344.56
B36: 27 | C36: 0 | D36: 0 | E36: 0 | F36: 0 | G36: 0 | I36: 5 | J36: JM07-1019725 | K36: Postobón Naranja 1.75 L | L36: NARANJA POSTOBON 1.750 ML PET X 12 PM (Postobón S.A.) | M36: 6 | N36: 3151.26 | O36: 12 | P36: =M36*O36 -> 72 | Q36: =IF(P36>0, R36/P36, 0) -> 262.605 | R36: ='Detalle Compras Septiembre 2026'!G517 -> 18907.56
B37: 28 | C37: 0 | D37: 0 | E37: 0 | F37: 0 | G37: 0 | I37: 5 | J37: JM07-1019725 | K37: Postobón Uva 1.75 L | L37: UVA POSTOBON PET 1.750 ML PET X 12 PM (Postobón S.A.) | M37: 6 | N37: 3151.26 | O37: 12 | P37: =M37*O37 -> 72 | Q37: =IF(P37>0, R37/P37, 0) -> 262.605 | R37: ='Detalle Compras Septiembre 2026'!G518 -> 18907.56
B38: 29 | C38: 0 | D38: 0 | E38: 0 | F38: 0 | G38: 0 | I38: 5 | J38: JM07-1019725 | K38: Piña Postobón 350 ml Vidrio | L38: PIÑA NACIONAL 350 ML VIDRIO R X 30 (Postobón S.A.) | M38: 15 | N38: 1450.98 | O38: 30 | P38: =M38*O38 -> 450 | Q38: =IF(P38>0, R38/P38, 0) -> 48.366 | R38: ='Detalle Compras Septiembre 2026'!G519 -> 21764.7
B39: 30 | C39: 0 | D39: 0 | E39: 0 | F39: 0 | G39: 0 | I39: 5 | J39: JM07-1019725 | K39: Colombiana 350 ml Vidrio | L39: COLOMBIANA NACIONAL 350 ML VIDRIO R X 30 (Postobón S.A.) | M39: 15 | N39: 1450.98 | O39: 30 | P39: =M39*O39 -> 450 | Q39: =IF(P39>0, R39/P39, 0) -> 48.366 | R39: ='Detalle Compras Septiembre 2026'!G520 -> 21764.7
B40: TOTAL MES | C40: 7593154.9 | D40: 20298 | E40: 374.0839 | F40: 1 | G40: 134 | I40: 5 | J40: JM07-1019725 | K40: Postobón Uva 350 ml Vidrio | L40: UVA POSTOBON 350 ML VIDRIO R X 30 (Postobón S.A.) | M40: 15 | N40: 1450.98 | O40: 30 | P40: =M40*O40 -> 450 | Q40: =IF(P40>0, R40/P40, 0) -> 48.366 | R40: ='Detalle Compras Septiembre 2026'!G521 -> 21764.7
I41: 5 | J41: JM07-1019725 | K41: Postobón Manzana 350 ml Vidrio | L41: MANZANA POSTOBON 350 ML VIDRIO R X 30 (Postobón S.A.) | M41: 15 | N41: 1450.98 | O41: 30 | P41: =M41*O41 -> 450 | Q41: =IF(P41>0, R41/P41, 0) -> 48.366 | R41: ='Detalle Compras Septiembre 2026'!G522 -> 21764.7
I42: 5 | J42: JM07-1019725 | K42: Postobón Manzana 1.75 L | L42: MANZANA POSTOBON 1.750 ML PET X 12 PM (Postobón S.A.) | M42: 12 | N42: 3151.26 | O42: 12 | P42: =M42*O42 -> 144 | Q42: =IF(P42>0, R42/P42, 0) -> 262.605 | R42: ='Detalle Compras Septiembre 2026'!G523 -> 37815.12
I43: 5 | J43: JM07-1019725 | K43: Colombiana 1.75 L | L43: COLOMBIANA NACIONAL 1.750 ML PET X 12 PM (Postobón S.A.) | M43: 12 | N43: 3151.26 | O43: 12 | P43: =M43*O43 -> 144 | Q43: =IF(P43>0, R43/P43, 0) -> 262.605 | R43: ='Detalle Compras Septiembre 2026'!G524 -> 37815.12
I44: 5 | J44: JM07-1019725 | K44: Agua Cristal 600 ml | L44: AGUA CRISTAL 600 ML PET X 24 (Postobón S.A.) | M44: 48 | N44: 1333.33 | O44: 24 | P44: =M44*O44 -> 1152 | Q44: =IF(P44>0, R44/P44, 0) -> 55.555417 | R44: ='Detalle Compras Septiembre 2026'!G525 -> 63999.84
I45: 5 | J45: JM07-1019725 | K45: Agua Cristal con Gas 600 ml | L45: AGUA CRISTAL CON GAS 600 ML PET X 24 (Postobón S.A.) | M45: 48 | N45: 1500 | O45: 24 | P45: =M45*O45 -> 1152 | Q45: =IF(P45>0, R45/P45, 0) -> 62.5 | R45: ='Detalle Compras Septiembre 2026'!G526 -> 72000
I46: SUBTOTAL DÍA 5 (15 compras) | M46: =SUM(M31:M45) -> 219 | N46: =IF(M46>0, R46/M46, 0) -> 1764.8588 | O46: - | P46: =SUM(P31:P45) -> 4695 | Q46: =IF(P46>0, R46/P46, 0) -> 82.322486 | R46: =SUM(R31:R45) -> 386504.07
I47: 7 | J47: NV202629 | K47: Hielo en bloque | L47: BLOQUE MEDIA (INDUSTRIA HIELO EL NEVADO SAS) | M47: 2 | N47: 9500 | O47: 1 | P47: =M47*O47 -> 2 | Q47: =IF(P47>0, R47/P47, 0) -> 9500 | R47: ='Detalle Compras Septiembre 2026'!G564 -> 19000
I48: 7 | J48: NV202629 | K48: Hielo en bolsa | L48: BOLSA X 5 KL TUBULAR (INDUSTRIA HIELO EL NEVADO SAS) | M48: 4 | N48: 5000 | O48: 1 | P48: =M48*O48 -> 4 | Q48: =IF(P48>0, R48/P48, 0) -> 5000 | R48: ='Detalle Compras Septiembre 2026'!G565 -> 20000
I49: 7 | J49: NV202664 | K49: Hielo en bloque | L49: BLOQUE MEDIA (INDUSTRIA HIELO EL NEVADO SAS) | M49: 2 | N49: 9500 | O49: 1 | P49: =M49*O49 -> 2 | Q49: =IF(P49>0, R49/P49, 0) -> 9500 | R49: ='Detalle Compras Septiembre 2026'!G566 -> 19000
I50: 7 | J50: NV202664 | K50: Hielo en bolsa | L50: BOLSA X 5 KL TUBULAR (INDUSTRIA HIELO EL NEVADO SAS) | M50: 3 | N50: 5000 | O50: 1 | P50: =M50*O50 -> 3 | Q50: =IF(P50>0, R50/P50, 0) -> 5000 | R50: ='Detalle Compras Septiembre 2026'!G567 -> 15000
I51: SUBTOTAL DÍA 7 (4 compras) | M51: =SUM(M47:M50) -> 11 | N51: =IF(M51>0, R51/M51, 0) -> 6636.3636 | O51: - | P51: =SUM(P47:P50) -> 11 | Q51: =IF(P51>0, R51/P51, 0) -> 6636.3636 | R51: =SUM(R47:R50) -> 73000
I52: 8 | J52: NV202876 | K52: Hielo en Bloque Media | L52: BLOQUE MEDIA (INDUSTRIA HIELO EL NEVADO SAS) | M52: 2 | N52: 9500 | O52: 1 | P52: =M52*O52 -> 2 | Q52: =IF(P52>0, R52/P52, 0) -> 9500 | R52: ='Detalle Compras Septiembre 2026'!G550 -> 19000
I53: 8 | J53: NV202875 | K53: Hielo en Bolsa x 5 kg Tubular | L53: BOLSA X 5 KL TUBULAR (INDUSTRIA HIELO EL NEVADO SAS) | M53: 2 | N53: 5000 | O53: 1 | P53: =M53*O53 -> 2 | Q53: =IF(P53>0, R53/P53, 0) -> 5000 | R53: ='Detalle Compras Septiembre 2026'!G551 -> 10000
I54: SUBTOTAL DÍA 8 (2 compras) | M54: =SUM(M52:M53) -> 4 | N54: =IF(M54>0, R54/M54, 0) -> 7250 | O54: - | P54: =SUM(P52:P53) -> 4 | Q54: =IF(P54>0, R54/P54, 0) -> 7250 | R54: =SUM(R52:R53) -> 29000
I55: 9 | J55: REM-38763 | K55: Jug del valle | L55: JUGO NUTIVA EN CAJA X 200ML (Doña Mary Remision 38763) | M55: 720 | N55: 700 | O55: 1 | P55: =M55*O55 -> 720 | Q55: =IF(P55>0, R55/P55, 0) -> 700 | R55: ='Detalle Compras Septiembre 2026'!G280 -> 504000
I56: 9 | J56: JM071024895 | K56: Manzana h2oh | L56: MANZANA H2OH 600 ML PET X 15 (Postobon S.A. JM071024895) | M56: 7 | N56: 2166.67 | O56: 1 | P56: =M56*O56 -> 7 | Q56: =IF(P56>0, R56/P56, 0) -> 2166.6686 | R56: ='Detalle Compras Septiembre 2026'!G296 -> 15166.68
I57: 9 | J57: JM071024895 | K57: Limonada h2oh | L57: LIMONADA H2OH! 600 ML PET X 15 (Postobon S.A. JM071024895) | M57: 8 | N57: 2166.67 | O57: 1 | P57: =M57*O57 -> 8 | Q57: =IF(P57>0, R57/P57, 0) -> 2166.6687 | R57: ='Detalle Compras Septiembre 2026'!G297 -> 17333.35
I58: 9 | J58: JM071024895 | K58: Maracuya h2oh | L58: MARACUYA H2OH! 600 ML PET X 15 (Postobon S.A. JM071024895) | M58: 15 | N58: 2166.67 | O58: 1 | P58: =M58*O58 -> 15 | Q58: =IF(P58>0, R58/P58, 0) -> 2166.6687 | R58: ='Detalle Compras Septiembre 2026'!G298 -> 32500.03
I59: 9 | J59: JM071024895 | K59: Agua cristal con gas | L59: AGUA CRISTAL CON GAS 600 ML PET X 24 (Postobon S.A. JM071024895) | M59: 24 | N59: 1500 | O59: 24 | P59: =M59*O59 -> 576 | Q59: =IF(P59>0, R59/P59, 0) -> 62.5 | R59: ='Detalle Compras Septiembre 2026'!G299 -> 36000
I60: 9 | J60: JM071024895 | K60: Agua cristal | L60: AGUA CRISTAL 600 ML PET X 24 (Postobon S.A. JM071024895) | M60: 48 | N60: 1333.33 | O60: 24 | P60: =M60*O60 -> 1152 | Q60: =IF(P60>0, R60/P60, 0) -> 55.555417 | R60: ='Detalle Compras Septiembre 2026'!G300 -> 63999.84
I61: 9 | J61: JM071024895 | K61: Bretaña | L61: BRETANA 350 ML VIDRIO R X 30 (Postobon S.A. JM071024895) | M61: 90 | N61: 1916.67 | O61: 30 | P61: =M61*O61 -> 2700 | Q61: =IF(P61>0, R61/P61, 0) -> 63.889 | R61: ='Detalle Compras Septiembre 2026'!G301 -> 172500.3
I62: 9 | J62: JM071024895 | K62: Colombiana vidrio | L62: COLOMBIANA NACIONAL 350 ML VIDRIO R X 30 (Postobon S.A. JM071024895) | M62: 15 | N62: 1726.67 | O62: 30 | P62: =M62*O62 -> 450 | Q62: =IF(P62>0, R62/P62, 0) -> 57.555533 | R62: ='Detalle Compras Septiembre 2026'!G302 -> 25899.99
I63: 9 | J63: JM071024895 | K63: Popular vidrio | L63: POPULAR 350 ML VIDRIO R X 30 (Postobon S.A. JM071024895) | M63: 15 | N63: 1726.67 | O63: 30 | P63: =M63*O63 -> 450 | Q63: =IF(P63>0, R63/P63, 0) -> 57.555533 | R63: ='Detalle Compras Septiembre 2026'!G303 -> 25899.99
I64: 9 | J64: JM071024895 | K64: Uva vidrio | L64: UVA POSTOBON 350 ML VIDRIO R X 30 (Postobon S.A. JM071024895) | M64: 15 | N64: 1726.67 | O64: 30 | P64: =M64*O64 -> 450 | Q64: =IF(P64>0, R64/P64, 0) -> 57.555533 | R64: ='Detalle Compras Septiembre 2026'!G304 -> 25899.99
I65: 9 | J65: JM071024895 | K65: Manzana vidrio | L65: MANZANA POSTOBON 350 ML VIDRIO R X 30 (Postobon S.A. JM071024895) | M65: 15 | N65: 1726.67 | O65: 30 | P65: =M65*O65 -> 450 | Q65: =IF(P65>0, R65/P65, 0) -> 57.555533 | R65: ='Detalle Compras Septiembre 2026'!G305 -> 25899.99
I66: 9 | J66: JM071024895 | K66: Tamarindo vidrio | L66: TAMARINDO POSTOBON 350 ML VIDRIO R X 30 (Postobon S.A. JM071024895) | M66: 30 | N66: 1500 | O66: 30 | P66: =M66*O66 -> 900 | Q66: =IF(P66>0, R66/P66, 0) -> 49.999833 | R66: ='Detalle Compras Septiembre 2026'!G306 -> 44999.85
I67: 9 | J67: JM071024895 | K67: Manzana 1.75l | L67: MANZANA POSTOBON 1.750 ML PET X 12 PM (Postobon S.A. JM071024895) | M67: 12 | N67: 3750 | O67: 12 | P67: =M67*O67 -> 144 | Q67: =IF(P67>0, R67/P67, 0) -> 312.49993 | R67: ='Detalle Compras Septiembre 2026'!G307 -> 44999.99
... I69: 9 | J69: JM071024895 | K69: Uva 1.75l | L69: UVA POSTOBON PET 1.750 ML PET X 12 PM (Postobon S.A. JM071024895) | M69: 12 | N69: 3750 | O69: 12 | P69: =M69*O69 -> 144 | Q69: =IF(P69>0, R69/P69, 0) -> 312.50007 | R69: ='Detalle Compras Septiembre 2026'!G309 -> 45000.01
I70: 9 | J70: NV202947 | K70: Hielo en Bolsa x 5 kg Tubular | L70: BOLSA X 5 KL TUBULAR (INDUSTRIA HIELO EL NEVADO SAS) | M70: 2 | N70: 5000 | O70: 1 | P70: =M70*O70 -> 2 | Q70: =IF(P70>0, R70/P70, 0) -> 5000 | R70: ='Detalle Compras Septiembre 2026'!G534 -> 10000
I71: 9 | J71: FEC 2940 | K71: Limonada de Coco Fusionada x 10 | L71: LIMONADA DE COCO FUSIONADA X 10 (HENRY ANTONIO CASTAÑO TORO) | M71: 5 | N71: 26000 | O71: 1 | P71: =M71*O71 -> 5 | Q71: =IF(P71>0, R71/P71, 0) -> 26000 | R71: ='Detalle Compras Septiembre 2026'!G535 -> 130000
I72: 9 | J72: Z1284001674 | K72: Café Colcafé Cappuccino Clásico 500 g | L72: Colcafé Cappuccino Clasic 500g (ALKOSTO) | M72: 1 | N72: 44900 | O72: 1 | P72: =M72*O72 -> 1 | Q72: =IF(P72>0, R72/P72, 0) -> 44900 | R72: ='Detalle Compras Septiembre 2026'!G540 -> 44900
I73: 9 | J73: MA42914 | K73: Alquemix Galaxy V 170 g | L73: ALQUEMIX GALAXY V 170G (PRODUCTOS NATURALES DE LA SABANA S.A.S. BIC) | M73: 5 | N73: 3160 | O73: 1 | P73: =M73*O73 -> 5 | Q73: =IF(P73>0, R73/P73, 0) -> 3160 | R73: ='Detalle Compras Septiembre 2026'!G542 -> 15800
I74: 9 | J74: MA42914 | K74: Alquemix Milo V 95 g | L74: ALQUEMIX MILO V95G (PRODUCTOS NATURALES DE LA SABANA S.A.S. BIC) | M74: 5 | N74: 2510 | O74: 1 | P74: =M74*O74 -> 5 | Q74: =IF(P74>0, R74/P74, 0) -> 2510 | R74: ='Detalle Compras Septiembre 2026'!G543 -> 12550
I75: 9 | J75: MA42914 | K75: Crema de Leche 1000 g | L75: CREMA DE LECHE 1000G (PRODUCTOS NATURALES DE LA SABANA S.A.S. BIC) | M75: 2 | N75: 18200 | O75: 1 | P75: =M75*O75 -> 2 | Q75: =IF(P75>0, R75/P75, 0) -> 18200 | R75: ='Detalle Compras Septiembre 2026'!G544 -> 36400
I76: 9 | J76: MA42914 | K76: Leche Institucional 1100 ml | L76: SABOR ORIGINAL INSTITUCIONAL 1100ML (PRODUCTOS NATURALES DE LA SABANA S.A.S. BIC) | M76: 70 | N76: 4180 | O76: 1 | P76: =M76*O76 -> 70 | Q76: =IF(P76>0, R76/P76, 0) -> 4180 | R76: ='Detalle Compras Septiembre 2026'!G545 -> 292600
I77: 9 | J77: MA42914 | K77: Jugo Tangelo 400 ml | L77: TANGELO BOTELLA 400 ML (PRODUCTOS NATURALES DE LA SABANA S.A.S. BIC) | M77: 6 | N77: 1100 | O77: 1 | P77: =M77*O77 -> 6 | Q77: =IF(P77>0, R77/P77, 0) -> 1100 | R77: ='Detalle Compras Septiembre 2026'!G546 -> 6600
I78: 9 | J78: MA42914 | K78: Alquería M&M 100 g | L78: ALQUERIA M&M 100G (PRODUCTOS NATURALES DE LA SABANA S.A.S. BIC) | M78: 6 | N78: 2510 | O78: 1 | P78: =M78*O78 -> 6 | Q78: =IF(P78>0, R78/P78, 0) -> 2510 | R78: ='Detalle Compras Septiembre 2026'!G547 -> 15060
I79: 9 | J79: MA42914 | K79: Alquería Flips 170 g | L79: ALQUERIA CER 170G FLIPS (PRODUCTOS NATURALES DE LA SABANA S.A.S. BIC) | M79: 5 | N79: 3160 | O79: 1 | P79: =M79*O79 -> 5 | Q79: =IF(P79>0, R79/P79, 0) -> 3160 | R79: ='Detalle Compras Septiembre 2026'!G548 -> 15800
I80: 9 | J80: MA42914 | K80: Alquería Hojuelas 170 g | L80: ALQUERIA HOJUELAS 170GR (PRODUCTOS NATURALES DE LA SABANA S.A.S. BIC) | M80: 6 | N80: 3160 | O80: 1 | P80: =M80*O80 -> 6 | Q80: =IF(P80>0, R80/P80, 0) -> 3160 | R80: ='Detalle Compras Septiembre 2026'!G549 -> 18960
I81: SUBTOTAL DÍA 9 (26 compras) | M81: =SUM(M55:M80) -> 1151 | N81: =IF(M81>0, R81/M81, 0) -> 1497.6281 | O81: - | P81: =SUM(P55:P80) -> 8423 | Q81: =IF(P81>0, R81/P81, 0) -> 204.65036 | R81: =SUM(R55:R80) -> 1723770
I82: 10 | J82: CUADERNO CAJA / NO REGISTRADO | K82: Coca-Cola Domicilios (Neymar) | L82: Coca-Cola Domicilios (Neymar) | M82: 1 | N82: 329500 | O82: 1 | P82: =M82*O82 -> 1 | Q82: =IF(P82>0, R82/P82, 0) -> 329500 | R82: ='Detalle Compras Septiembre 2026'!G355 -> 329500
I83: 10 | J83: FVCL 5350357 | K83: Brisa Manzana 600ml | L83: BRISA MANZANA 600ML PET(6) REDUCCION (Ind. Nac. Gaseosas) | M83: 1 | N83: 10504 | O83: 1 | P83: =M83*O83 -> 1 | Q83: =IF(P83>0, R83/P83, 0) -> 10504 | R83: ='Detalle Compras Septiembre 2026'!G367 -> 10504
I84: 10 | J84: FVCL 5350352 | K84: Brisa 1L | L84: BRISA ECOFLEX 1 LITRO (6) REDUCCION (Ind. Nac. Gaseosas) | M84: 1 | N84: 12000 | O84: 1 | P84: =M84*O84 -> 1 | Q84: =IF(P84>0, R84/P84, 0) -> 12000 | R84: ='Detalle Compras Septiembre 2026'!G368 -> 12000
I85: 10 | J85: FVCL 5350354 | K85: Coca Cola 1L | L85: COCA COLA SO 1L PET (12) REDUCCION (Ind. Nac. Gaseosas) | M85: 1 | N85: 33782 | O85: 12 | P85: =M85*O85 -> 12 | Q85: =IF(P85>0, R85/P85, 0) -> 2815.1667 | R85: ='Detalle Compras Septiembre 2026'!G369 -> 33782
I86: 10 | J86: FVCL 5350355 | K86: Quatro 1.5L | L86: QUATRO CHOICE 1.5 LT PET (12) REDUCCION (Ind. Nac. Gaseosas) | M86: 1 | N86: 37815 | O86: 12 | P86: =M86*O86 -> 12 | Q86: =IF(P86>0, R86/P86, 0) -> 3151.25 | R86: ='Detalle Compras Septiembre 2026'!G370 -> 37815
I87: 10 | J87: 6760 / FP 5350350 | K87: Agua Brisa | L87: AGUA BRISA (INDUSTRIA NACIONAL DE GASEOSAS SA) | M87: 1 | N87: 264500 | O87: 1 | P87: =M87*O87 -> 1 | Q87: =IF(P87>0, R87/P87, 0) -> 264500 | R87: ='Detalle Compras Septiembre 2026'!G501 -> 264500
I88: 10 | J88: 6759 / FP 5350358 | K88: Gaseosas | L88: GASEOSAS (INDUSTRIA NACIONAL DE GASEOSAS SA) | M88: 1 | N88: 65000 | O88: 1 | P88: =M88*O88 -> 1 | Q88: =IF(P88>0, R88/P88, 0) -> 65000 | R88: ='Detalle Compras Septiembre 2026'!G502 -> 65000
I89: 10 | J89: NV203068 | K89: Bloque media | L89: BLOQUE MEDIA (EL NEVADO S.A.S.) | M89: 2 | N89: 9500 | O89: 1 | P89: =M89*O89 -> 2 | Q89: =IF(P89>0, R89/P89, 0) -> 9500 | R89: ='Detalle Compras Septiembre 2026'!G506 -> 19000
I90: 10 | J90: A 1498 | K90: Extracto de Coco Premium 1000 ml | L90: Extrato de coco premium 1000 mL (COL COCO S.A.S.) | M90: 6 | N90: 24395 | O90: 1 | P90: =M90*O90 -> 6 | Q90: =IF(P90>0, R90/P90, 0) -> 24395 | R90: ='Detalle Compras Septiembre 2026'!G527 -> 146370
I91: SUBTOTAL DÍA 10 (9 compras) | M91: =SUM(M82:M90) -> 15 | N91: =IF(M91>0, R91/M91, 0) -> 61231.4 | O91: - | P91: =SUM(P82:P90) -> 37 | Q91: =IF(P91>0, R91/P91, 0) -> 24823.541 | R91: =SUM(R82:R90) -> 918471
I92: 11 | J92: NV203136 | K92: Hielo Bloque Media | L92: BLOQUE MEDIA (INDUSTRIA HIELO EL NEVADO SAS) | M92: 2 | N92: 9500 | O92: 1 | P92: =M92*O92 -> 2 | Q92: =IF(P92>0, R92/P92, 0) -> 9500 | R92: ='Detalle Compras Septiembre 2026'!G498 -> 19000
I93: 11 | J93: NV203136 | K93: Hielo Bolsa Tubular 5 Kg | L93: BOLSA X 5 KL TUBULAR (INDUSTRIA HIELO EL NEVADO SAS) | M93: 3 | N93: 5000 | O93: 1 | P93: =M93*O93 -> 3 | Q93: =IF(P93>0, R93/P93, 0) -> 5000 | R93: ='Detalle Compras Septiembre 2026'!G499 -> 15000
I94: SUBTOTAL DÍA 11 (2 compras) | M94: =SUM(M92:M93) -> 5 | N94: =IF(M94>0, R94/M94, 0) -> 6800 | O94: - | P94: =SUM(P92:P93) -> 5 | Q94: =IF(P94>0, R94/P94, 0) -> 6800 | R94: =SUM(R92:R93) -> 34000
I95: 12 | J95: V03-105561 | K95: Cerveza Coronita 210ml | L95: 1 CERVEZA CORONITA*210ml*6und EXTRA BOTE | M95: 1 | N95: 20750 | O95: 1 | P95: =M95*O95 -> 1 | Q95: =IF(P95>0, R95/P95, 0) -> 20750 | R95: ='Detalle Compras Septiembre 2026'!G460 -> 20750
I96: 12 | J96: V03-105561 | K96: Cerveza Coronita 210ml | L96: 2 CERVEZA CORONITA*210ml*6und EXTRA BOTE | M96: 1 | N96: 20750 | O96: 1 | P96: =M96*O96 -> 1 | Q96: =IF(P96>0, R96/P96, 0) -> 20750 | R96: ='Detalle Compras Septiembre 2026'!G461 -> 20750
I97: 12 | J97: V03-105561 | K97: Cerveza Coronita 210ml | L97: 3 CERVEZA CORONITA*210ml*6und EXTRA BOTE | M97: 1 | N97: 20750 | O97: 1 | P97: =M97*O97 -> 1 | Q97: =IF(P97>0, R97/P97, 0) -> 20750 | R97: ='Detalle Compras Septiembre 2026'!G462 -> 20750
I98: 12 | J98: V03-105561 | K98: Cerveza Coronita 210ml | L98: 4 CERVEZA CORONITA*210ml*6und EXTRA BOTE | M98: 1 | N98: 20750 | O98: 1 | P98: =M98*O98 -> 1 | Q98: =IF(P98>0, R98/P98, 0) -> 20750 | R98: ='Detalle Compras Septiembre 2026'!G463 -> 20750
I99: SUBTOTAL DÍA 12 (4 compras) | M99: =SUM(M95:M98) -> 4 | N99: =IF(M99>0, R99/M99, 0) -> 20750 | O99: - | P99: =SUM(P95:P98) -> 4 | Q99: =IF(P99>0, R99/P99, 0) -> 20750 | R99: =SUM(R95:R98) -> 83000
I100: 13 | J100: FVCL 5378420 | K100: Agua | L100: AGUA BRISA PET 600ML (24) | M100: 2 | N100: 32000 | O100: 24 | P100: =M100*O100 -> 48 | Q100: =IF(P100>0, R100/P100, 0) -> 1333.3333 | R100: ='Detalle Compras Septiembre 2026'!G468 -> 64000
I101: 13 | J101: FVCL 5378421 | K101: Gaseosa | L101: COCA-COLA 350ML VIR(30) | M101: 1 | N101: 62500 | O101: 30 | P101: =M101*O101 -> 30 | Q101: =IF(P101>0, R101/P101, 0) -> 2083.3333 | R101: ='Detalle Compras Septiembre 2026'!G469 -> 62500
I102: SUBTOTAL DÍA 13 (2 compras) | M102: =SUM(M100:M101) -> 3 | N102: =IF(M102>0, R102/M102, 0) -> 42166.667 | O102: - | P102: =SUM(P100:P101) -> 78 | Q102: =IF(P102>0, R102/P102, 0) -> 1621.7949 | R102: =SUM(R100:R101) -> 126500
I103: 15 | J103: FEPL3208151 | K103: Jugo Tangelo | L103: TANGELO BOTELLA 400 ML (Alquería) | M103: 4 | N103: 1309 | O103: 1 | P103: =M103*O103 -> 4 | Q103: =IF(P103>0, R103/P103, 0) -> 1309 | R103: ='Detalle Compras Septiembre 2026'!G574 -> 5236
I104: 15 | J104: SF45262 | K104: Hielo | L104: BLOQUE MEDIA X 2 (Hielo El Nevado Remisión SF45262) | M104: 1 | N104: 19000 | O104: 1 | P104: =M104*O104 -> 1 | Q104: =IF(P104>0, R104/P104, 0) -> 19000 | R104: ='Detalle Compras Septiembre 2026'!G594 -> 19000
...

Sheet Dashboard Nomina
B2: RESTAURANTE CHOCLOS Y ASADOS LA FINCA
B3: DASHBOARD ANALÍTICO DE NÓMINA, HONORARIOS Y TALENTO HUMANO - SEPTIEMBRE 2026
B5: TOTAL TALENTO HUMANO Y HONORARIOS | E5: NÓMINA FIJA Y SERVICIOS TEMPORALES | I5: HONORARIOS Y GESTIÓN DIRECTIVA | L5: TURNOS OPERATIVOS EN EFECTIVO | O5: Nº PAGOS REGISTRADOS
B6: =$E$27 -> 49772637 | E6: =$E$11+$E$12 -> 39220837 | I6: =$E$13+$E$14+$E$15+$E$16 -> 5944800 | L6: =SUM(E17:E22) -> 3063200 | O6: =$D$27 -> 89
B7: Nómina + Temporales + Honorarios + Turnos + Gestión | E7: 4 Quincenas BBVA + 2 Facturas GIT (Agosto y Sept) | I7: Contadora, Antonio, Arturo, Eliana | L7: Turnos caja menor: salón, cocina y fin de semana | O7: Transacciones personal
B9: 1. RESUMEN EJECUTIVO POR MODALIDAD DE CONTRATACIÓN Y BENEFICIARIO | I9: 2. REGISTRO CRONOLÓGICO Y DETALLADO DÍA A DÍA (DETALLE DE TRANSACCIONES)
B10: Concepto / Beneficiario | C10: Modalidad Contractual | D10: Nº Pagos | E10: Total Mes ($) | F10: % Part. | G10: Promedio Pago ($) | I10: Día | J10: Soporte / Fac | K10: Beneficiario / Personal | L10: Concepto / Modalidad | M10: Descripción Detallada | N10: Vr. Pagado ($) | O10: Fuente / Observaciones
B11: Nómina Bancaria 1ra Quincena (BBVA) | C11: Nómina Quincenal Fija | D11: =COUNTIF('Detalle Compras Septiembre 2026'!$H$569:$H$635, "TR-BBVA-1509") -> 4 | E11: =SUMIF('Detalle Compras Septiembre 2026'!$H$569:$H$635, "TR-BBVA-1509", 'Detalle Compras Septiembre 2026'!$G$569:$G$635) -> 4302852 | F11: =IF($E$27>0, E11/$E$27, 0) -> 0.086450151 | G11: =IF(D11>0, E11/D11, 0) -> 1075713 | I11: 7 | J11: Libro de Caja | K11: Arturo Díaz | L11: Gestión Directiva | M11: Devolución Señor Arturo Principal (Johanna) | N11: ='Detalle Compras Septiembre 2026'!G174 -> 90000 | O11: Efectivo Caja Menor
B12: Servicios Temporales Nómina (GIT) | C12: Temporal / AIU Planta | D12: 3 | E12: ='Detalle Compras Septiembre 2026'!$G$377+'Detalle Compras Septiembre 2026'!$G$642+'Detalle Compras Septiembre 2026'!$G$643 -> 34917985 | F12: =IF($E$27>0, E12/$E$27, 0) -> 0.70154983 | G12: =IF(D12>0, E12/D12, 0) -> 11639328 | I12: 7 | J12: RCM-07-Sep-2026 | K12: Arturo Díaz | L12: Gestión Directiva | M12: Encomienda Arturo (Recibo Caja Menor 07-Sep-2026) | N12: ='Detalle Compras Septiembre 2026'!G185 -> 74000 | O12: Caja Menor
B13: Honorarios Contadora Pública | C13: Honorarios Profesionales | D13: 3 | E13: ='Detalle Compras Septiembre 2026'!$G$374+'Detalle Compras Septiembre 2026'!$G$397+'Detalle Compras Septiembre 2026'!$G$484 -> 2400000 | F13: =IF($E$27>0, E13/$E$27, 0) -> 0.048219266 | G13: =IF(D13>0, E13/D13, 0) -> 800000 | I13: 7 | J13: Libro de Caja | K13: Marleny | L13: Turno Operativo | M13: Turno Marleny Domicilios (Carolina) | N13: ='Detalle Compras Septiembre 2026'!G190 -> 66000 | O13: Efectivo Caja Menor
B14: Gestión y Dirección (Antonio Díaz) | C14: Gestión Directiva / Apoyo | D14: 2 | E14: ='Detalle Compras Septiembre 2026'!$G$344+'Detalle Compras Septiembre 2026'!$G$392 -> 310000 | F14: =IF($E$27>0, E14/$E$27, 0) -> 0.0062283218 | G14: =IF(D14>0, E14/D14, 0) -> 155000 | I14: 7 | J14: Libro de Caja | K14: Jhonatan | L14: Vale Descontable | M14: Crédito Jhonatan Domicilios (Carolina) | N14: ='Detalle Compras Septiembre 2026'!G193 -> 4000 | O14: Anticipo Empleado
B15: Retiros y Encomiendas (Don Arturo) | C15: Retiro Socio / Encomiendas | D15: 6 | E15: ='Detalle Compras Septiembre 2026'!$G$174+'Detalle Compras Septiembre 2026'!$G$185+'Detalle Compras Septiembre 2026'!$G$194+'Detalle Compras Septiembre 2026'!$G$318+'Detalle Compras Septiembre 2026'!$G$692+'Detalle Compras Septiembre 2026'!$G$693 -> 1740800 | F15: =IF($E$27>0, E15/$E$27, 0) -> 0.034975041 | G15: =IF(D15>0, E15/D15, 0) -> 290133.33 | I15: 7 | J15: Libro de Caja | K15: Arturo Díaz | L15: Gestión Directiva | M15: Devolución Señor Arturo Domicilios (Carolina) | N15: ='Detalle Compras Septiembre 2026'!G194 -> 85000 | O15: Salida Caja Menor
B16: Honorarios Operativos (Eliana) | C16: Honorarios / Cuenta Cobro | D16: 2 | E16: ='Detalle Compras Septiembre 2026'!$G$373+'Detalle Compras Septiembre 2026'!$G$687 -> 1494000 | F16: =IF($E$27>0, E16/$E$27, 0) -> 0.030016493 | G16: =IF(D16>0, E16/D16, 0) -> 747000 | I16: 7 | J16: Libro de Caja | K16: Carolina | L16: Transporte Personal | M16: Transporte Carolina Domicilios (Carolina) | N16: ='Detalle Compras Septiembre 2026'!G195 -> 15000 | O16: Transporte Operativo
B17: Turnos de Personal - Marleny | C17: Turno Operativo Salón/Cocina | D17: 11 | E17: ='Detalle Compras Septiembre 2026'!$G$190+'Detalle Compras Septiembre 2026'!$G$253+'Detalle Compras Septiembre 2026'!$G$316+'Detalle Compras Septiembre 2026'!$G$343+'Detalle Compras Septiembre 2026'!$G$354+'Detalle Compras Septiembre 2026'!$G$603+'Detalle Compras Septiembre 2026'!$G$611+'Detalle Compras Septiembre 2026'!$G$617+'Detalle Compras Septiembre 2026'!$G$635+'Detalle Compras Septiembre 2026'!$G$696+'Detalle Compras Septiembre 2026'!$G$710 -> 718000 | F17: =IF($E$27>0, E17/$E$27, 0) -> 0.014425597 | G17: =IF(D17>0, E17/D17, 0) -> 65272.727 | I17: SUBTOTAL DÍA 7 (6 pagos) | N17: =SUM(N11:N16) -> 334000
B18: Turnos de Personal - Andrés | C18: Turno Operativo Salón/Apoyo | D18: 9 | E18: ='Detalle Compras Septiembre 2026'!$G$251+'Detalle Compras Septiembre 2026'!$G$314+'Detalle Compras Septiembre 2026'!$G$350+'Detalle Compras Septiembre 2026'!$G$387+'Detalle Compras Septiembre 2026'!$G$589+'Detalle Compras Septiembre 2026'!$G$604+'Detalle Compras Septiembre 2026'!$G$631+'Detalle Compras Septiembre 2026'!$G$690+'Detalle Compras Septiembre 2026'!$G$711 -> 594000 | F18: =IF($E$27>0, E18/$E$27, 0) -> 0.011934268 | G18: =IF(D18>0, E18/D18, 0) -> 66000 | I18: 8 | J18: Libro de Caja | K18: Andrés | L18: Turno Operativo | M18: Turno Andrés Principal (Johanna) | N18: ='Detalle Compras Septiembre 2026'!G251 -> 66000 | O18: Efectivo Caja Menor
B19: Turnos de Personal - Sebastián | C19: Turno Operativo Salón/Servicio | D19: 10 | E19: ='Detalle Compras Septiembre 2026'!$G$315+'Detalle Compras Septiembre 2026'!$G$351+'Detalle Compras Septiembre 2026'!$G$388+'Detalle Compras Septiembre 2026'!$G$591+'Detalle Compras Septiembre 2026'!$G$614+'Detalle Compras Septiembre 2026'!$G$630+'Detalle Compras Septiembre 2026'!$G$691+'Detalle Compras Septiembre 2026'!$G$697+'Detalle Compras Septiembre 2026'!$G$702+'Detalle Compras Septiembre 2026'!$G$712 -> 660000 | F19: =IF($E$27>0, E19/$E$27, 0) -> 0.013260298 | G19: =IF(D19>0, E19/D19, 0) -> 66000 | I19: 8 | J19: Libro de Caja | K19: Diego / Luigui | L19: Turno Operativo | M19: Turno Diego / Luigui Principal (Johanna) | N19: ='Detalle Compras Septiembre 2026'!G252 -> 66000 | O19: Efectivo Caja Menor
B20: Turnos de Personal - Wilson | C20: Turno Operativo Salón/Servicio | D20: 6 | E20: ='Detalle Compras Septiembre 2026'!$G$254+'Detalle Compras Septiembre 2026'!$G$389+'Detalle Compras Septiembre 2026'!$G$590+'Detalle Compras Septiembre 2026'!$G$689+'Detalle Compras Septiembre 2026'!$G$703+'Detalle Compras Septiembre 2026'!$G$713 -> 462000 | F20: =IF($E$27>0, E20/$E$27, 0) -> 0.0092822086 | G20: =IF(D20>0, E20/D20, 0) -> 77000 | I20: 8 | J20: Libro de Caja | K20: Marleny | L20: Turno Operativo | M20: Turno Marleny Domicilios (Neymar) | N20: ='Detalle Compras Septiembre 2026'!G253 -> 66000 | O20: Efectivo Caja Menor
B21: Seguridad y Vigilancia (Fredy Toty / Taty) | C21: Turno Nocturno / Vigilancia | D21: 2 | E21: ='Detalle Compras Septiembre 2026'!$G$352+'Detalle Compras Septiembre 2026'!$G$619 -> 140000 | F21: =IF($E$27>0, E21/$E$27, 0) -> 0.0028127905 | G21: =IF(D21>0, E21/D21, 0) -> 70000 | I21: 8 | J21: Libro de Caja | K21: Wilson | L21: Turno Operativo | M21: Wilson (Lunes y Martes) Principal (Johanna) - 2 días | N21: ='Detalle Compras Septiembre 2026'!G254 -> 132000 | O21: Efectivo Caja Menor
B22: Otros Turnos y Refuerzos Operativos | C22: Turnos y Horas Apoyo (Leyton/Martha/Lucero) | D22: 6 | E22: ='Detalle Compras Septiembre 2026'!$G$252+'Detalle Compras Septiembre 2026'!$G$414+'Detalle Compras Septiembre 2026'!$G$415+'Detalle Compras Septiembre 2026'!$G$618+'Detalle Compras Septiembre 2026'!$G$685+'Detalle Compras Septiembre 2026'!$G$706 -> 489200 | F22: =IF($E$27>0, E22/$E$27, 0) -> 0.0098286936 | G22: =IF(D22>0, E22/D22, 0) -> 81533.333 | I22: 8 | J22: Libro de Caja | K22: José David | L22: Vale Descontable | M22: Crédito José David Domicilios (Neymar) | N22: ='Detalle Compras Septiembre 2026'!G257 -> 20000 | O22: Anticipo Empleado
B23: Incentivos Laborales y Abonos | C23: Incentivo / Abono Cuenta Cobro | D23: 2 | E23: ='Detalle Compras Septiembre 2026'!$G$491+'Detalle Compras Septiembre 2026'!$G$492 -> 900000 | F23: =IF($E$27>0, E23/$E$27, 0) -> 0.018082225 | G23: =IF(D23>0, E23/D23, 0) -> 450000 | I23: SUBTOTAL DÍA 8 (5 pagos) | N23: =SUM(N18:N22) -> 350000
B24: Auxilio de Transporte de Personal | C24: Apoyo Transporte Operativo | D24: 10 | E24: ='Detalle Compras Septiembre 2026'!$G$195+'Detalle Compras Septiembre 2026'!$G$335+'Detalle Compras Septiembre 2026'!$G$347+'Detalle Compras Septiembre 2026'!$G$353+'Detalle Compras Septiembre 2026'!$G$379+'Detalle Compras Septiembre 2026'!$G$494+'Detalle Compras Septiembre 2026'!$G$698+'Detalle Compras Septiembre 2026'!$G$699+'Detalle Compras Septiembre 2026'!$G$700+'Detalle Compras Septiembre 2026'!$G$701 -> 305500 | F24: =IF($E$27>0, E24/$E$27, 0) -> 0.0061379107 | G24: =IF(D24>0, E24/D24, 0) -> 30550 | I24: 9 | J24: Libro de Caja | K24: Andrés | L24: Turno Operativo | M24: Turno Andrés Principal (Johanna) | N24: ='Detalle Compras Septiembre 2026'!G314 -> 66000 | O24: Efectivo Caja Menor
B25: Anticipos y Vales Empleados | C25: Préstamo Menor Descontable | D25: 7 | E25: ='Detalle Compras Septiembre 2026'!$G$193+'Detalle Compras Septiembre 2026'!$G$257+'Detalle Compras Septiembre 2026'!$G$593+'Detalle Compras Septiembre 2026'!$G$610+'Detalle Compras Septiembre 2026'!$G$707+'Detalle Compras Septiembre 2026'!$G$708+'Detalle Compras Septiembre 2026'!$G$709 -> 88800 | F25: =IF($E$27>0, E25/$E$27, 0) -> 0.0017841128 | G25: =IF(D25>0, E25/D25, 0) -> 12685.714 | I25: 9 | J25: Libro de Caja | K25: Sebastián | L25: Turno Operativo | M25: Turno Sebastián Principal (Johanna) | N25: ='Detalle Compras Septiembre 2026'!G315 -> 66000 | O25: Efectivo Caja Menor
B26: Salud Ocupacional y Exámenes Médicos (IPS) | C26: Exámenes Médicos Ingreso | D26: 6 | E26: =SUM('Detalle Compras Septiembre 2026'!$G$636:$G$641) -> 249500 | F26: =IF($E$27>0, E26/$E$27, 0) -> 0.0050127945 | G26: =IF(D26>0, E26/D26, 0) -> 41583.333 | I26: 9 | J26: Libro de Caja | K26: Marleny | L26: Turno Operativo | M26: Turno Marleny Domicilios (María) | N26: ='Detalle Compras Septiembre 2026'!G316 -> 66000 | O26: Efectivo Caja Menor
B27: TOTAL CONSOLIDADO TALENTO HUMANO Y HONORARIOS | C27: Todas las modalidades | D27: =SUM(D11:D26) -> 89 | E27: =SUM(E11:E26) -> 49772637 | F27: =SUM(F11:F26) -> 1 | G27: =IF(D27>0, E27/D27, 0) -> 559243.11 | I27: 9 | J27: Libro de Caja | K27: Arturo Díaz | L27: Gestión Directiva | M27: Don Arturo recogió Domicilios (María) | N27: ='Detalle Compras Septiembre 2026'!G318 -> 500000 | O27: Retiro Efectivo Caja
I28: SUBTOTAL DÍA 9 (4 pagos) | N28: =SUM(N24:N27) -> 698000
I29: 10 | J29: RCM-10-Sep-2026-7 | K29: Marleny | L29: Transporte Personal | M29: MARLENY - TRANSPORTE MAÑANA (Recibo Caja Menor) | N29: ='Detalle Compras Septiembre 2026'!G335 -> 20000 | O29: Apoyo Transporte
I30: 10 | J30: RCM-10-Sep-2026-5 | K30: Marleny | L30: Turno Operativo | M30: MARLENE - 7 HORAS (Recibo Caja Menor 10/09/2026) | N30: ='Detalle Compras Septiembre 2026'!G343 -> 58000 | O30: Recibo Oficial Caja
I31: 10 | J31: RCM-10-Sep-2026-4 | K31: Antonio Díaz | L31: Gestión Directiva | M31: ANTONIO L. DIAZ - TAXI DILIGENCIAS (Recibo Caja Menor) | N31: ='Detalle Compras Septiembre 2026'!G344 -> 10000 | O31: Recibo Oficial Caja
I32: 10 | J32: RCM-10-Sep-2026-1 | K32: Edith | L32: Transporte Personal | M32: TRANSPORTE EDITH (Recibo Caja Menor Marfil 10/09/26) | N32: ='Detalle Compras Septiembre 2026'!G347 -> 50000 | O32: Recibo Oficial Caja
I33: 10 | J33: Libro de Caja | K33: Andrés | L33: Turno Operativo | M33: Turno Andrés Principal (Johanna) | N33: ='Detalle Compras Septiembre 2026'!G350 -> 66000 | O33: Efectivo Caja Menor
I34: 10 | J34: Libro de Caja | K34: Sebastián | L34: Turno Operativo | M34: Turno Sebastián Principal (Johanna) | N34: ='Detalle Compras Septiembre 2026'!G351 -> 66000 | O34: Efectivo Caja Menor
I35: 10 | J35: Libro de Caja | K35: Taty Vigilancia | L35: Seguridad / Vigilancia | M35: Turno Taty Vigilancia Domicilios (Neymar) | N35: ='Detalle Compras Septiembre 2026'!G352 -> 70000 | O35: Efectivo Caja Menor
I36: 10 | J36: Libro de Caja | K36: Deys | L36: Transporte Personal | M36: Transporte Deys Domicilios (Neymar) | N36: ='Detalle Compras Septiembre 2026'!G353 -> 28000 | O36: Efectivo Caja Menor
I37: 10 | J37: Libro de Caja | K37: Marleny | L37: Turno Operativo | M37: Turno Marleny Domicilios (Neymar) | N37: ='Detalle Compras Septiembre 2026'!G354 -> 66000 | O37: Efectivo Caja Menor
I38: SUBTOTAL DÍA 10 (9 pagos) | N38: =SUM(N29:N37) -> 434000
I39: 11 | J39: Cuenta de Cobro | K39: Eliana | L39: Honorarios Operativos | M39: Pago de Servicios Eliana (Cuenta de Cobro) | N39: ='Detalle Compras Septiembre 2026'!G373 -> 1149000 | O39: Cuenta de Cobro
I40: 11 | J40: Cuaderno Don Arturo | K40: Contadora Pública | L40: Honorarios Contadora | M40: Honorarios Contadora (Cuaderno Don Arturo) | N40: ='Detalle Compras Septiembre 2026'!G374 -> 1200000 | O40: Asesoría Contable
I41: 11 | J41: FELE11955 | K41: GIT Organizacional | L41: Servicios Temporales | M41: SERVICIOS TEMPORALES + AIU (Factura FELE11955 - Agosto 16-31) | N41: ='Detalle Compras Septiembre 2026'!G377 -> 16523800 | O41: Factura Electrónica
I42: 11 | J42: Cuaderno Don Arturo | K42: Danilo | L42: Transporte Personal | M42: Transporte Danilo (Cuaderno Don Arturo) | N42: ='Detalle Compras Septiembre 2026'!G379 -> 15000 | O42: Apoyo Transporte
I43: 11 | J43: Libro de Caja | K43: Andrés | L43: Turno Operativo | M43: Turno Andrés Principal (Johanna/Wilson) | N43: ='Detalle Compras Septiembre 2026'!G387 -> 66000 | O43: Efectivo Caja Menor
I44: 11 | J44: Libro de Caja | K44: Sebastián | L44: Turno Operativo | M44: Turno Sebastián Principal (Johanna/Wilson) | N44: ='Detalle Compras Septiembre 2026'!G388 -> 66000 | O44: Efectivo Caja Menor
I45: 11 | J45: Libro de Caja | K45: Wilson | L45: Turno Operativo | M45: Turno Wilson Principal (Johanna/Wilson) | N45: ='Detalle Compras Septiembre 2026'!G389 -> 66000 | O45: Efectivo Caja Menor
I46: 11 | J46: Libro de Caja | K46: Antonio Díaz | L46: Gestión Directiva | M46: Pago Antonio (Caja Menor Johanna/Wilson) | N46: ='Detalle Compras Septiembre 2026'!G392 -> 300000 | O46: Efectivo Caja Menor
I47: 11 | J47: Fac 039427 | K47: Contadora Pública | L47: Honorarios Contadora | M47: Honorarios como contadora pública 01 al 31 de agosto | N47: ='Detalle Compras Septiembre 2026'!G397 -> 900000 | O47: Cuenta de Cobro Oficial
I48: 11 | J48: S/N | K48: Marleny | L48: Turnos Operativos | M48: Turno Marleny Domicilios (Carolina) | N48: ='Detalle Compras Septiembre 2026'!G414 -> 66000 | O48: Planilla Caja Menor
I49: 11 | J49: S/N | K49: Marleny | L49: Turnos Operativos | M49: Marleny 6 Horas Adicionales Domicilios | N49: ='Detalle Compras Septiembre 2026'!G415 -> 49500 | O49: Planilla Caja Menor
I50: 11 | J50: Libro de Caja | K50: Eliana Garcés | L50: Honorarios Operativos | M50: Eliana Garcés (ela cobra) - Pago efectivo caja menor | N50: ='Detalle Compras Septiembre 2026'!G687 -> 345000 | O50: Efectivo Caja Menor
I51: SUBTOTAL DÍA 11 (12 pagos) | N51: =SUM(N39:N50) -> 20746300
I52: 12 | J52: Libro de Caja | K52: Wilson | L52: Turno Operativo | M52: Turno Wilson Principal pagado en efectivo | N52: ='Detalle Compras Septiembre 2026'!G689 -> 66000 | O52: Efectivo Caja Menor
I53: 12 | J53: Libro de Caja | K53: Andrés | L53: Turno Operativo | M53: Turno Andrés Principal pagado en efectivo | N53: ='Detalle Compras Septiembre 2026'!G690 -> 66000 | O53: Efectivo Caja Menor
I54: 12 | J54: Libro de Caja | K54: Sebastián | L54: Turno Operativo | M54: Turno Sebastián Principal pagado en efectivo | N54: ='Detalle Compras Septiembre 2026'!G691 -> 66000 | O54: Efectivo Caja Menor
I55: 12 | J55: Libro de Caja | K55: Arturo Díaz | L55: Gestión Directiva | M55: Don Arturo recogió efectivo socio (Caja Menor) | N55: ='Detalle Compras Septiembre 2026'!G692 -> 750000 | O55: Retiro Efectivo Socio
I56: 12 | J56: Libro de Caja | K56: Arturo Díaz | L56: Gestión Directiva | M56: Crédito Don Arturo (Vale de caja menor) | N56: ='Detalle Compras Septiembre 2026'!G693 -> 241800 | O56: Vale de Caja Menor
I57: 12 | J57: Libro de Caja | K57: Marleny | L57: Turno Operativo | M57: Turno Marleny Domicilios pagado en efectivo | N57: ='Detalle Compras Septiembre 2026'!G696 -> 66000 | O57: Efectivo Caja Menor
I58: 12 | J58: Libro de Caja | K58: Sebastián | L58: Turno Operativo | M58: Turno Sebastián Domicilios pagado en efectivo | N58: ='Detalle Compras Septiembre 2026'!G697 -> 66000 | O58: Efectivo Caja Menor
I59: 12 | J59: Libro de Caja | K59: Lina | L59: Transporte Personal | M59: Transporte Lina Domicilios (Caja menor) | N59: ='Detalle Compras Septiembre 2026'!G698 -> 40000 | O59: Apoyo Transporte
I60: 12 | J60: Libro de Caja | K60: Danilo | L60: Transporte Personal | M60: Transporte 2 días Danilo Domicilios (Caja menor) | N60: ='Detalle Compras Septiembre 2026'!G699 -> 30000 | O60: Apoyo Transporte
I61: 12 | J61: Libro de Caja | K61: Deicy | L61: Transporte Personal | M61: Transporte Deicy Domicilios (Caja menor) | N61: ='Detalle Compras Septiembre 2026'!G700 -> 27500 | O61: Apoyo Transporte
I62: 12 | J62: Libro de Caja | K62: Enith | L62: Transporte Personal | M62: Transporte Enith Domicilios (Caja menor) | N62: ='Detalle Compras Septiembre 2026'!G701 -> 50000 | O62: Apoyo Transporte
I63: SUBTOTAL DÍA 12 (11 pagos) | N63: =SUM(N52:N62) -> 1469300
I64: 13 | J64: Libro de Caja | K64: Sebastián | L64: Turno Operativo | M64: Turno Sebastián Principal pagado en efectivo | N64: ='Detalle Compras Septiembre 2026'!G702 -> 66000 | O64: Efectivo Caja Menor
I65: 13 | J65: Libro de Caja | K65: Wilson | L65: Turno Operativo | M65: Turno Wilson Principal pagado en efectivo | N65: ='Detalle Compras Septiembre 2026'!G703 -> 66000 | O65: Efectivo Caja Menor
I66: 13 | J66: Libro de Caja | K66: Martha Collazos | L66: Turnos Operativos | M66: Turno Martha Collazos Domicilios en efectivo | N66: ='Detalle Compras Septiembre 2026'!G706 -> 70000 | O66: Efectivo Caja Menor
I67: 13 | J67: Libro de Caja | K67: Carolina | L67: Vale Descontable | M67: Crédito Carolina (Vale de caja menor) | N67: ='Detalle Compras Septiembre 2026'!G707 -> 22500 | O67: Anticipo Empleado
I68: 13 | J68: Libro de Caja | K68: Daniela | L68: Vale Descontable | M68: Crédito Daniela (Vale de caja menor) | N68: ='Detalle Compras Septiembre 2026'!G708 -> 9000 | O68: Anticipo Empleado
I69: 13 | J69: Libro de Caja | K69: María Bertilda | L69: Vale Descontable | M69: Crédito María Bertilda (Vale de caja menor) | N69: ='Detalle Compras Septiembre 2026'!G709 -> 24500 | O69: Anticipo Empleado
I70: 13 | J70: Libro de Caja | K70: Marleny | L70: Turno Operativo | M70: Turno Marleny Cocina Domicilios en efectivo | N70: ='Detalle Compras Septiembre 2026'!G710 -> 66000 | O70: Efectivo Caja Menor
I71: SUBTOTAL DÍA 13 (7 pagos) | N71: =SUM(N64:N70) -> 324000
I72: 14 | J72: Cuenta de Cobro | K72: Contadora Pública | L72: Honorarios Contadora | M72: Por concepto de declaración de renta (Cuenta de Cobro) | N72: ='Detalle Compras Septiembre 2026'!G484 -> 300000 | O72: Asesoría Tributaria
I73: 14 | J73: FELE12018 | K73: GIT Organizacional | L73: Servicios Temporales | M73: SERVICIOS TEMPORALES SEPTIEMBRE 01 AL 15 (Factura FELE12018) | N73: ='Detalle Compras Septiembre 2026'!G642 -> 16246091 | O73: Factura Electrónica
I74: 14 | J74: FELE12018 | K74: GIT Organizacional | L74: Servicios Temporales | M74: AIU FISCAL + IVA RÉGIMEN ESPECIAL (Factura FELE12018) | N74: ='Detalle Compras Septiembre 2026'!G643 -> 2148094 | O74: Factura Electrónica
I75: 14 | J75: Libro de Caja | K75: Andrés | L75: Turno Operativo | M75: Turno Andrés Principal pagado en efectivo | N75: ='Detalle Compras Septiembre 2026'!G711 -> 66000 | O75: Efectivo Caja Menor
I76: 14 | J76: Libro de Caja | K76: Sebastián | L76: Turno Operativo | M76: Turno Sebastián Principal pagado en efectivo | N76: ='Detalle Compras Septiembre 2026'!G712 -> 66000 | O76: Efectivo Caja Menor
I77: 14 | J77: Libro de Caja | K77: Wilson | L77: Turno Operativo | M77: Turno Wilson Principal pagado en efectivo | N77: ='Detalle Compras Septiembre 2026'!G713 -> 66000 | O77: Efectivo Caja Menor
I78: SUBTOTAL DÍA 14 (6 pagos) | N78: =SUM(N72:N77) -> 18892185
I79: 15 | J79: TR-BBVA-1509 | K79: Jacqueline Jiménez Burbano | L79: Nómina Bancaria | M79: PAGO NOMINA 1RA QUINCENA SEPTIEMBRE (Transferencia BBVA) | N79: ='Detalle Compras Septiembre 2026'!G575 -> 897464 | O79: Bancario 1ra Quincena
I80: 15 | J80: TR-BBVA-1509 | K80: Juan David Aguirre Piamba | L80: Nómina Bancaria | M80: PAGO NOMINA 1RA QUINCENA SEPTIEMBRE (Transferencia BBVA) | N80: ='Detalle Compras Septiembre 2026'!G576 -> 892864 | O80: Bancario 1ra Quincena
I81: 15 | J81: TR-BBVA-1509 | K81: Enith Mosquera Mosquera | L81: Nómina Bancaria | M81: PAGO NOMINA 1RA QUINCENA SEPTIEMBRE (Transferencia BBVA) | N81: ='Detalle Compras Septiembre 2026'!G577 -> 897464 | O81: Bancario 1ra Quincena
I82: 15 | J82: TR-BBVA-1509 | K82: Mary Luz Henao Hernández | L82: Nómina Bancaria | M82: PAGO NOMINA 1RA QUINCENA SEPTIEMBRE (Transferencia BBVA) | N82: ='Detalle Compras Septiembre 2026'!G578 -> 1615060 | O82: Bancario 1ra Quincena
I83: 15 | J83: Libro de Caja | K83: Andrés | L83: Turno Operativo | M83: Turno Andrés pagado en efectivo de caja menor | N83: ='Detalle Compras Septiembre 2026'!G589 -> 66000 | O83: Efectivo Caja Menor
I84: 15 | J84: Libro de Caja | K84: Wilson | L84: Turno Operativo | M84: Turno Wilson pagado en efectivo de caja menor | N84: ='Detalle Compras Septiembre 2026'!G590 -> 66000 | O84: Efectivo Caja Menor
I85: 15 | J85: Libro de Caja | K85: Sebastián | L85: Turno Operativo | M85: Turno Sebastián pagado en efectivo de caja menor | N85: ='Detalle Compras Septiembre 2026'!G591 -> 66000 | O85: Efectivo Caja Menor
I86: 15 | J86: Libro de Caja | K86: Joan David | L86: Vale Descontable | M86: Vale / anticipo empleado Joan David | N86: ='Detalle Compras Septiembre 2026'!G593 -> 5000 | O86: Anticipo Empleado
I87: 15 | J87: Libro de Caja | K87: Marleny | L87: Turno Operativo | M87: Turno Marleny pagado en efectivo | N87: ='Detalle Compras Septiembre 2026'!G603 -> 66000 | O87: Efectivo Caja Menor
I88: 15 | J88: FE2553 | K88: Health Care IPS S.A.S. | L88: Salud Ocupacional | M88: Examen Coprológico ingreso (Factura FE2553) | N88: ='Detalle Compras Septiembre 2026'!G636 -> 11000 | O88: Salud Ocupacional
I89: 15 | J89: FE2553 | K89: Health Care IPS S.A.S. | L89: Salud Ocupacional | M89: Examen Frotis Faríngeo ingreso (Factura FE2553) | N89: ='Detalle Compras Septiembre 2026'!G637 -> 11000 | O89: Salud Ocupacional
I90: 15 | J90: FE2553 | K90: Health Care IPS S.A.S. | L90: Salud Ocupacional | M90: Examen Hongos KOH ingreso (Factura FE2553) | N90: ='Detalle Compras Septiembre 2026'!G638 -> 11000 | O90: Salud Ocupacional
I91: 15 | J91: FE2553 | K91: Health Care IPS S.A.S. | L91: Salud Ocupacional | M91: Evaluación Médica Pre-Ingreso (Factura FE2553) | N91: ='Detalle Compras Septiembre 2026'!G639 -> 63000 | O91: Salud Ocupacional
I92: 15 | J92: FE2553 | K92: Health Care IPS S.A.S. | L92: Salud Ocupacional | M92: Panel Drogas de Abuso (Factura FE2553) | N92: ='Detalle Compras Septiembre 2026'!G640 -> 46500 | O92: Salud Ocupacional
I93: 15 | J93: FE2553 | K93: Health Care IPS S.A.S. | L93: Salud Ocupacional | M93: Evaluación Médica Ocupacional Periódica (Factura FE2553) | N93: ='Detalle Compras Septiembre 2026'!G641 -> 107000 | O93: Salud Ocupacional
I94: SUBTOTAL DÍA 15 (15 pagos) | N94: =SUM(N79:N93) -> 4821352
I95: 16 | J95: S/N | K95: Personal Operativo | L95: Incentivos Laborales | M95: Pago Incentivo Mes de Agosto / 26 | N95: ='Detalle Compras Septiembre 2026'!G491 -> 100000 | O95: Bonificación Personal
I96: 16 | J96: S/N | K96: Personal / Servicios | L96: Abonos Laborales | M96: Abono cuenta de cobro saldo $ 345.000 | N96: ='Detalle Compras Septiembre 2026'!G492 -> 800000 | O96: Abono Cuenta Cobro
I97: 16 | J97: S/N | K97: Personal Operativo | L97: Transporte Personal | M97: 2 días de transporte de personal | N97: ='Detalle Compras Septiembre 2026'!G494 -> 30000 | O97: Apoyo Transporte
I98: 16 | J98: Libro de Caja | K98: Andrés | L98: Turno Operativo | M98: Turno Andrés pagado en efectivo | N98: ='Detalle Compras Septiembre 2026'!G604 -> 66000 | O98: Efectivo Caja Menor
I99: 16 | J99: Libro de Caja | K99: Neymar | L99: Vale Descontable | M99: Vale / anticipo empleado Neymar | N99: ='Detalle Compras Septiembre 2026'!G610 -> 3800 | O99: Anticipo Empleado
I100: 16 | J100: Libro de Caja | K100: Marleny | L100: Turno Operativo | M100: Turno Marleny pagado en efectivo | N100: ='Detalle Compras Septiembre 2026'!G611 -> 66000 | O100: Efectivo Caja Menor
I101: SUBTOTAL DÍA 16 (6 pagos) | N101: =SUM(N95:N100) -> 1065800
I102: 17 | J102: Libro de Caja | K102: Sebastián | L102: Turno Operativo | M102: Turno Sebastián pagado en efectivo | N102: ='Detalle Compras Septiembre 2026'!G614 -> 66000 | O102: Efectivo Caja Menor
I103: 17 | J103: Libro de Caja | K103: Marleny | L103: Turno Operativo | M103: Turno Marleny pagado en efectivo | N103: ='Detalle Compras Septiembre 2026'!G617 -> 66000 | O103: Efectivo Caja Menor
...

Sheet Detalle Ventas Septiembre 2026
A1: Día | B1: Fecha | C1: Código | D1: Categoría | E1: Producto | F1: Unidad | G1: Cantidad Vendida | H1: Precio Unitario Neto | I1: Venta Bruta | J1: Descuentos | K1: Venta Neta | L1: Impoconsumo (8%) | M1: Gran Total Facturado | N1: % Part. Día | O1: Proveedor / Emisor Factura
A2: 1 | B2: 01/09/2026 | C2: 73 | D2: Bebidas | E2: Agua tarro | F2: ud | G2: 13 | H2: 2593 | I2: 33704 | J2: 0 | K2: 33704 | L2: 2696 | M2: 36400 | N2: 0.0054 | O2: Restaurante Choclos y Asados La Finca S.A.S.
A3: 1 | B3: 01/09/2026 | C3: 65 | D3: Bebidas | E3: Aguacate porc | F3: ud | G3: 2 | H3: 2778 | I3: 5556 | J3: 0 | K3: 5556 | L3: 444 | M3: 6000 | N3: 0.0009 | O3: Restaurante Choclos y Asados La Finca S.A.S.
A4: 1 | B4: 01/09/2026 | C4: 1 | D4: Platos Fuertes / Carnes | E4: Albondigas | F4: ud | G4: 22 | H4: 18729 | I4: 415741 | J4: 3704 | K4: 412037 | L4: 32963 | M4: 445000 | N4: 0.0656 | O4: Restaurante Choclos y Asados La Finca S.A.S.
A5: 1 | B5: 01/09/2026 | C5: 12 | D5: Pescados y Mariscos | E5: Arroz con camaron | F5: ud | G5: 7 | H5: 41667 | I5: 291667 | J5: 0 | K5: 291667 | L5: 23333 | M5: 315000 | N5: 0.0464 | O5: Restaurante Choclos y Asados La Finca S.A.S.
A6: 1 | B6: 01/09/2026 | C6: 104 | D6: Especialidades Típicas | E6: Bandeja sola | F6: ud | G6: 9 | H6: 15844 | I6: 144444 | J6: 1852 | K6: 142592 | L6: 11407 | M6: 153999 | N6: 0.0227 | O6: Restaurante Choclos y Asados La Finca S.A.S.
A7: 1 | B7: 01/09/2026 | C7: 95 | D7: Platos Fuertes / Carnes | E7: Bao | F7: ud | G7: 2 | H7: 926 | I7: 1852 | J7: 0 | K7: 1852 | L7: 148 | M7: 2000 | N7: 0.0003 | O7: Restaurante Choclos y Asados La Finca S.A.S.
A8: 1 | B8: 01/09/2026 | C8: 136 | D8: Especialidades Típicas | E8: Calentado chicharron | F8: ud | G8: 1 | H8: 24074 | I8: 24074 | J8: 0 | K8: 24074 | L8: 1926 | M8: 26000 | N8: 0.0038 | O8: Restaurante Choclos y Asados La Finca S.A.S.
A9: 1 | B9: 01/09/2026 | C9: 8 | D9: Platos Fuertes / Carnes | E9: Carne molida | F9: ud | G9: 11 | H9: 18855 | I9: 207407 | J9: 0 | K9: 207407 | L9: 16593 | M9: 224000 | N9: 0.033 | O9: Restaurante Choclos y Asados La Finca S.A.S.
A10: 1 | B10: 01/09/2026 | C10: 311 | D10: Pescados y Mariscos | E10: Cazuela de camaron | F10: ud | G10: 2 | H10: 44907 | I10: 89815 | J10: 0 | K10: 89815 | L10: 7185 | M10: 97000 | N10: 0.0143 | O10: Restaurante Choclos y Asados La Finca S.A.S.
A11: 1 | B11: 01/09/2026 | C11: 87 | D11: Especialidades Típicas | E11: Cazuela frijol | F11: ud | G11: 2 | H11: 37500 | I11: 75000 | J11: 0 | K11: 75000 | L11: 6000 | M11: 81000 | N11: 0.0119 | O11: Restaurante Choclos y Asados La Finca S.A.S.
A12: 1 | B12: 01/09/2026 | C12: 206 | D12: Pescados y Mariscos | E12: Cazuela mariscos | F12: ud | G12: 2 | H12: 44907 | I12: 89815 | J12: 0 | K12: 89815 | L12: 7185 | M12: 97000 | N12: 0.0143 | O12: Restaurante Choclos y Asados La Finca S.A.S.
A13: 1 | B13: 01/09/2026 | C13: 13 | D13: Platos Fuertes / Carnes | E13: Cerdo ejecutivo | F13: ud | G13: 2 | H13: 18519 | I13: 37037 | J13: 0 | K13: 37037 | L13: 2963 | M13: 40000 | N13: 0.0059 | O13: Restaurante Choclos y Asados La Finca S.A.S.
... A1598: 20 | B1598: 20/09/2026 | C1598: 1050 | D1598: Bebidas | E1598: Vive 100 pequ | F1598: ud | G1598: 0 | H1598: 0 | I1598: 0 | J1598: 0 | K1598: 0 | L1598: 0 | M1598: 0 | N1598: 0 | O1598: Restaurante Choclos y Asados La Finca S.A.S.

Sheet Detalle Compras Septiembre 2026
A1: Día | B1: Categoría | C1: Ítem | D1: Descripción Original (PDF) | E1: Cantidad | F1: Costo Unitario | G1: Vr. Compra | H1: N° Comprobante / Factura | I1: Relación con el Cuaderno | J1: Detalle | K1: Proveedor
A2: 1 | B2: Carnes | C2: Pezuña | D2: PEZUÑA CERDO A GRANEL (Supertiendas Cañaveral - 01FZ70896) | E2: 4.755 | F2: 7900 | G2: 37565 | H2: 01FZ70896 | I2: No Cruza con Cuaderno Don Arturo | K2: Supertiendas Cañaveral S.A.S.
A3: 1 | B3: Carnes | C3: Pezuña | D3: PEZUÑA CERDO A GRANEL (Supertiendas Cañaveral - 01FZ70896) | E3: 3.365 | F3: 8915.3 | G3: 30000 | H3: 01FZ70896 | I3: No Cruza con Cuaderno Don Arturo | K3: Supertiendas Cañaveral S.A.S.
A4: 1 | B4: Desechables | C4: Pilas | D4: PILA ALCALINA ENERGIZER (Supertiendas Cañaveral - 01FZ70896) | E4: 1 | F4: 14900 | G4: 14900 | H4: 01FZ70896 | I4: No Cruza con Cuaderno Don Arturo | K4: Supertiendas Cañaveral S.A.S.
A5: 1 | B5: Verduras | C5: Aguacate | D5: 8 AGUACATE COMUN*und (Supertiendas Cañaveral - 05FH119923) | E5: 8 | F5: 6800 | G5: 54400 | H5: 05FH119923 | I5: No Cruza con Cuaderno Don Arturo | K5: Supertiendas Cañaveral S.A.S.
A6: 1 | B6: Grano | C6: Arepas | D6: 100 arepas (Cuenta de Cobro 01-Sep-2026 Neftaly Ocampo) | E6: 100 | F6: 150 | G6: 15000 | H6: CC-01-Sep-2026 | I6: No Cruza con Cuaderno Don Arturo | K6: Neftaly Ocampo (Arepas)
A7: 1 | B7: Carnes | C7: Bagre de mar | D7: BAGRE DE MAR (Gabriel Ramirez Cubillos - FAC-188) | E7: 20 | F7: 16500 | G7: 330000 | H7: FAC-188 | I7: No Cruza con Cuaderno Don Arturo | K7: Alejandro Ramírez Cubillos (Pescados)
A8: 1 | B8: Carnes | C8: Filete de pollo x 120 | D8: Filete pollo 110g (Alexis Valencia - Factura 916) | E8: 4.58 | F8: 18500 | G8: 84730 | H8: FAC-916 | I8: No Cruza con Cuaderno Don Arturo | K8: Cárnicos Valencia (Alexis Valencia)
A9: 1 | B9: Carnes | C9: Filete de pollo x 350 | D9: Filete pollo 350g (Alexis Valencia - Factura 916) | E9: 15.1 | F9: 18500 | G9: 279350 | H9: FAC-916 | I9: Cruza con Cuaderno Don Arturo | K9: Cárnicos Valencia (Alexis Valencia)
A10: 1 | B10: Carnes | C10: Salmon | D10: Filete de Salmon Grande (Frio Sabor FVE-121) | E10: 9.87 | F10: 55000 | G10: 542850 | H10: FVE-121 | I10: No Cruza con Cuaderno Don Arturo | K10: Frío Sabor (Gerson Valencia)
A11: 1 | B11: Carnes | C11: Tilapia y truchas | D11: Tilapia Roja (Frio Sabor FVE-121) | E11: 19.81 | F11: 18000 | G11: 356580 | H11: FVE-121 | I11: No Cruza con Cuaderno Don Arturo | K11: Frío Sabor (Gerson Valencia)
A12: 1 | B12: INVENTARIO INICIAL | C12: INVENTARIO INICIAL | D12: INVENTARIO INICIAL | E12: 1 | F12: 12243950 | G12: 12243950 | H12: INVENTARIO INICIAL | I12: No Cruza con Cuaderno Don Arturo | K12: Inventario Inicial
A13: 1 | B13: Desechables | C13: Bloque media | D13: BLOQUE MEDIA (Hielo El Nevado NV202121) | E13: 2 | F13: 9500 | G13: 19000 | H13: NV202121 | I13: No Cruza con Cuaderno Don Arturo | K13: Industria Hielo El Nevado S.A.S.
... A27: 1 | B27: Carnes | C27: Tocino barril | D27: TOCINETA BARRIL (Carnes Los Monos - YP24152) | E27: 90.35 | F27: 21900 | G27: 1978665 | H27: YP24152 | I27: No Cruza con Cuaderno Don Arturo | K27: Distribuidora de Carnes ET Los Monos
A28: 1 | B28: Servicios Públicos | C28: Acueducto y Energía | D28: TOTAL A PAGAR | E28: 1 | F28: 921345 | G28: 921345 | H28: 18184113 | I28: No Cruza con Cuaderno Don Arturo | J28: 16/09/2026 | K28: EMCALI E.I.C.E. E.S.P.
A29: 2 | B29: Bebidas | C29: Gatorade | D29: BEB.GATORADE*500ml SURT. (Global Liquors - VC242401) | E29: 2 | F29: 39000 | G29: 78000 | H29: VC242401 | I29: No Cruza con Cuaderno Don Arturo | K29: Global Liquors (Licores)
A30: 2 | B30: Bebidas | C30: H2o | D30: AGUA H2O*600ml SURTIDA (Global Liquors VC242401 c/ NC NX8465) | E30: 1 | F30: 32500 | G30: 32500 | H30: VC242401 | I30: No Cruza con Cuaderno Don Arturo | K30: Global Liquors (Licores)
A31: 2 | B31: Bebidas | C31: Vive 100 | D31: BEB.EN.*380 VIVE100 (Global Liquors - VC242401) | E31: 1 | F31: 51600 | G31: 51600 | H31: VC242401 | I31: No Cruza con Cuaderno Don Arturo | K31: Global Liquors (Licores)
A32: 2 | B32: Desechables | C32: Bloque media | D32: BLOQUE MEDIA (Hielo El Nevado SF44886) | E32: 2 | F32: 9500 | G32: 19000 | H32: SF44886 | I32: No Cruza con Cuaderno Don Arturo | K32: Industria Hielo El Nevado S.A.S.
A33: 2 | B33: Verduras | C33: Aguacate | D33: 19 Aguacates (Recibo Caja Menor 02-Sep-2026) | E33: 19 | F33: 5263.16 | G33: 100000 | H33: RCM-02-Sep-2026 | I33: No Cruza con Cuaderno Don Arturo | K33: Gastos Menores / Caja Menor
A34: 2 | B34: Servicios | C34: Acopi | D34: Taxi - Acopi (Recibo Caja Menor 02-Sep-2026) | E34: 1 | F34: 30000 | G34: 30000 | H34: RCM-02-Sep-2026 | I34: No Cruza con Cuaderno Don Arturo | K34: Transporte Taxis / Acopi
A35: 2 | B35: Desechables | C35: Mazamorra | D35: Mazamorra (Franco Bravo - Recibo Caja Menor 02-Sep-2026) | E35: 1 | F35: 25000 | G35: 25000 | H35: RCM-02-Sep-2026 | I35: No Cruza con Cuaderno Don Arturo | K35: Gastos Menores / Caja Menor
A36: 2 | B36: Desechables | C36: Bloque media | D36: BLOQUE MEDIA (Hielo El Nevado - NV202202) | E36: 2 | F36: 9500 | G36: 19000 | H36: NV202202 | I36: No Cruza con Cuaderno Don Arturo | K36: Industria Hielo El Nevado S.A.S.
A37: 2 | B37: Desechables | C37: Bolsa 5kl tubular | D37: BOLSA X 5 KL TUBULAR (Hielo El Nevado - NV202202) | E37: 2 | F37: 5000 | G37: 10000 | H37: NV202202 | I37: No Cruza con Cuaderno Don Arturo | K37: Industria Hielo El Nevado S.A.S.
A38: 2 | B38: Grano | C38: Leche entera | D38: AVENA PRO CUBANA VASO 220G (Alquería - FEPL-3167991) | E38: 5 | F38: 3105.6 | G38: 15528 | H38: FEPL-3167991 | I38: Cruza con Cuaderno Don Arturo | K38: Productos Naturales de la Sabana (Alquería)
A39: 2 | B39: Grano | C39: Leche entera | D39: AVENA PRO AUTENTICA VASO 220G (Alquería - FEPL-3167991) | E39: 5 | F39: 3105.6 | G39: 15528 | H39: FEPL-3167991 | I39: Cruza con Cuaderno Don Arturo | K39: Productos Naturales de la Sabana (Alquería)
A40: 2 | B40: Grano | C40: Leche entera | D40: TANGELO BOTELLA 400 ML (Alquería - FEPL-3167991) | E40: 5 | F40: 1309 | G40: 6545 | H40: FEPL-3167991 | I40: Cruza con Cuaderno Don Arturo | K40: Productos Naturales de la Sabana (Alquería)
... A199: 7 | B199: Verduras | C199: Raices chinas | D199: 4 RAICES CHINAS VIVA MEJOR*250g (Supertiendas Cañaveral 11FH128829) | E199: 4 | F199: 2400 | G199: 9600 | H199: 11FH128829 | I199: No Cruza con Cuaderno Don Arturo | K199: Supertiendas Cañaveral S.A.S.
A200: 7 | B200: Insumos | C200: Arepas | D200: arepas | E200: 100 | F200: 150 | G200: 15000 | H200: S/N | I200: No Cruza con Cuaderno Don Arturo | J200: 16/09/2026 | K200: Neftaly Ocampo (Arepas)
A201: 8 | B201: Desechables | C201: Bolsa 5kl tubular | D201: BOLSA X 5 KL TUBULAR (Hielo El Nevado SF45044) | E201: 2 | F201: 5000 | G201: 10000 | H201: SF45044 | I201: No Cruza con Cuaderno Don Arturo | K201: Industria Hielo El Nevado S.A.S.
A202: 8 | B202: Verduras | C202: Arracacha | D202: Arracacha (Fruver Los Monos Remision A 0672) | E202: 4.2 | F202: 6000 | G202: 25200 | H202: REM-A 0672 | I202: No Cruza con Cuaderno Don Arturo | K202: Distribuidora de Carnes ET Los Monos
A203: 8 | B203: Verduras | C203: Arveja | D203: Arveja (Fruver Los Monos Remision A 0672) | E203: 3.3 | F203: 15000 | G203: 49500 | H203: REM-A 0672 | I203: No Cruza con Cuaderno Don Arturo | K203: Distribuidora de Carnes ET Los Monos
A204: 8 | B204: Verduras | C204: Cebolla Larga Atado | D204: Ata Larga (Fruver Los Monos Remision A 0672) | E204: 10 | F204: 6000 | G204: 60000 | H204: REM-A 0672 | I204: No Cruza con Cuaderno Don Arturo | K204: Distribuidora de Carnes ET Los Monos
A205: 8 | B205: Verduras | C205: Cebolla cabezona | D205: Cebolla Cabezona (Fruver Los Monos Remision A 0672) | E205: 9.5 | F205: 3800 | G205: 36100 | H205: REM-A 0672 | I205: No Cruza con Cuaderno Don Arturo | K205: Distribuidora de Carnes ET Los Monos
A206: 8 | B206: Verduras | C206: Lechuga batavia | D206: L. Batavia (Fruver Los Monos Remision A 0672) | E206: 42 | F206: 2800 | G206: 117600 | H206: REM-A 0672 | I206: No Cruza con Cuaderno Don Arturo | K206: Distribuidora de Carnes ET Los Monos
A207: 8 | B207: Verduras | C207: Limon tahiti | D207: Limon T (Fruver Los Monos Remision A 0672) | E207: 63.2 | F207: 3400 | G207: 214880 | H207: REM-A 0672 | I207: No Cruza con Cuaderno Don Arturo | K207: Distribuidora de Carnes ET Los Monos
A208: 8 | B208: Verduras | C208: Papa Capira bulto | D208: Capira bulto (Fruver Los Monos Remision A 0672) | E208: 1 | F208: 130000 | G208: 130000 | H208: REM-A 0672 | I208: No Cruza con Cuaderno Don Arturo | K208: Distribuidora de Carnes ET Los Monos
A209: 8 | B209: Verduras | C209: Papa amarilla | D209: Papa Amarilla (Fruver Los Monos Remision A 0672) | E209: 8.7 | F209: 6000 | G209: 52200 | H209: REM-A 0672 | I209: No Cruza con Cuaderno Don Arturo | K209: Distribuidora de Carnes ET Los Monos
A210: 8 | B210: Verduras | C210: Papa manbera | D210: Papa Mambera (Fruver Los Monos Remision A 0672) | E210: 6.8 | F210: 3500 | G210: 23800 | H210: REM-A 0672 | I210: No Cruza con Cuaderno Don Arturo | K210: Distribuidora de Carnes ET Los Monos
A211: 8 | B211: Verduras | C211: Pepino comun | D211: Pepino (Fruver Los Monos Remision A 0672) | E211: 3.3 | F211: 2500 | G211: 8250 | H211: REM-A 0672 | I211: No Cruza con Cuaderno Don Arturo | K211: Distribuidora de Carnes ET Los Monos
A212: 8 | B212: Verduras | C212: Perejil | D212: Perejil por atado (Fruver Los Monos Remision A 0672) | E212: 4 | F212: 9000 | G212: 36000 | H212: REM-A 0672 | I212: No Cruza con Cuaderno Don Arturo | K212: Distribuidora de Carnes ET Los Monos
... A267: 8 | B267: Grano | C267: Huevo aa | D267: 15 PANAL AA X 14.500 + PENDIENTE 10.000 (Cuenta de cobro Sept 8) | E267: 15 | F267: 15166.67 | G267: 227500 | H267: CC-08-Sep-2026 | I267: Cruza con Cuaderno Don Arturo | K267: Compras Menores en Efectivo
A268: 8 | B268: Mantenimiento | C268: Pintura | D268: MADETEC PISOS BRILLANTE COMP A 1550 CTO / 5891274 | E268: 1 | F268: 54899.46 | G268: 54899.46 | H268: FESR-3837 | I268: No Cruza con Cuaderno Don Arturo | J268: 16/09/2026 | K268: Compras Menores en Efectivo
A269: 8 | B269: Mantenimiento | C269: Catalizador | D269: CATALIZADOR MADETEC COMP.B 1551 CUARTO / 5890473 | E269: 1 | F269: 74899.79 | G269: 74899.79 | H269: FESR-3837 | I269: No Cruza con Cuaderno Don Arturo | J269: 16/09/2026 | K269: Compras Menores en Efectivo
A270: 8 | B270: Mantenimiento | C270: Thinner | D270: TETRASOL - THINER CORRIENTE CANECA / 51004 | E270: 1 | F270: 4999.19 | G270: 4999.19 | H270: FESR-3837 | I270: No Cruza con Cuaderno Don Arturo | J270: 16/09/2026 | K270: Compras Menores en Efectivo
A271: 8 | B271: Mantenimiento | C271: Barniz | D271: BARNEX CAOBA 6605 CUARTO / 5890530 | E271: 1 | F271: 49900.27 | G271: 49900.27 | H271: FESR-3837 | I271: No Cruza con Cuaderno Don Arturo | J271: 16/09/2026 | K271: Compras Menores en Efectivo
A272: 8 | B272: Insumos | C272: Arepas | D272: Arepas | E272: 200 | F272: 150 | G272: 30000 | H272: S/N | I272: No Cruza con Cuaderno Don Arturo | J272: 16/09/2026 | K272: Neftaly Ocampo (Arepas)
A273: 9 | B273: Verduras | C273: Papa a la francesa paq 2.5 kl | D273: PAPA A LA FRANCESA PAQ 2.5 KL (Carnes Los Monos - YP24314) | E273: 16 | F273: 17500 | G273: 280000 | H273: YP24314 | I273: No Cruza con Cuaderno Don Arturo | K273: Distribuidora de Carnes ET Los Monos
A274: 9 | B274: Carnes | C274: Camaron precocido | D274: CAMARON DE CULTIVO PRECOCIDO 91-110P (Carnes Los Monos - YP24314) | E274: 20.2 | F274: 22900 | G274: 462580 | H274: YP24314 | I274: No Cruza con Cuaderno Don Arturo | K274: Distribuidora de Carnes ET Los Monos
A275: 9 | B275: Carnes | C275: Costilla de cerdo especial | D275: COSTILLA DE CERDO IBP 244L (Carnes Los Monos - YP24314) | E275: 28.6 | F275: 15900 | G275: 454740 | H275: YP24314 | I275: No Cruza con Cuaderno Don Arturo | K275: Distribuidora de Carnes ET Los Monos
A276: 9 | B276: Carnes | C276: Lengua de res | D276: LENGUA DE RES IMP X KL (Carnes Los Monos - YP24314) | E276: 24.7 | F276: 23900 | G276: 590330 | H276: YP24314 | I276: No Cruza con Cuaderno Don Arturo | K276: Distribuidora de Carnes ET Los Monos
A277: 9 | B277: Carnes | C277: Sobaco | D277: SOBACO (Carnes Los Monos - YP24314) | E277: 22.18 | F277: 25900 | G277: 574462 | H277: YP24314 | I277: No Cruza con Cuaderno Don Arturo | K277: Distribuidora de Carnes ET Los Monos
A278: 9 | B278: Carnes | C278: Tocineta barril | D278: TOCINETA BARRIL (Carnes Los Monos - YP24314) | E278: 68.7 | F278: 21900 | G278: 1504530 | H278: YP24314 | I278: No Cruza con Cuaderno Don Arturo | K278: Distribuidora de Carnes ET Los Monos
A279: 9 | B279: Carnes | C279: Trozos e pechuga | D279: TROZOS DE PECHUGA (Carnes Los Monos - YP24314) | E279: 17.26 | F279: 11500 | G279: 198490 | H279: YP24314 | I279: No Cruza con Cuaderno Don Arturo | K279: Distribuidora de Carnes ET Los Monos
A280: 9 | B280: Bebidas | C280: Jug del valle | D280: JUGO NUTIVA EN CAJA X 200ML (Doña Mary Remision 38763) | E280: 720 | F280: 700 | G280: 504000 | H280: REM-38763 | I280: No Cruza con Cuaderno Don Arturo | K280: Distribuidora Doña Mary (Desechables)
A281: 9 | B281: Desechables | C281: Bolsa manigueta t25 | D281: BOLSA MANIGUETA T25 ECON (Doña Mary Remision 38763) | E281: 10 | F281: 4600 | G281: 46000 | H281: REM-38763 | I281: No Cruza con Cuaderno Don Arturo | K281: Distribuidora Doña Mary (Desechables)
A282: 9 | B282: Desechables | C282: Bolsa maniguetat40 | D282: BOLSA MANIGUETA T30 BLNCA ECONM (Doña Mary Remision 38763) | E282: 10 | F282: 5550 | G282: 55500 | H282: REM-38763 | I282: No Cruza con Cuaderno Don Arturo | K282: Distribuidora Doña Mary (Desechables)
A283: 9 | B283: Desechables | C283: Cinta impronta 24x80mm | D283: CINTA IMPRONTA (Doña Mary Remision 38763) | E283: 12 | F283: 3000 | G283: 36000 | H283: REM-38763 | I283: No Cruza con Cuaderno Don Arturo | K283: Distribuidora Doña Mary (Desechables)
A284: 9 | B284: Desechables | C284: Contenedor 16 onz. darnel 20x20 | D284: CONTENEDOR 16 ONZ DARNEL X 20X20 PAQ (Doña Mary Remision 38763) | E284: 20 | F284: 11200 | G284: 224000 | H284: REM-38763 | I284: No Cruza con Cuaderno Don Arturo | K284: Distribuidora Doña Mary (Desechables)
... A327: 9 | B327: Verduras | C327: Limonada cerezada | D327: LIMONADA CEREZADA (Fruitty Frezze FAC-A 0001-00021624) | E327: 3 | F327: 16800 | G327: 50400 | H327: 0001-00021624 | I327: No Cruza con Cuaderno Don Arturo | K327: Compras Menores en Efectivo
A328: 9 | B328: Abarrotes | C328: Aceite | D328: ACEITE DE SOY | E328: 5 | F328: 22990 | G328: 114950 | H328: L1S113066 | I328: Cruza con Cuaderno Don Arturo (Pág. 160 L14 - 5 Galones Aceite $114.950) | J328: 16/09/2026 | K328: Compras Menores en Efectivo
A329: 9 | B329: Insumos | C329: Arepas | D329: Arepas | E329: 100 | F329: 150 | G329: 15000 | H329: S/N | I329: No Cruza con Cuaderno Don Arturo | J329: 16/09/2026 | K329: Neftaly Ocampo (Arepas)
A330: 9 | B330: Aseo | C330: Limpion Flecos | D330: 1) 8907-LIMPION FLECOS COLVEN | E330: 1 | F330: 3000 | G330: 3000 | H330: S/N | I330: No Cruza con Cuaderno Don Arturo | J330: 16/09/2026 | K330: Compras Menores en Efectivo
A331: 10 | B331: Desechables | C331: Hielo bloque | D331: BLOQUE MEDIA X 2 (Distribuciones Hielo El Nevado Remision SF45104) | E331: 2 | F331: 9500 | G331: 19000 | H331: SF45104 | I331: No Cruza con Cuaderno Don Arturo | K331: Industria Hielo El Nevado S.A.S.
A332: 10 | B332: Desechables | C332: Hielo tubular | D332: BOLSA 5KL TUBULAR X 3 (Distribuciones Hielo El Nevado Remision SF45104) | E332: 3 | F332: 5000 | G332: 15000 | H332: SF45104 | I332: No Cruza con Cuaderno Don Arturo | K332: Industria Hielo El Nevado S.A.S.
A333: 10 | B333: Grano | C333: Chocolate | D333: 1/2 LB CHOCOLATE (Licores Zafiro Remision Sept 10/2026) | E333: 0.5 | F333: 38000 | G333: 19000 | H333: REM-10-Sep-2026-ZAF | I333: Cruza con Cuaderno Don Arturo | K333: Compras Menores en Efectivo
A334: 10 | B334: Carnes | C334: Pernil de pollo | D334: PERNIL POLLO (Alexis Valencia Remision 10-09-2026) | E334: 87.3 | F334: 7500 | G334: 654750 | H334: REM-10-Sep-2026 | I334: Cruza con Cuaderno Don Arturo (Pág. 160 L9 - Valencia 927 $654.750) | K334: Cárnicos Valencia (Alexis Valencia)
A335: 10 | B335: Servicios | C335: Transporte | D335: MARLENY - TRANSPORTE MANANA (Recibo Caja Menor 10/09/26) | E335: 1 | F335: 20000 | G335: 20000 | H335: RCM-10-Sep-2026-7 | I335: Cruza con Cuaderno Don Arturo | K335: Personal Operativo (Turnos de Caja)
A336: 10 | B336: Carnes | C336: Chorizo | D336: CHORIZOS (Recibo Caja Menor 10/09/26) | E336: 1 | F336: 18000 | G336: 18000 | H336: RCM-10-Sep-2026-6 | I336: Cruza con Cuaderno Don Arturo | K336: Gastos Menores / Caja Menor
A337: 10 | B337: Carnes | C337: Costilla | D337: COSTILLA (Recibo Caja Menor 10/09/26) | E337: 1 | F337: 5000 | G337: 5000 | H337: RCM-10-Sep-2026-6 | I337: Cruza con Cuaderno Don Arturo | K337: Gastos Menores / Caja Menor
A338: 10 | B338: Verduras | C338: Aguacate | D338: AGUACATES 20 UND (Recibo Caja Menor 10/09/26) | E338: 20 | F338: 5000 | G338: 100000 | H338: RCM-10-Sep-2026-6 | I338: Cruza con Cuaderno Don Arturo | K338: Gastos Menores / Caja Menor
A339: 10 | B339: Verduras | C339: Papa | D339: PAPA 11 UND (Recibo Caja Menor 10/09/26) | E339: 11 | F339: 3000 | G339: 33000 | H339: RCM-10-Sep-2026-6 | I339: Cruza con Cuaderno Don Arturo | K339: Gastos Menores / Caja Menor
A340: 10 | B340: Desechables | C340: Hojas platano | D340: HOJAS PLATANO 40 UND (Recibo Caja Menor 10/09/26) | E340: 40 | F340: 2700 | G340: 108000 | H340: RCM-10-Sep-2026-6 | I340: Cruza con Cuaderno Don Arturo | K340: Gastos Menores / Caja Menor
A341: 10 | B341: Grano | C341: Masa | D341: MASA 9 UND (Recibo Caja Menor 10/09/26) | E341: 9 | F341: 3000 | G341: 27000 | H341: RCM-10-Sep-2026-6 | I341: Cruza con Cuaderno Don Arturo | K341: Gastos Menores / Caja Menor
A342: 10 | B342: Grano | C342: Color | D342: COLOR 5 UND (Recibo Caja Menor 10/09/26) | E342: 5 | F342: 9000 | G342: 45000 | H342: RCM-10-Sep-2026-6 | I342: Cruza con Cuaderno Don Arturo | K342: Gastos Menores / Caja Menor
... A366: 10 | B366: Verduras | C366: Mezcla liquida limon | D366: MEZCLA LIQUIDA LIMON 2000ML X 6 (AM Letrascore Remision 0305) | E366: 6 | F366: 12500 | G366: 75000 | H366: 0305 | I366: No Cruza con Cuaderno Don Arturo | K366: Compras Menores en Efectivo
A367: 10 | B367: Bebidas | C367: Brisa Manzana 600ml | D367: BRISA MANZANA 600ML PET(6) REDUCCION (Ind. Nac. Gaseosas) | E367: 1 | F367: 10504 | G367: 10504 | H367: FVCL 5350357 | I367: No Cruza con Cuaderno Don Arturo | J367: 17/09/2026 | K367: Compras Menores en Efectivo
A368: 10 | B368: Bebidas | C368: Brisa 1L | D368: BRISA ECOFLEX 1 LITRO (6) REDUCCION (Ind. Nac. Gaseosas) | E368: 1 | F368: 12000 | G368: 12000 | H368: FVCL 5350352 | I368: No Cruza con Cuaderno Don Arturo | J368: 17/09/2026 | K368: Compras Menores en Efectivo
A369: 10 | B369: Bebidas | C369: Coca Cola 1L | D369: COCA COLA SO 1L PET (12) REDUCCION (Ind. Nac. Gaseosas) | E369: 1 | F369: 33782 | G369: 33782 | H369: FVCL 5350354 | I369: No Cruza con Cuaderno Don Arturo | J369: 17/09/2026 | K369: Coca-Cola FEMSA
A370: 10 | B370: Bebidas | C370: Quatro 1.5L | D370: QUATRO CHOICE 1.5 LT PET (12) REDUCCION (Ind. Nac. Gaseosas) | E370: 1 | F370: 37815 | G370: 37815 | H370: FVCL 5350355 | I370: No Cruza con Cuaderno Don Arturo | J370: 17/09/2026 | K370: Compras Menores en Efectivo
A371: 11 | B371: Servicios | C371: Arriendo local | D371: AYDE GUEVARA - ARRENDAMIENTO LOCAL (Recibo Caja Menor Taydem 11/09/2026) | E371: 1 | F371: 5241000 | G371: 5241000 | H371: RCM-11-Sep-2026 | I371: Cruza con Cuaderno Don Arturo | K371: Ayde Guevara (Arrendamiento)
A372: 11 | B372: Servicios | C372: Software nube | D372: COMPUTACION EN LA NUBE PLAN EMPRESARIAL (Dataico SAS E-412886) | E372: 1 | F372: 72000 | G372: 72000 | H372: E-412886 | I372: Cruza con Cuaderno Don Arturo | K372: Dataico S.A.S.
A373: 11 | B373: Servicios | C373: Pago Eliana | D373: Pago de Servicios Eliana | E373: 1 | F373: 1149000 | G373: 1149000 | H373: Cuenta de Cobro | I373: Cruza con Cuaderno Don Arturo | K373: Compras Menores en Efectivo
A374: 11 | B374: Servicios | C374: Contadora | D374: Contadora | E374: 1 | F374: 1200000 | G374: 1200000 | H374: CUADERNO DON ARTURO / NO REGISTRADO | I374: Cruza con Cuaderno Don Arturo | K374: Contadora Pública
A375: 11 | B375: Servicios | C375: Cuchillos y cucharas | D375: Cuchillos y cucharas | E375: 1 | F375: 432000 | G375: 432000 | H375: CUADERNO DON ARTURO / NO REGISTRADO | I375: Cruza con Cuaderno Don Arturo | K375: Compras Menores en Efectivo
A376: 11 | B376: Servicios | C376: ET Los Monos | D376: ET Los Monos | E376: 1 | F376: 19944200 | G376: 19944200 | H376: CUADERNO DON ARTURO / NO REGISTRADO | I376: Cruza con Cuaderno Don Arturo | K376: Distribuidora de Carnes ET Los Monos
A377: 11 | B377: Servicios | C377: Git Organizacional | D377: SERVICIOS TEMPORALES + AIU (Factura Electrónica FELE11955 - GIT Organizacional) | E377: 1 | F377: 16523800 | G377: 16523800 | H377: FELE11955 | I377: Cruza con Cuaderno Don Arturo | J377: 19/09/2026 | K377: GIT Organizacional S.A.S.
A378: 11 | B378: Servicios | C378: Pintura para mesas | D378: Pintura para mesas | E378: 1 | F378: 200000 | G378: 200000 | H378: CUADERNO DON ARTURO / NO REGISTRADO | I378: Cruza con Cuaderno Don Arturo | K378: Compras Menores en Efectivo
A379: 11 | B379: Servicios | C379: Transporte Danilo | D379: Transporte Danilo | E379: 1 | F379: 15000 | G379: 15000 | H379: CUADERNO DON ARTURO / NO REGISTRADO | I379: Cruza con Cuaderno Don Arturo | K379: Personal Operativo (Turnos de Caja)
A380: 11 | B380: Carnes | C380: Costilla ahumada | D380: Costilla ahumada | E380: 1 | F380: 364000 | G380: 364000 | H380: CUADERNO DON ARTURO / NO REGISTRADO | I380: Cruza con Cuaderno Don Arturo | K380: Compras Menores en Efectivo
A381: 11 | B381: Carnes | C381: Costilla ahumada | D381: Costilla ahumada | E381: 1 | F381: 364000 | G381: 364000 | H381: CUADERNO DON ARTURO / NO REGISTRADO | I381: Cruza con Cuaderno Don Arturo | K381: Compras Menores en Efectivo
A382: 11 | B382: Carnes | C382: Mariscos | D382: Mariscos | E382: 1 | F382: 1124100 | G382: 1124100 | H382: CUADERNO DON ARTURO / NO REGISTRADO | I382: Cruza con Cuaderno Don Arturo | K382: Compras Menores en Efectivo
A383: 11 | B383: Carnes | C383: Costilla ahumada | D383: dos cajas costilla (Cuaderno Pág. 159 Renglón 2) | E383: 2 | F383: 364000 | G383: 728000 | H383: CUADERNO DON ARTURO / NO REGISTRADO | I383: Cruza con Cuaderno Don Arturo | K383: Compras Menores en Efectivo
A384: 11 | B384: Verduras | C384: Verduras chucho | D384: VERDURAS VARIAS (Facturas Electrónicas FEFM 5710, 5716, 5727 - Chucho) | E384: 1 | F384: 2288950 | G384: 2288950 | H384: FEFM 5710 / 5716 / 5727 | I384: Cruza con Cuaderno Don Arturo | J384: 19/09/2026 | K384: Jesús Tobón (Fruver)
A385: 11 | B385: Grano | C385: Granero Piamonte | D385: Granero Piamonte | E385: 1 | F385: 1076000 | G385: 1076000 | H385: CUADERNO DON ARTURO / NO REGISTRADO | I385: Cruza con Cuaderno Don Arturo | K385: Granero Piamonte
A386: 11 | B386: Verduras | C386: Aguacate | D386: Aguacates (Segundo registro Cuaderno Pág. 159 Renglón 9) | E386: 1 | F386: 200000 | G386: 200000 | H386: CUADERNO DON ARTURO / NO REGISTRADO | I386: Cruza con Cuaderno Don Arturo | K386: Compras Menores en Efectivo
A387: 11 | B387: Servicios | C387: Andres Principal (Johanna/Wilson) | D387: Andres Principal (Johanna/Wilson) | E387: 1 | F387: 66000 | G387: 66000 | H387: CUADERNO CAJA / NÓMINA EFECTIVO | I387: No Cruza con Cuaderno Don Arturo | K387: Personal Operativo (Turnos de Caja)
A388: 11 | B388: Servicios | C388: Sebastian Principal (Johanna/Wilson) | D388: Sebastian Principal (Johanna/Wilson) | E388: 1 | F388: 66000 | G388: 66000 | H388: CUADERNO CAJA / NÓMINA EFECTIVO | I388: No Cruza con Cuaderno Don Arturo | K388: Personal Operativo (Turnos de Caja)
A389: 11 | B389: Servicios | C389: Wilson Principal (Johanna/Wilson) | D389: Wilson Principal (Johanna/Wilson) | E389: 1 | F389: 66000 | G389: 66000 | H389: CUADERNO CAJA / NÓMINA EFECTIVO | I389: No Cruza con Cuaderno Don Arturo | K389: Personal Operativo (Turnos de Caja)
A390: 11 | B390: Carnes | C390: Tilapia Principal (Johanna/Wilson) | D390: Tilapia Principal (Johanna/Wilson) | E390: 1 | F390: 377500 | G390: 377500 | H390: CUADERNO CAJA / NO REGISTRADO | I390: No Cruza con Cuaderno Don Arturo | K390: Personal Operativo (Turnos de Caja)
...

Sheet Hoja2
A1: CARNE LOS MONOS
A2: FACTURA | B2: FECHA | C2: TOTAL
A3: YP24089 | B3: 46262 | C3: 7834972 | D3: CANCELADA
A4: YP24140 | B4: 1 | C4: 2546555 | D4: CANCELADA
A5: YP24152 | B5: 1 | C5: 1978665 | D5: CANCELADA
A6: YP24244 | B6: 5 | C6: 7583980 | D6: CANCELADA
A7: MY8683 | B7: 7 | C7: 1528617
A8: YP24314 | B8: 9 | C8: 4065132
A9: YP24490 | B9: 17 | C9: 4335049
A10: YP24413 | B10: 12 | C10: 6083354
A11: MY8828 | B11: 14 | C11: 660028.8
A12: YP24534 | B12: 19 | C12: 4708833
B14: TOTAL | C14: 41325186
B15: CANCELADO | C15: 19944172
B16: SIN CANCELAR | C16: 21381014

Sheet Auditoría Cuaderno vs Excel
B2: AUDITORÍA Y CONCILIACIÓN INTEGRAL: CUADERNO DE CONTROL DON ARTURO (PÁG. 159 Y 160) VS EXCEL
B3: Conciliación 100% de 75 Registros Manuscritos ($102.406.519) + Inventario Inicial ($12.243.950) vs Costeo General Detalle Compras
B5: TOTAL CUADERNO PÁG. 159 | D5: TOTAL CUADERNO PÁG. 160 | F5: INVENTARIO INICIAL | H5: TOTAL CUADERNO GENERAL | J5: TOTAL COSTEO GENERAL EXCEL | L5: ESTADO AUDITORÍA
B6: 60724569 | D6: 41681950 | F6: 12243950 | H6: 114650469 | J6: 1.7195161e+08 | L6: 100% CONCILIADO
B7: 40 registros (Días 11 y 15) | D7: 35 registros (Días 15, 16 y 21) | F7: Encabezado Pág. 159 Don Arturo | H7: 75 Registros + Inv. Inicial | J7: Todas las compras y gastos causados | L7: 58 ítems cruzados / ajustados
B9: 1. MATRIZ DE CONCILIACIÓN LÍNEA POR LÍNEA: LOS 58 REGISTROS DEL CUADERNO DE DON ARTURO EN EXCEL
B10: # | C10: Pág. | D10: Línea | E10: Día | F10: Concepto en Cuaderno Don Arturo | G10: Valor Cuaderno ($) | H10: Estado Conciliación | I10: Valor en Excel ($) | J10: Diferencia ($) | K10: Fila(s) Excel | L10: Nº Comprobante / Soporte | M10: Observaciones y Dictamen de Auditoría
B11: 1 | C11: 159 | D11: 1 | E11: 11 | F11: Pago Arrendamiento | G11: 5241000 | H11: COINCIDE EXACTO | I11: 5241000 | J11: 0 | K11: Fila 319 | L11: RCM-11-Sep-2026 | M11: Recibo Caja Menor Taydem - Arrendamiento Ayde Guevara. Coincidencia plena.
B12: 2 | C12: 159 | D12: 2 | E12: 11 | F12: dos cajas costilla | G12: 728000 | H12: INGRESADO MANUAL (CUADERNO) | I12: 728000 | J12: 0 | K12: Fila 333 | L12: S/N | M12: 2 cajas costilla de cerdo compradas día 11 según cuaderno Don Arturo.
B13: 3 | C13: 159 | D13: 3 | E13: 11 | F13: ET Los Monos | G13: 19944200 | H13: INGRESADO MANUAL (CUADERNO) | I13: 19944200 | J13: 0 | K13: Fila 321 | L13: S/N | M13: Factura de carnes ET Los Monos acumulada registrada según control cuaderno.
B14: 4 | C14: 159 | D14: 4 | E14: 11 | F14: GIT Organizacional | G14: 16523800 | H14: COINCIDE FACTURA OFICIAL | I14: 16523800 | J14: 0 | K14: Fila 322 | L14: FELE11955 | M14: Pago quincena servicios temporales personal GIT Organizacional (Factura FELE11955).
B15: 5 | C15: 159 | D15: 5 | E15: 11 | F15: Verduras chucho | G15: 2288950 | H15: INGRESADO MANUAL (CUADERNO) | I15: 2288950 | J15: 0 | K15: Fila 323 | L15: S/N | M15: Verduras Jesús Tobón (Chucho) acumuladas registradas según cuaderno Don Arturo.
B16: 6 | C16: 159 | D16: 6 | E16: 11 | F16: Pulpas frutas | G16: 254200 | H16: COINCIDE EXACTO | I16: 254200 | J16: 0 | K16: Filas 142-146 | L16: RCM-05-Sep | M16: Compra de pulpas de frutas surtidas registrada en día 5.
B17: 7 | C17: 159 | D17: 7 | E17: 11 | F17: Panales de Huevo | G17: 227500 | H17: COINCIDE EXACTO | I17: 227500 | J17: 0 | K17: Fila 221 | L17: RCM-08-Sep | M17: Compra de panales de huevos registrada en día 8.
B18: 8 | C18: 159 | D18: 8 | E18: 11 | F18: Aguacates | G18: 200000 | H18: LEGALIZADO FACTURA REAL | I18: 204000 | J18: -4000 | K18: Fila 173 | L18: RCM-06-Sep | M18: Factura real soportada por $204.000 (diferencia de -$4.000 vs anotación estimada).
B19: 9 | C19: 159 | D19: 9 | E19: 11 | F19: Aguacates | G19: 200000 | H19: INGRESADO MANUAL (CUADERNO) | I19: 200000 | J19: 0 | K19: Fila 332 | L19: S/N | M19: Segunda compra de aguacates registrada el día 11 en el cuaderno Don Arturo.
B20: 10 | C20: 159 | D20: 10 | E20: 11 | F20: Gallinas 02.09 | G20: 443900 | H20: COINCIDE EXACTO | I20: 443900 | J20: 0 | K20: Fila 191 | L20: S/N | M20: Compra de gallinas semana día 7 registrada con exactitud.
B21: 11 | C21: 159 | D21: 11 | E21: 11 | F21: Panales de Huevos | G21: 198500 | H21: COINCIDE EXACTO | I21: 198500 | J21: 0 | K21: Fila 80 | L21: RCM-03-Sep | M21: Compra de panales de huevos día 3.
B22: 12 | C22: 159 | D22: 12 | E22: 11 | F22: Chorizos | G22: 238000 | H22: COINCIDE EXACTO | I22: 238000 | J22: 0 | K22: Filas 92-93 | L22: RCM-03-Sep | M22: Compra de chorizos día 3 registrada en detalle de compras.
... B85: 75 | C85: 160 | D85: 35 | E85: 21 | F85: Carnes Los Monos | G85: 12337150 | H85: COINCIDE FACTURAS OFICIALES | I85: 12337132 | J85: 18 | K85: Facs MY8683, YP24314, YP24413, MY8828 | L85: ET Los Monos | M85: Cancelación facturas carne Los Monos (.337.132 vs .337.150).
B86: SUBTOTAL PÁG. 159 (40 REGISTROS) | F86: 60724569 | H86: 40 REGISTROS AUDITADOS | I86: 60750111 | L86: -
B87: SUBTOTAL PÁG. 160 (35 REGISTROS) | F87: 41681950 | H87: 35 REGISTROS AUDITADOS | I87: 41681635 | L87: -
B88: TOTAL 75 REGISTROS CUADERNO DON ARTURO | F88: 102406519 | H88: 100% REGISTRADO EN EXCEL | I88: 102431746 | L88: -
B90: 2. RESUMEN FINANCIERO Y CUADRATURA CONSOLIDADA: CUADERNO VS COSTEO GENERAL
B91: Concepto de Conciliación | I91: Naturaleza / Impacto
B92: Total Cuaderno Don Arturo (75 ítems manuscritos) | I92: Control Manuscrito
B93: (+) Inventario Inicial Manuscrito | I93: Encabezado Pág. 159
B94: (=) TOTAL CUADERNO DON ARTURO CONSOLIDADO | I94: Total Control Don Arturo
B95: Total Costeo General en Excel (Detalle Compras) | I95: Costo/Gasto General
B96: Total Cuaderno Don Arturo (75 ítems manuscritos) | I96: Cruce Cuaderno
B97: (=) DIFERENCIA: GASTOS EN EXCEL QUE NO ESTÁN EN EL CUADERNO | I97: Gastos Directos / Facturas
B99: 3. ANÁLISIS BILATERAL: COMPRAS Y GASTOS EN EXCEL QUE NO ESTÁN EN EL CUADERNO DE DON ARTURO
B100: Categoría de Costo / Gasto | E100: Nº Ítems | F100: Total en Excel ($) | H100: % Part. | I100: Principales Proveedores / Conceptos Oficiales | L100: Causa por la que NO está en el Cuaderno
B101: Carnes | E101: 112 | F101: 43616226 | H101: 0.41362918 | I101: ET Los Monos crédito, Distribuidora M y C, El Gran Surtidor, Alejandro Ramírez (Pescados) | L101: Facturas electrónicas DIAN a crédito y transferencias bancarias de carnicería.
B102: Nómina y Talento Humano | E102: 35 | F102: 24987237 | H102: 0.23696343 | I102: GIT Organizacional (Servicios temporales quincena 1), Turnos adicionales Marleny/Andrés/Sebastián | L102: Nómina tercerizada canalizada por factura formal y turnos diarios pagados de caja menor.
B103: Verduras y Fruver | E103: 114 | F103: 7021245 | H103: 0.066585124 | I103: Jesús Tobón (Fruver facturación semanal agrupada), Compras mercado galería | L103: Remisiones y facturas electrónicas semanales del proveedor de verduras.
B104: Servicios Públicos | E104: 4 | F104: 1193345 | H104: 0.011316942 | I104: EMCALI Acueducto y Energía, Claro Telefonía Móvil | L104: Servicios causados por factura electrónica institucional.
B105: Bebidas | E105: 95 | F105: 5929256 | H105: 0.056229379 | I105: Coca-Cola FEMSA, Postobón, Hielo El Nevado, Cervecería | L105: Facturación electrónica directa de distribuidores de bebidas y recibos de hielo.
B106: Desechables | E106: 115 | F106: 5402726 | H106: 0.051236096 | I106: Makro, Distribuidoras de desechables, Plásticos y empaques | L106: Compras al por mayor con factura electrónica para abastecimiento de empaques.
B107: Servicios Operativos | E107: 51 | F107: 5259582 | H107: 0.049878607 | I107: Dataico (Software facturación), Taxis Acopi, Servicios de recolección y limpieza | L107: Gastos operativos menores causados con recibos de caja menor.
B108: Mantenimiento | E108: 8 | F108: 3655999 | H108: 0.034671222 | I108: Eliana Murillo (Saldo Cuarto Frío), Ferreterías, Materiales soldadura y eléctricos | L108: Contrato formal de mantenimiento y compras de ferretería con soporte.
B109: Grano y Abarrotes | E109: 50 | F109: 4021790 | H109: 0.038140157 | I109: Granero Piamonte facturas adicionales, Distribuidora San Alejo, Harinas y granos | L109: Compras de granero con facturación electrónica adicional a las del cuaderno.
B110: Gastos Administrativos | E110: 11 | F110: 1552000 | H110: 0.014718203 | I110: Health Care IPS (Exámenes de ingreso), Asesorías jurídicas, Papelería | L110: Facturación institucional corporativa.
B111: Gastos Generales y Varios | E111: 13 | F111: 1308300 | H111: 0.012407104 | I111: Incentivos de personal, Compras menores de emergencia en sede | L111: Recibos de caja menor directos del punto de venta.
B112: Insumos de Cocina | E112: 23 | F112: 1101646 | H112: 0.010447326 | I112: Alquería (Lácteos y cremas adicionales), Especias, Insumos panadería | L112: Facturación electrónica Alquería e insumos de cocina.
... B115: TOTAL COMPRAS EN EXCEL NO PRESENTES EN CUADERNO | E115: 644 | F115: 105447652 | H115: 1 | I115: Totalizado por Facturación Electrónica DIAN + Caja Menor | L115: Todas las partidas cuentan con comprobante oficial en archivo.

Sheet Auditoria libro de Caja
B2: AUDITORÍA INTEGRAL: LIBRO DIARIO DE CAJA (07 AL 11 DE SEPTIEMBRE 2026) VS EXCEL
B3: Conciliación de 8 Cierres de Caja Diarios (Domicilios y Barra) | Trazabilidad de Egresos vs Facturas Oficiales en Excel | Validación de Turnos y Medios de Pago
B5: TOTAL INGRESOS CAJA (8 CIERRES) | D5: EGRESOS CRUZADOS EN EXCEL | G5: TURNOS PAGADOS EN EFECTIVO | I5: GASTOS MENORES SIN FACTURA | K5: ÍTEMS AUDITADOS Y CONCILIADOS
B6: 25175286 | D6: 2208436 | G6: 868000 | I6: 2905950 | K6: 69
B7: Ventas brutas Efectivo, Datáfono y Nequi | D7: Gastos de caja legalizados con factura oficial | G7: Mano de obra operativa pagada en caja | I7: Insumos de plaza, taxis y ferretería menor | K7: 100% de los registros del PDF analizados
B9: 1. MATRIZ CONSOLIDADA: TODOS LOS EGRESOS DEL LIBRO DE CAJA (PDF) CRUZADOS CON EL EXCEL
B10: Pág / Fecha | C10: Caja / Responsable | D10: Ítem Manuscrito en Caja | E10: Valor Caja ($) | G10: Categoría de Caja | H10: Estado en Excel | I10: Fila Excel | J10: Soporte / Comprobante en Excel | K10: Valor Excel ($) | L10: Diagnóstico y Hallazgo de Auditoría
B11: Pág. 1 (07/09) | C11: Domicilios (Carolina) | D11: Broca | E11: 10000 | F11: Broca Domicilios (Carolina) | G11: Mantenimiento | H11: NO REGISTRADO | I11: - | J11: Sin factura en Excel | K11: - | L11: Herramienta menor para mantenimiento de sede (gasto de caja menor).
B12: Pág. 1 (07/09) | C12: Domicilios (Carolina) | D12: Coco / Limonada | E12: 37100 | F12: Coco / Limonada Domicilios (Carolina) | G12: Alimentos / Bebidas | H12: NO REGISTRADO | I12: - | J12: Sin factura en Excel | K12: - | L12: Compra en plaza/frutería local sin soporte formal.
B13: Pág. 1 (07/09) | C13: Domicilios (Carolina) | D13: Turno Marleny | E13: 66000 | F13: Turno Marleny Domicilios (Carolina) | G13: Nómina Operativa | H13: NÓMINA EFECTIVO | I13: - | J13: Pago operativo directo | K13: - | L13: Turno pagado en efectivo de caja. No aplica en compras de insumos.
B14: Pág. 1 (07/09) | C14: Domicilios (Carolina) | D14: Credito Jhonatan | E14: 4000 | F14: Credito Jhonatan Domicilios (Carolina) | G14: Préstamo Empleado | H14: VALE DE CAJA | I14: - | J14: Anticipo de caja menor | K14: - | L14: Préstamo/vale de caja interno de empleado.
B15: Pág. 1 (07/09) | C15: Domicilios (Carolina) | D15: Transporte Carolina | E15: 15000 | F15: Transporte Carolina Domicilios (Carolina) | G15: Transporte Operativo | H15: NO REGISTRADO | I15: - | J15: Sin factura en Excel | K15: - | L15: Transporte por diligencia administrativa (caso Daniela).
B16: Pág. 1 (07/09) | C16: Domicilios (Carolina) | D16: Devolución Señor Arturo | E16: 85000 | F16: Devolución Señor Arturo Domicilios (Carolina) | G16: Devolución Saldo | H16: NO REGISTRADO | I16: - | J16: Sin factura en Excel | K16: - | L16: Salida de caja menor por reintegro/devolución.
B17: Pág. 2 (08/09) | C17: Principal (Johanna) | D17: Wilson (Lunes y Martes) | E17: 132000 | F17: Wilson (Lunes y Martes) Principal (Johanna) | G17: Nómina Operativa | H17: NÓMINA EFECTIVO | I17: - | J17: Pago operativo directo | K17: - | L17: Dos turnos operativos ($66.000 x 2) cancelados en efectivo.
B18: Pág. 2 (08/09) | C18: Principal (Johanna) | D18: Andres | E18: 66000 | F18: Andres Principal (Johanna) | G18: Nómina Operativa | H18: NÓMINA EFECTIVO | I18: - | J18: Pago operativo directo | K18: - | L18: Turno operativo cancelado en efectivo de caja.
B19: Pág. 2 (08/09) | C19: Principal (Johanna) | D19: Diego / Luigui | E19: 66000 | F19: Diego / Luigui Principal (Johanna) | G19: Nómina Operativa | H19: NÓMINA EFECTIVO | I19: - | J19: Pago operativo directo | K19: - | L19: Turno operativo cancelado en efectivo de caja.
B20: Pág. 2 (08/09) | C20: Principal (Johanna) | D20: Hielo | E20: 10000 | F20: Hielo Principal (Johanna) | G20: Insumos Operativos | H20: CONCILIADO EXACTO | I20: Fila 186 / 219 | J20: Hielo El Nevado SF45023 / SF45044 | K20: 10000 | L20: Coincide exactamente con la remisión oficial de Hielo El Nevado ($10.000).
B21: Pág. 2 (08/09) | C21: Principal (Johanna) | D21: Acopi | E21: 30000 | F21: Acopi Principal (Johanna) | G21: Gastos Operativos | H21: CONCILIADO EXACTO | I21: Fila 188 | J21: RCM-07-Sep-2026 (Acopi Almuerzo German) | K21: 30000 | L21: Coincide exactamente con el Recibo de Caja Menor por almuerzos Acopi.
B22: Pág. 2 (08/09) | C22: Principal (Johanna) | D22: Sistema de Higiene | E22: 35100 | F22: Sistema de Higiene Principal (Johanna) | G22: Aseo y Limpieza | H22: NO REGISTRADO | I22: - | J22: Sin factura en Excel | K22: - | L22: Insumos de desinfección y bioseguridad pagados en caja menor.
B23: Pág. 2 (08/09) | C23: Principal (Johanna) | D23: Platano verde | E23: 66000 | F23: Platano verde Principal (Johanna) | G23: Verduras y Frutas | H23: RELACIONADO | I23: Fila 210 | J23: REM-A 0672 Fruver Los Monos ($85.400) | K23: 85400 | L23: Plátano verde en fruver (en Excel registrado en remisión por $85.400).
B24: Pág. 2 (08/09) | C24: Principal (Johanna) | D24: Leche de coco | E24: 147000 | F24: Leche de coco Principal (Johanna) | G24: Insumos Cocina | H24: CONCILIADO EXACTO | I24: Fila 215 | J24: RCM-08-09-26 (7 lts Leche Coco) | K24: 147000 | L24: ¡COINCIDENCIA EXACTA AL 100%! Recibo Caja Menor por 7 litros de leche de coco.
B25: Pág. 2 (08/09) | C25: Principal (Johanna) | D25: Cinta | E25: 14000 | F25: Cinta Principal (Johanna) | G25: Empaques / Suministros | H25: CONCILIADO EXACTO | I25: Fila 224 | J25: RCM-08-09-26 (Cinta Antiadherente) | K25: 14000 | L25: ¡COINCIDENCIA EXACTA AL 100%! Recibo Caja Menor cinta antiadherente.
B26: Pág. 2 (08/09) | C26: Principal (Johanna) | D26: Platano | E26: 78500 | F26: Platano Principal (Johanna) | G26: Verduras y Frutas | H26: RELACIONADO | I26: Fila 209 | J26: REM-A 0672 Fruver Los Monos ($74.200) | K26: 74200 | L26: Plátano maduro en fruver Los Monos (en Excel remisión por $74.200).
B27: Pág. 2 (08/09) | C27: Principal (Johanna) | D27: 10 Portacazuelas | E27: 90000 | F27: 10 Portacazuelas Principal (Johanna) | G27: Menaje y Vajilla | H27: NO REGISTRADO | I27: - | J27: Sin factura en Excel | K27: - | L27: Adquisición de portacazuelas para servicio del restaurante.
B28: Pág. 2 (08/09) | C28: Principal (Johanna) | D28: Yuca | E28: 81000 | F28: Yuca Principal (Johanna) | G28: Verduras y Tubérculos | H28: NO REGISTRADO | I28: - | J28: Sin factura en Excel | K28: - | L28: Compra directa en galería/plaza pagada desde caja menor.
B29: Pág. 2 (08/09) | C29: Principal (Johanna) | D29: Pitaya | E29: 5555 | F29: Pitaya Principal (Johanna) | G29: Frutas | H29: CONCILIADO AL PESO | I29: Fila 183 | J29: Cañaveral 11FH128831 (Pitahaya 0.505kg) | K29: 5555 | L29: ¡COINCIDENCIA EXACTA AL PESO ($5.555)! Factura oficial Cañaveral.
B30: Pág. 2 (08/09) | C30: Principal (Johanna) | D30: Mortadela raices | E30: 90125 | F30: Mortadela raices Principal (Johanna) | G30: Insumos Cocina | H30: CONCILIADO AL PESO | I30: Filas 174, 178, 184 | J30: Cañaveral 11FH128829 ($59.325+$21.200+$9.600) | K30: 90125 | L30: ¡COINCIDENCIA EXACTA AL PESO ($90.125)! Agrupa Alas, Mortadela Rica y Raíces.
B31: Pág. 2 (08/09) | C31: Principal (Johanna) | D31: Pezunas y espinazo | E31: 61606 | F31: Pezunas y espinazo Principal (Johanna) | G31: Carnes | H31: CONCILIADO AL PESO | I31: Filas 175, 179, 187 | J31: La Sevillana SEV-07SEP ($29.795+$31.377+$433) | K31: 61606 | L31: ¡COINCIDENCIA EXACTA AL PESO ($61.606,04)! Factura Agropecuaria La Sevillana.
B32: Pág. 2 (08/09) | C32: Principal (Johanna) | D32: Alimento para la gata | E32: 13500 | F32: Alimento para la gata Principal (Johanna) | G32: Gastos Varios | H32: NO REGISTRADO | I32: - | J32: Sin factura en Excel | K32: - | L32: Compra menor de concentrado.
B33: Pág. 2 (08/09) | C33: Principal (Johanna) | D33: Radios M6 | E33: 130000 | F33: Radios M6 Principal (Johanna) | G33: Dotación / Equipos | H33: NO REGISTRADO | I33: - | J33: Sin factura en Excel | K33: - | L33: Radios de comunicación interna para operación de servicio.
B34: Pág. 3 (08/09) | C34: Domicilios (Neymar) | D34: Lechuga | E34: 5000 | F34: Lechuga Domicilios (Neymar) | G34: Verduras | H34: NO REGISTRADO | I34: - | J34: Sin factura en Excel | K34: - | L34: Compra menor de lechuga para domicilios.
B35: Pág. 3 (08/09) | C35: Domicilios (Neymar) | D35: Taxi compresor | E35: 20000 | F35: Taxi compresor Domicilios (Neymar) | G35: Mantenimiento | H35: NO REGISTRADO | I35: - | J35: Sin factura en Excel | K35: - | L35: Transporte para recarga/mantenimiento de compresor.
B36: Pág. 3 (08/09) | C36: Domicilios (Neymar) | D36: Habichuela, blanquillo, víscera | E36: 86600 | F36: Habichuela, blanquillo, víscera Domicilios (Neymar) | G36: Insumos Cocina | H36: NO REGISTRADO | I36: - | J36: Sin factura en Excel | K36: - | L36: Compra mixta de galería para menú.
B37: Pág. 3 (08/09) | C37: Domicilios (Neymar) | D37: Credito Jose david | E37: 20000 | F37: Credito Jose david Domicilios (Neymar) | G37: Préstamo Empleado | H37: VALE DE CAJA | I37: - | J37: Anticipo de caja menor | K37: - | L37: Vale de anticipo empleado descontable.
B38: Pág. 3 (08/09) | C38: Domicilios (Neymar) | D38: Visceras | E38: 72200 | F38: Visceras Domicilios (Neymar) | G38: Carnes Menores | H38: NO REGISTRADO | I38: - | J38: Sin factura en Excel | K38: - | L38: Compra adicional de vísceras para cocina.
B39: Pág. 3 (08/09) | C39: Domicilios (Neymar) | D39: Turno Marleny | E39: 66000 | F39: Turno Marleny Domicilios (Neymar) | G39: Nómina Operativa | H39: NÓMINA EFECTIVO | I39: - | J39: Pago operativo directo | K39: - | L39: Turno operativo cancelado en efectivo de caja.
B40: Pág. 4 (09/09) | C40: Principal (Johanna) | D40: Andres | E40: 66000 | F40: Andres Principal (Johanna) | G40: Nómina Operativa | H40: NÓMINA EFECTIVO | I40: - | J40: Pago operativo directo | K40: - | L40: Turno operativo cancelado en efectivo de caja.
B41: Pág. 4 (09/09) | C41: Principal (Johanna) | D41: Sebastian | E41: 66000 | F41: Sebastian Principal (Johanna) | G41: Nómina Operativa | H41: NÓMINA EFECTIVO | I41: - | J41: Pago operativo directo | K41: - | L41: Turno operativo cancelado en efectivo de caja.
B42: Pág. 4 (09/09) | C42: Principal (Johanna) | D42: Hielo | E42: 19000 | F42: Hielo Principal (Johanna) | G42: Insumos Operativos | H42: CONCILIADO EXACTO | I42: Fila 301 | J42: Hielo El Nevado SF45104 (Bloque media) | K42: 19000 | L42: Coincide con remisión oficial de Hielo El Nevado (bloque media $19.000).
B43: Pág. 4 (09/09) | C43: Principal (Johanna) | D43: Champiñones | E43: 31000 | F43: Champiñones Principal (Johanna) | G43: Verduras | H43: NO REGISTRADO | I43: - | J43: Sin factura en Excel | K43: - | L43: Compra en efectivo para cocina.
B44: Pág. 4 (09/09) | C44: Principal (Johanna) | D44: Espinazo, Cuchuco, Salchicha | E44: 76500 | F44: Espinazo, Cuchuco, Salchicha Principal (Johanna) | G44: Carnes y Granos | H44: NO REGISTRADO | I44: - | J44: Sin factura en Excel | K44: - | L44: Combo de ingredientes para sopa/menú del día.
B45: Pág. 4 (09/09) | C45: Principal (Johanna) | D45: Inmunocal | E45: 40000 | F45: Inmunocal Principal (Johanna) | G45: Botiquín / Salud | H45: NO REGISTRADO | I45: - | J45: Sin factura en Excel | K45: - | L45: Gasto menor de farmacia / salud.
B46: Pág. 4 (09/09) | C46: Principal (Johanna) | D46: Acopi | E46: 30000 | F46: Acopi Principal (Johanna) | G46: Gastos Operativos | H46: CONCILIADO EXACTO | I46: Fila 268 | J46: RCM-09-Sep-2026 (Acopi German) | K46: 30000 | L46: ¡COINCIDENCIA EXACTA! Recibo de Caja Menor Acopi German.
B47: Pág. 4 (09/09) | C47: Principal (Johanna) | D47: Mazamorra | E47: 25000 | F47: Mazamorra Principal (Johanna) | G47: Alimentos | H47: CONCILIADO EXACTO | I47: Fila 264 | J47: RCM-09-Sep-2026 (Mazamorra Franco Bravo) | K47: 25000 | L47: ¡COINCIDENCIA EXACTA AL 100%! Recibo de Franco Bravo.
B48: Pág. 5 (09/09) | C48: Domicilios (María) | D48: Lenteja | E48: 47300 | F48: Lenteja Domicilios (María) | G48: Granos / Abarrotes | H48: CONCILIADO EXACTO | I48: Fila 255 | J48: D1 SAS G6G0471810 (25 un Lenteja $47.250) | K48: 47250 | L48: ¡COINCIDENCIA EXACTA! Factura D1 por $47.250 (redondeado en caja a $47.300).
B49: Pág. 5 (09/09) | C49: Domicilios (María) | D49: Galleta | E49: 76900 | F49: Galleta Domicilios (María) | G49: Abarrotes / Confitería | H49: CONCILIADO EXACTO | I49: Fila 254 | J49: D1 SAS G1G0285471 (14 un Galleta $76.860) | K49: 76860 | L49: ¡COINCIDENCIA EXACTA! Factura D1 por $76.860 (redondeado en caja a $76.900).
B50: Pág. 5 (09/09) | C50: Domicilios (María) | D50: Liga / Lija | E50: 4500 | F50: Liga / Lija Domicilios (María) | G50: Ferretería | H50: CONCILIADO AL PESO | I50: Fila 263 | J50: REM-09-Sep-2026 (1 Disco Flaper $4.500) | K50: 4500 | L50: ¡COINCIDENCIA EXACTA AL PESO ($4.500)! Ferretería disco lija/flapper.
B51: Pág. 5 (09/09) | C51: Domicilios (María) | D51: Pulpa de coco | E51: 130000 | F51: Pulpa de coco Domicilios (María) | G51: Pulpas de Fruta | H51: NO REGISTRADO | I51: - | J51: Sin factura en Excel | K51: - | L51: Compra en efectivo para preparación de cocina.
B52: Pág. 5 (09/09) | C52: Domicilios (María) | D52: Don Arturo recogió | E52: 500000 | F52: Don Arturo recogió Domicilios (María) | G52: Retiro de Efectivo Socio | H52: RETIRO SOCIO | I52: - | J52: Retiro de caja utilidad | K52: - | L52: Salida de utilidad a socio propietario. No es costo operativo.
B53: Pág. 5 (09/09) | C53: Domicilios (María) | D53: Turno Marleny | E53: 66000 | F53: Turno Marleny Domicilios (María) | G53: Nómina Operativa | H53: NÓMINA EFECTIVO | I53: - | J53: Pago operativo directo | K53: - | L53: Turno operativo cancelado en efectivo de caja.
B54: Pág. 6 (10/09) | C54: Principal (Johanna) | D54: Andres | E54: 66000 | F54: Andres Principal (Johanna) | G54: Nómina Operativa | H54: NÓMINA EFECTIVO | I54: - | J54: Pago operativo directo | K54: - | L54: Turno operativo cancelado en efectivo de caja.
B55: Pág. 6 (10/09) | C55: Principal (Johanna) | D55: Sebastian | E55: 66000 | F55: Sebastian Principal (Johanna) | G55: Nómina Operativa | H55: NÓMINA EFECTIVO | I55: - | J55: Pago operativo directo | K55: - | L55: Turno operativo cancelado en efectivo de caja.
B56: Pág. 6 (10/09) | C56: Principal (Johanna) | D56: Hielo | E56: 34000 | F56: Hielo Principal (Johanna) | G56: Insumos Operativos | H56: CONCILIADO EXACTO | I56: Filas 301, 302 | J56: Hielo El Nevado SF45104 ($19.000 + $15.000) | K56: 34000 | L56: ¡COINCIDENCIA EXACTA ($34.000)! Bloque media ($19k) + Bolsa tubular ($15k).
B57: Pág. 6 (10/09) | C57: Principal (Johanna) | D57: Mazamorra | E57: 20000 | F57: Mazamorra Principal (Johanna) | G57: Alimentos | H57: CONCILIADO EXACTO | I57: Fila 303 | J57: RCM-10-Sep-2026-2 (Mazamorra Franco Bravo) | K57: 20000 | L57: ¡COINCIDENCIA EXACTA AL 100%! Recibo de Caja Menor Franco Bravo.
B58: Pág. 6 (10/09) | C58: Principal (Johanna) | D58: Acopi | E58: 30000 | F58: Acopi Principal (Johanna) | G58: Gastos Operativos | H58: CONCILIADO EXACTO | I58: Fila 304 | J58: RCM-10-Sep-2026-3 (Acopi German) | K58: 30000 | L58: ¡COINCIDENCIA EXACTA AL 100%! Recibo de Caja Menor Acopi German.
B59: Pág. 6 (10/09) | C59: Principal (Johanna) | D59: Pastas la Muñeca | E59: 75350 | F59: Pastas la Muñeca Principal (Johanna) | G59: Granos / Abarrotes | H59: RELACIONADO | I59: Fila 305 | J59: Cañaveral 06FZ47115 (Pasta tornillo $66.400) | K59: 66400 | L59: Compra en supermercado de pastas para servicio.
B60: Pág. 6 (10/09) | C60: Principal (Johanna) | D60: Pulpas | E60: 352450 | F60: Pulpas Principal (Johanna) | G60: Pulpas de Fruta | H60: CONCILIADO AL PESO | I60: Filas 269-274 | J60: Fruitty Freeze FAC-A 0001-00021624 | K60: 352450 | L60: ¡COINCIDENCIA EXACTA AL PESO ($352.450)! Factura electrónica oficial Fruitty.
B61: Pág. 6 (10/09) | C61: Principal (Johanna) | D61: Postobón | E61: 614300 | F61: Postobón Principal (Johanna) | G61: Bebidas Comerciales | H61: CONCILIADO FACTURA | I61: Filas 276-289 | J61: Postobon S.A. JM071024895 ($621.140) | K61: 621140 | L61: Factura oficial Postobón pagada en efectivo de caja (diferencia menor de $6.840).
B62: Pág. 7 (10/09) | C62: Domicilios (Neymar) | D62: Turno Taty Vigilancia | E62: 70000 | F62: Turno Taty Vigilancia Domicilios (Neymar) | G62: Nómina / Seguridad | H62: NÓMINA EFECTIVO | I62: - | J62: Pago operativo directo | K62: - | L62: Turno de seguridad nocturna pagado en efectivo.
B63: Pág. 7 (10/09) | C63: Domicilios (Neymar) | D63: Turno Marleny | E63: 66000 | F63: Turno Marleny Domicilios (Neymar) | G63: Nómina Operativa | H63: RELACIONADO | I63: Fila 309 | J63: RCM-10-Sep-2026-5 (Marlene 7 hrs $58.000) | K63: 58000 | L63: En Excel se legalizó recibo por $58.000 (diferencia de $8.000 por horas).
B64: Pág. 7 (10/09) | C64: Domicilios (Neymar) | D64: Harina y Aceite | E64: 109000 | F64: Harina y Aceite Domicilios (Neymar) | G64: Granos / Cocina | H64: CONCILIADO EXACTO | I64: Filas 297, 298 | J64: D1 G9F9316392 ($17.000 + $91.950 = $108.950) | K64: 108950 | L64: ¡COINCIDENCIA EXACTA CON D1 ($108.950)! Redondeado en caja a $109.000.
B65: Pág. 7 (10/09) | C65: Domicilios (Neymar) | D65: Transporte Deys | E65: 28000 | F65: Transporte Deys Domicilios (Neymar) | G65: Transporte Operativo | H65: NO REGISTRADO | I65: - | J65: Sin factura en Excel | K65: - | L65: Transporte para diligencia operativa en moto/taxi.
B66: Pág. 7 (10/09) | C66: Domicilios (Neymar) | D66: Transporte Enith | E66: 50000 | F66: Transporte Enith Domicilios (Neymar) | G66: Transporte Operativo | H66: CONCILIADO EXACTO | I66: Fila 299 | J66: RCM-10-Sep-2026-1 (Transporte Edith $50.000) | K66: 50000 | L66: ¡COINCIDENCIA EXACTA AL 100%! Recibo Caja Menor Transporte Edith/Enith.
B67: Pág. 7 (10/09) | C67: Domicilios (Neymar) | D67: Zumo de limón | E67: 75000 | F67: Zumo de limón Domicilios (Neymar) | G67: Insumos Bebidas | H67: CONCILIADO EXACTO | I67: Fila 300 | J67: AM Letrascore Remisión 0305 ($75.000) | K67: 75000 | L67: ¡COINCIDENCIA EXACTA AL 100%! Soporte Remisión oficial 6 und x 2000ml.
B68: Pág. 7 (10/09) | C68: Domicilios (Neymar) | D68: Coca-Cola | E68: 329500 | F68: Coca-Cola Domicilios (Neymar) | G68: Bebidas Comerciales | H68: NO REGISTRADO | I68: - | J68: Sin factura en Excel | K68: - | L68: Surtido de bebidas Coca-Cola pagado de caja sin factura radicada.
B69: Pág. 8 (11/09) | C69: Principal (Johanna/Wilson) | D69: Andres | E69: 66000 | F69: Andres Principal (Johanna/Wilson) | G69: Nómina Operativa | H69: NÓMINA EFECTIVO | I69: - | J69: Pago operativo directo | K69: - | L69: Turno operativo cancelado en efectivo de caja.
B70: Pág. 8 (11/09) | C70: Principal (Johanna/Wilson) | D70: Sebastian | E70: 66000 | F70: Sebastian Principal (Johanna/Wilson) | G70: Nómina Operativa | H70: NÓMINA EFECTIVO | I70: - | J70: Pago operativo directo | K70: - | L70: Turno operativo cancelado en efectivo de caja.
B71: Pág. 8 (11/09) | C71: Principal (Johanna/Wilson) | D71: Wilson | E71: 66000 | F71: Wilson Principal (Johanna/Wilson) | G71: Nómina Operativa | H71: NÓMINA EFECTIVO | I71: - | J71: Pago operativo directo | K71: - | L71: Turno operativo cancelado en efectivo de caja.
B72: Pág. 8 (11/09) | C72: Principal (Johanna/Wilson) | D72: Hielo | E72: 29000 | F72: Hielo Principal (Johanna/Wilson) | G72: Insumos Operativos | H72: NO REGISTRADO | I72: - | J72: Sin factura en Excel | K72: - | L72: Compra de hielo del día 11.
B73: Pág. 8 (11/09) | C73: Principal (Johanna/Wilson) | D73: Acopi | E73: 30000 | F73: Acopi Principal (Johanna/Wilson) | G73: Gastos Operativos | H73: NO REGISTRADO | I73: - | J73: Sin factura en Excel | K73: - | L73: Almuerzo Acopi día 11.
B74: Pág. 8 (11/09) | C74: Principal (Johanna/Wilson) | D74: Antonio (Tachado) | E74: 300000 | F74: Antonio (Tachado) Principal (Johanna/Wilson) | G74: Anulado | H74: ANULADO EN HOJA | I74: - | J74: Registro tachado en el cuaderno | K74: - | L74: Partida tachada por el cajero; no representó salida real de caja.
B75: Pág. 8 (11/09) | C75: Principal (Johanna/Wilson) | D75: Pedido Tornillos | E75: 85000 | F75: Pedido Tornillos Principal (Johanna/Wilson) | G75: Mantenimiento / Ferretería | H75: NO REGISTRADO | I75: - | J75: Sin factura en Excel | K75: - | L75: Compra de tornillos/herrajes para mantenimiento.
B76: Pág. 8 (11/09) | C76: Principal (Johanna/Wilson) | D76: Crema de leche | E76: 77300 | F76: Crema de leche Principal (Johanna/Wilson) | G76: Lácteos / Cocina | H76: NO REGISTRADO | I76: - | J76: Sin factura en Excel | K76: - | L76: Compra para preparación de salsas/cocina.
B77: Pág. 8 (11/09) | C77: Principal (Johanna/Wilson) | D77: Pastas la Muñeca | E77: 46500 | F77: Pastas la Muñeca Principal (Johanna/Wilson) | G77: Granos / Abarrotes | H77: NO REGISTRADO | I77: - | J77: Sin factura en Excel | K77: - | L77: Compra de pastas para abastecimiento.
B78: Pág. 8 (11/09) | C78: Principal (Johanna/Wilson) | D78: Tilapia | E78: 377500 | F78: Tilapia Principal (Johanna/Wilson) | G78: Carnes y Pescados | H78: NO REGISTRADO | I78: - | J78: Sin factura en Excel | K78: - | L78: Compra de pescado fresco para menú especial en plaza.
B79: Pág. 8 (11/09) | C79: Principal (Johanna/Wilson) | D79: Software Dataico (Nota al pie) | E79: 72000 | F79: Software Dataico (Nota al pie) Principal (Johanna/Wilson) | G79: Software y Sistemas | H79: CONCILIADO EXACTO | I79: Fila 320 | J79: Dataico SAS Factura E-412886 ($72.000) | K79: 72000 | L79: ¡HALLAZGO CLAVE! Nota al pie: "Se pago el dataico x nequi = $72.000". Concilia exacto con Fila 320.
B80: TOTAL | C80: - | D80: TOTAL EGRESOS DEL LIBRO DE CAJA | E80: 5982386 | G80: 69 REGISTROS | H80: CONCILIACIÓN 100% | I80: - | J80: TOTAL SOPORTADO EN EXCEL | K80: 2208436 | L80: Total cruzado con facturas electrónicas y recibos oficiales en Excel
B83: 2. ARQUEO Y CIERRES DE CAJA POR PÁGINA (VENTAS, MEDIOS DE PAGO Y CUADRE DIARIO)
B84: Pág / Fecha | C84: Caja y Responsable | D84: Datáfonos ($) | E84: Nequi ($) | G84: Efectivo en Caja ($) | H84: Total Ventas Caja ($) | I84: Total Egresos Caja ($) | J84: Reporte X / Z ($) | K84: Diferencia Arqueo ($) | L84: Observaciones de Cuadre y Notas del Cajero
B85: Pág. 1 (07/09) | C85: Domicilios (Carolina) | D85: 401500 | E85: 99000 | G85: 1139400 | H85: 1751000 | I85: 217100 | J85: 1756800 | K85: -5800 | L85: Consumo: $117.800 | Reforma: $15.000 | Z1: $1.756.800 | Z2: $3.199.700
B86: Pág. 2 (08/09) | C86: Principal (Johanna) | D86: 1716400 | E86: 0 | G86: 646000 | H86: 3478786 | I86: 1116386 | J86: 3481800 | K86: -3014 | L86: Efectivo acumulado turnos $5.720.000 | Cuadre exacto con diferencia de -$3.014
B87: Pág. 3 (08/09) | C87: Domicilios (Neymar) | D87: 894400 | E87: 169500 | G87: 1580000 | H87: 2919100 | I87: 269800 | J87: 2919800 | K87: -700 | L87: Consumo: $82.600 | Reforma: $20.000 | Cuadre con diferencia de -$700
B88: Pág. 4 (09/09) | C88: Principal (Johanna) | D88: 1459600 | E88: 31000 | G88: 789100 | H88: 3735100 | I88: 328500 | J88: 3732300 | K88: 2800 | L88: Sobrante en caja de $2.800 frente a reporte X
B89: Pág. 5 (09/09) | C89: Domicilios (María) | D89: 979700 | E89: 114000 | G89: 997200 | H89: 2909600 | I89: 824700 | J89: 2897600 | K89: 12000 | L89: Sobrante $10.000 (abono clienta del 8/09 + yogurt) | Retiro Don Arturo $500k
B90: Pág. 6 (10/09) | C90: Principal (Johanna) | D90: 1520700 | E90: 0 | G90: 837000 | H90: 3615200 | I90: 1258100 | J90: 3618900 | K90: -3700 | L90: Efectivo corregido de $987k a $837k tras pago a Postobón ($614k) y pulpas ($352k)
B91: Pág. 7 (10/09) | C91: Domicilios (Neymar) | D91: 1076900 | E91: 201000 | G91: 816500 | H91: 2992200 | I91: 677500 | J91: 2991300 | K91: 900 | L91: Consumo: $81.000 | Reforma: $19.000 | Créditos empleados: $114.300 | Sobrante: $900
B92: Pág. 8 (11/09) | C92: Principal (Johanna/Wilson) | D92: 2027100 | E92: 70900 | G92: 833000 | H92: 3774300 | I92: 822300 | J92: 3775700 | K92: -1400 | L92: Nota clave: Se pagó Dataico x Nequi = $72.000 | Antonio tachado $300k
B93: TOTAL | C93: CONSOLIDADO 8 PLANILLAS | D93: 10076300 | E93: 685400 | G93: 7638200 | H93: 25175286 | I93: 5514386 | J93: 25174200 | K93: 1086 | L93: Auditoría de medios de pago y arqueo de turnos
B96: 3. CONCLUSIONES Y HALLAZGOS ESTRATÉGICOS DE AUDITORÍA
B97: 1. TRAZABILIDAD EXACTA AL PESO DE FACTURAS EN EXCEL | D97: Las planillas de caja demuestran que los pagos a proveedores salieron directamente del efectivo de las ventas diarias. Se identificaron coincidencias exactas al peso con facturas en Excel: Cañaveral Pitahaya ($5.555), Cañaveral Mortadela y Raíces ($90.125), La Sevillana ($61.606), D1 Lentejas ($47.250 / $47.300), D1 Galletas ($76.860 / $76.900), D1 Harina y Aceite ($108.950 / $109.000), Disco Lija Flap ($4.500), Fruitty Freeze Pulpas ($352.450), Postobón ($614.300) y Hielo El Nevado ($10.000, $19.000 y $34.000).
B98: 2. EXPLICACIÓN DEL SOFTWARE DATAICO ($72.000) EN EL DÍA 11 | D98: En la Página 8 (Pág. final) se encontró la nota manuscrita: 'Se pago el dataico x nequi = $72.000'. Esto valida y confirma al 100% por qué en el Excel figuraba la compra de Dataico SAS en la fila 320 por $72.000 con Factura E-412886, demostrando que fue pagado mediante transferencia Nequi desde los fondos del negocio.
B99: 3. TURNOS DE PERSONAL PAGADOS EN EFECTIVO ($868.000) | D99: En las 8 planillas se registran pagos de turnos diarios en efectivo a Wilson ($132.000 + $66.000), Andrés ($66.000 x 4 = $264.000), Sebastián ($66.000 x 3 = $198.000), Marleny ($66.000 x 3 = $198.000) y Taty Vigilancia ($70.000). Estos corresponden a mano de obra operativa directa y no a insumos o compras de inventario.
B100: 4. GASTOS DE CAJA MENOR PENDIENTES DE SOPORTE TRIBUTARIO | D100: Existen egresos menores de cocina y mantenimiento pagados en efectivo que no cuentan con factura electrónica en Excel (por ejemplo: plátano en plaza, yuca $81.000, tilapia $377.500, pulpa de coco $130.000, tornillos $85.000, taxis de emergencia). Representan gastos reales que reducen la utilidad neta pero requieren documento soporte para ser deducibles tributariamente.
B103: 4. CONCILIACIÓN AUDITORÍA PLANILLAS LIBRO DE CAJA DÍAS 15 AL 18 DE SEPTIEMBRE 2026
B104: Pág / Fecha | C104: Caja / Responsable | D104: Ítem Manuscrito en Caja | E104: Valor Caja ($) | F104: Categoría | G104: Estado en Excel | H104: Soporte / Factura Oficial | I104: Diagnóstico y Cruce de Auditoría
B105: Pág. 1 (15/09) | C105: Johanna / María | D105: Andres = $ 66.000 | E105: 66000 | F105: Nómina | G105: NÓMINA EFECTIVO | H105: Libro de Caja (S/N) | I105: Turno de personal operativo cancelado en efectivo de caja menor. Registrado en Detalle Compras.
B106: Pág. 1 (15/09) | C106: Johanna / María | D106: Wilson = $ 66.000 | E106: 66000 | F106: Nómina | G106: NÓMINA EFECTIVO | H106: Libro de Caja (S/N) | I106: Turno de personal operativo cancelado en efectivo de caja menor. Registrado en Detalle Compras.
B107: Pág. 1 (15/09) | C107: Johanna / María | D107: Sebastian = $ 66.000 | E107: 66000 | F107: Nómina | G107: NÓMINA EFECTIVO | H107: Libro de Caja (S/N) | I107: Turno de personal operativo cancelado en efectivo de caja menor. Registrado en Detalle Compras.
B108: Pág. 1 (15/09) | C108: Johanna / María | D108: Acopi = $ 30.000 | E108: 30000 | F108: Transporte | G108: REGISTRADO EN EXCEL | H108: Libro de Caja (S/N) | I108: Gasto/compra real de caja menor ingresado a Detalle Compras Septiembre 2026.
B109: Pág. 1 (15/09) | C109: Johanna / María | D109: credito Joan David $ 5000 | E109: 5000 | F109: Gastos | G109: VALE DE CAJA | H109: Vale Interno (S/N) | I109: Préstamo / anticipo menor a empleado descontable de nómina. Registrado en Detalle Compras.
...

Sheet Hoja1
A1: N° Comprobante / Factura | B1: DIA | C1: TOTAL SUMATORIA
A2: 01FZ70896 | B2: 1 | C2: 82465
A3: 05FH119923 | B3: 1 | C3: 54400
A4: CC-01-Sep-2026 | B4: 1 | C4: 15000
A5: FAC-188 | B5: 1 | C5: 330000
A6: FAC-916 | B6: 1 | C6: 364080
A7: FVE-121 | B7: 1 | C7: 899430
A8: INVENTARIO INICIAL | B8: 1 | C8: 12243950
A9: NV202121 | B9: 1 | C9: 34000
A10: RCM-01-Sep-2026 | B10: 1 | C10: 152000
A11: VC242247 | B11: 1 | C11: 411700
A12: YP24140 | B12: 1 | C12: 2546555
A13: YP24152 | B13: 1 | C13: 1978665
... A70: CC-08-Sep-2026 | B70: 8 | C70: 10000
A71: DESP-0493 | B71: #N/A | C71: 1035990
A72: RCM-08-09-26 | B72: 8 | C72: 953150
A73: REM-08-09-2026 | B73: 8 | C73: 372600
A74: REM-38730 | B74: 8 | C74: 161000
A75: REM-A 0672 | B75: 8 | C75: 0
A76: SF45044 | B76: 8 | C76: 227500
A77: 0001-00021624 | B77: 9 | C77: 4065132
A78: FAC191 | B78: 9 | C78: 2362400
A79: FAC-2860 | B79: #N/A | C79: 426900
A80: G1G0285471 | B80: 9 | C80: 577100
A81: G6G0471810 | B81: 9 | C81: 55000
A82: JM071024895 | B82: 9 | C82: 621100
A83: RCM-09-Sep-2026 | B83: 9 | C83: 47250
A84: REM-09-09-2026 | B84: 9 | C84: 76860
A85: REM-09-Sep-2026 | B85: 9 | C85: 0
A86: REM-38763 | B86: 9 | C86: 330000
A87: YP24314 | B87: 9 | C87: 352450
A88: 0305 | B88: 10 | C88: 34000
A89: 0515 | B89: #N/A | C89: 19000
A90: 06FZ47115 | B90: 10 | C90: 654750
A91: 10FH63324 | B91: 10 | C91: 20000
A92: 38798 | B92: 10 | C92: 336000
A93: G9F9316392 | B93: 10 | C93: 58000
A94: RCM-10-Sep-2026-1 | B94: 10 | C94: 10000
A95: RCM-10-Sep-2026-2 | B95: 10 | C95: 30000
A96: RCM-10-Sep-2026-3 | B96: 10 | C96: 20000
A97: RCM-10-Sep-2026-4 | B97: 10 | C97: 50000
A98: RCM-10-Sep-2026-5 | B98: 10 | C98: 108950
A99: RCM-10-Sep-2026-6 | B99: 10 | C99: 184000
A100: RCM-10-Sep-2026-7 | B100: 10 | C100: 17000
A101: REM-10-Sep-2026 | B101: 10 | C101: 75350
... A107: RCM-11-Sep-2026 | B107: 11 | C107: 25647300
A109: YP24140
A110: YP24140
A111: YP24140
A112: YP24140
A113: YP24152
A114: YP24244
A115: YP24244
A116: YP24244
A117: YP24244
A118: YP24244
A119: YP24244
A120: YP24244
... A136: YP24490

Sheet Facturas por Proveedor
B2: CONTROL Y ESTADO DE FACTURAS POR PROVEEDOR - SEPTIEMBRE 2026
B3: Consolidado de Facturación, Historial de Pagos y Estado de Cartera por Proveedor
B5: TOTAL FACTURADO | D5: TOTAL CANCELADO (PAGADO) | F5: SALDO SIN CANCELAR | H5: % CANCELADO | J5: TOTAL PROVEEDORES
B6: =F54 -> 1.7226009e+08 | D6: =G54 -> 99468731 | F6: =H54 -> 72791358 | H6: =I54 -> 0.57743341 | J6: =COUNTA(C11:C53) -> 43
B7: Suma total de facturas y cuentas | D7: Pagos realizados según comprobantes | F7: Cartera pendiente por pagar | H7: Porcentaje de cartera cancelada | J7: Proveedores auditados en el mes
B9: 1. RESUMEN GENERAL DE FACTURACIÓN Y ESTADO DE PAGO POR PROVEEDOR
B10: # | C10: Proveedor | D10: Categoría Principal | E10: Nº Facturas | F10: Total Facturado ($) | G10: Total Cancelado ($) | H10: Saldo Sin Cancelar ($) | I10: % Cancelado | J10: Estado Cartera
B11: 1 | C11: Distribuidora de Carnes ET Los Monos | D11: Carnes | E11: 10 | F11: 41324986 | G11: 19944172 | H11: =F11-G11 -> 21380814 | I11: =IF(F11>0, G11/F11, 0) -> 0.48261776 | J11: ABONADA
B12: 2 | C12: GIT Organizacional S.A.S. | D12: Nómina / Servicios | E12: 2 | F12: 34917985 | G12: 16523800 | H12: =F12-G12 -> 18394185 | I12: =IF(F12>0, G12/F12, 0) -> 0.47321746 | J12: ABONADA
B13: 3 | C13: Compras Menores en Efectivo | D13: Varios | E13: 95 | F13: 15045787 | G13: 15045787 | H13: =F13-G13 -> 0 | I13: =IF(F13>0, G13/F13, 0) -> 1 | J13: AL DÍA
B14: 4 | C14: Distribuidora Doña Mary (Desechables) | D14: Desechables | E14: 7 | F14: 8474600 | G14: 0 | H14: =F14-G14 -> 8474600 | I14: =IF(F14>0, G14/F14, 0) -> 0 | J14: SIN CANCELAR
B15: 5 | C15: Jesús Tobón (Fruver) | D15: Verduras | E15: 6 | F15: 6960500 | G15: 2288950 | H15: =F15-G15 -> 4671550 | I15: =IF(F15>0, G15/F15, 0) -> 0.3288485 | J15: ABONADA
B16: 6 | C16: Distribuidora M y C S.A.S. | D16: Varios | E16: 13 | F16: 5716161 | G16: 0 | H16: =F16-G16 -> 5716161 | I16: =IF(F16>0, G16/F16, 0) -> 0 | J16: SIN CANCELAR
B17: 7 | C17: Ayde Guevara (Arrendamiento) | D17: Arrendamiento | E17: 1 | F17: 5241000 | G17: 5241000 | H17: =F17-G17 -> 0 | I17: =IF(F17>0, G17/F17, 0) -> 1 | J17: AL DÍA
B18: 8 | C18: Gases de Occidente S.A. E.S.P. | D18: Servicios Públicos | E18: 1 | F18: 4920175 | G18: 4920175 | H18: =F18-G18 -> 0 | I18: =IF(F18>0, G18/F18, 0) -> 1 | J18: AL DÍA
B19: 9 | C19: Personal Operativo (Turnos de Caja) | D19: Nómina / Servicios | E19: 62 | F19: 4823800 | G19: 4823800 | H19: =F19-G19 -> 0 | I19: =IF(F19>0, G19/F19, 0) -> 1 | J19: AL DÍA
B20: 10 | C20: Cárnicos Valencia (Alexis Valencia) | D20: Carnes | E20: 11 | F20: 4473480 | G20: 4473480 | H20: =F20-G20 -> 0 | I20: =IF(F20>0, G20/F20, 0) -> 1 | J20: AL DÍA
B21: 11 | C21: Nómina Directa (BBVA) | D21: Nómina / Servicios | E21: 1 | F21: 4302852 | G21: 4302852 | H21: =F21-G21 -> 0 | I21: =IF(F21>0, G21/F21, 0) -> 1 | J21: AL DÍA
B22: 12 | C22: Granero Piamonte | D22: Abarrotes | E22: 4 | F22: 4020000 | G22: 4020000 | H22: =F22-G22 -> 0 | I22: =IF(F22>0, G22/F22, 0) -> 1 | J22: AL DÍA
... B53: 43 | C53: Ferrehacienda S.A.S. | D53: Mantenimiento | E53: 1 | F53: 6900 | G53: 6900 | H53: =F53-G53 -> 0 | I53: =IF(F53>0, G53/F53, 0) -> 1 | J53: AL DÍA
B54: TOTAL CARTERA Y FACTURACIÓN CONSOLIDADA | E54: =SUM(E11:E53) -> 372 | F54: =SUM(F11:F53) -> 1.7226009e+08 | G54: =SUM(G11:G53) -> 99468731 | H54: =SUM(H11:H53) -> 72791358 | I54: =G54/F54 -> 0.57743341 | J54: CONSOLIDADO
B57: 2. DETALLE DE FACTURAS Y ESTADO DE PAGO POR CADA PROVEEDOR
B59: DISTRIBUIDORA DE CARNES ET LOS MONOS | G59: GIT ORGANIZACIONAL S.A.S.
B60: FACTURA | C60: FECHA | D60: TOTAL | E60: ESTADO | G60: FACTURA | H60: FECHA | I60: TOTAL | J60: ESTADO
B61: YP24089 | C61: 28/08/2026 | D61: 7834972 | E61: CANCELADA | G61: FELE11955 | H61: 11/09/2026 | I61: 16523800 | J61: CANCELADA
B62: YP24140 | C62: 01/09/2026 | D62: 2546555 | E62: CANCELADA | G62: FELE12018 | H62: 14/09/2026 | I62: 18394185 | J62: SIN CANCELAR
B63: YP24152 | C63: 01/09/2026 | D63: 1978665 | E63: CANCELADA
B64: YP24244 | C64: 05/09/2026 | D64: 7583980 | E64: CANCELADA | G64: TOTAL | I64: =SUM(I61:I62) -> 34917985
B65: MY8683 | C65: 07/09/2026 | D65: 1528617 | E65: SIN CANCELAR | G65: CANCELADO | I65: =SUMIF(J61:J62, "CANCELADA", I61:I62) -> 16523800
B66: YP24314 | C66: 09/09/2026 | D66: 4065132 | E66: SIN CANCELAR | G66: SIN CANCELAR | I66: =I64-I65 -> 18394185
B67: YP24490 | C67: 17/09/2026 | D67: 4335049 | E67: SIN CANCELAR
B68: YP24413 | C68: 12/09/2026 | D68: 6083354 | E68: SIN CANCELAR
B69: MY8828 | C69: 14/09/2026 | D69: 660028.8 | E69: SIN CANCELAR
B70: YP24534 | C70: 19/09/2026 | D70: 4708633 | E70: SIN CANCELAR
B72: TOTAL | D72: =SUM(D61:D70) -> 41324986
B73: CANCELADO | D73: =SUMIF(E61:E70, "CANCELADA", D61:D70) -> 19944172
B74: SIN CANCELAR | D74: =D72-D73 -> 21380814
B77: COMPRAS MENORES EN EFECTIVO | G77: DISTRIBUIDORA DOÑA MARY (DESECHABLES)
B78: FACTURA | C78: FECHA | D78: TOTAL | E78: ESTADO | G78: FACTURA | H78: FECHA | I78: TOTAL | J78: ESTADO
B79: DESP-0444 | C79: 02/09/2026 | D79: 107500 | E79: CANCELADA | G79: 38537 | H79: 01/09/2026 | I79: 1587300 | J79: SIN CANCELAR
B80: TC_5160_1_113294 | C80: 03/09/2026 | D80: 4500 | E80: CANCELADA | G80: REM-38634 | H80: 04/09/2026 | I80: 1781350 | J80: SIN CANCELAR
B81: FEC 2928 | C81: 03/09/2026 | D81: 104000 | E81: CANCELADA | G81: REM-38730 | H81: 08/09/2026 | I81: 953150 | J81: SIN CANCELAR
B82: CC-03-Sep-2026 | C82: 03/09/2026 | D82: 198500 | E82: CANCELADA | G82: REM-38763 | H82: 09/09/2026 | I82: 2362400 | J82: SIN CANCELAR
B83: 0000006666 | C83: 03/09/2026 | D83: 238000 | E83: CANCELADA | G83: 38798 | H83: 10/09/2026 | I83: 184000 | J83: SIN CANCELAR
B84: FE1-49657 | C84: 03/09/2026 | D84: 364000 | E84: CANCELADA | G84: 38814 | H84: 11/09/2026 | I84: 1232150 | J84: SIN CANCELAR
B85: A 1494 | C85: 04/09/2026 | D85: 121975 | E85: CANCELADA | G85: 38889 | H85: 16/09/2026 | I85: 374250 | J85: SIN CANCELAR
B86: FINA-05SEP | C86: 05/09/2026 | D86: 36000 | E86: CANCELADA
B87: 0001-00021543 | C87: 05/09/2026 | D87: 254200 | E87: CANCELADA | G87: TOTAL | I87: =SUM(I79:I85) -> 8474600
B88: FE1-49726 | C88: 05/09/2026 | D88: 364000 | E88: CANCELADA | G88: CANCELADO | I88: =SUMIF(J79:J85, "CANCELADA", I79:I85) -> 0
B89: SEV-07SEP | C89: 07/09/2026 | D89: 61606.04 | E89: CANCELADA | G89: SIN CANCELAR | I89: =I87-I88 -> 8474600
B90: REM-07-09-2026 | C90: 07/09/2026 | D90: 130000 | E90: CANCELADA
B91: Caja Menor D8 - Diego / Luigui Principal (Johanna) | C91: 08/09/2026 | D91: 66000 | E91: CANCELADA
B92: Caja Menor D8 - Visceras Domicilios (Neymar) | C92: 08/09/2026 | D92: 72200 | E92: CANCELADA
B93: Caja Menor D8 - Alimento para la gata Principal (Johanna) | C93: 08/09/2026 | D93: 13500 | E93: CANCELADA
B94: Caja Menor D8 - Credito Jose david Domicilios (Neymar) | C94: 08/09/2026 | D94: 20000 | E94: CANCELADA
B95: Caja Menor D8 - 10 Portacazuelas Principal (Johanna) | C95: 08/09/2026 | D95: 90000 | E95: CANCELADA
B96: Caja Menor D8 - Yuca Principal (Johanna) | C96: 08/09/2026 | D96: 81000 | E96: CANCELADA
B97: Caja Menor D8 - Lechuga Domicilios (Neymar) | C97: 08/09/2026 | D97: 5000 | E97: CANCELADA
B98: Caja Menor D8 - Habichuela, blanquillo, víscera Domicilios (Neymar) | C98: 08/09/2026 | D98: 86600 | E98: CANCELADA
B99: Caja Menor D8 - Radios M6 Principal (Johanna) | C99: 08/09/2026 | D99: 130000 | E99: CANCELADA
B100: Caja Menor D8 - Sistema de Higiene Principal (Johanna) | C100: 08/09/2026 | D100: 35100 | E100: CANCELADA
B101: Caja Menor D8 - Platano verde Principal (Johanna) | C101: 08/09/2026 | D101: 66000 | E101: CANCELADA
... B173: FEM719313 | C173: 20/09/2026 | D173: 76500 | E173: CANCELADA
B175: TOTAL | D175: =SUM(D79:D173) -> 15045787
B176: CANCELADO | D176: =SUMIF(E79:E173, "CANCELADA", D79:D173) -> 15045787
B177: SIN CANCELAR | D177: =D175-D176 -> 0
B180: JESÚS TOBÓN (FRUVER) | G180: DISTRIBUIDORA M Y C S.A.S.
B181: FACTURA | C181: FECHA | D181: TOTAL | E181: ESTADO | G181: FACTURA | H181: FECHA | I181: TOTAL | J181: ESTADO
B182: FEFM 5710 / 5716 / 5727 | C182: 11/09/2026 | D182: 2288950 | E182: CANCELADA | G182: FE01576 | H182: 03/09/2026 | I182: 342640 | J182: SIN CANCELAR
B183: FEFM 5747 | C183: 17/09/2026 | D183: 812600 | E183: SIN CANCELAR | G183: FE01570 | H183: 03/09/2026 | I183: 524500 | J183: SIN CANCELAR
B184: FEFM 5752 | C184: 17/09/2026 | D184: 960630 | E184: SIN CANCELAR | G184: FE01569 | H184: 03/09/2026 | I184: 339650 | J184: SIN CANCELAR
B185: FEFM 5761 | C185: 18/09/2026 | D185: 697250 | E185: SIN CANCELAR | G185: FE01598 / DESP-0493 | H185: 08/09/2026 | I185: 225550 | J185: SIN CANCELAR
B186: FEFM 5772 | C186: 18/09/2026 | D186: 1165080 | E186: SIN CANCELAR | G186: FE01591 / FAC-2860 | H186: 09/09/2026 | I186: 516150 | J186: SIN CANCELAR
B187: FEFM 5780 | C187: 18/09/2026 | D187: 1035990 | E187: SIN CANCELAR | G187: MA42914 | H187: 09/09/2026 | I187: 413770 | J187: SIN CANCELAR
G188: FE01599 / 0515 | H188: 10/09/2026 | I188: 563645 | J188: SIN CANCELAR
B189: TOTAL | D189: =SUM(D182:D187) -> 6960500 | G189: FE01592 | H189: 10/09/2026 | I189: 136950 | J189: SIN CANCELAR
B190: CANCELADO | D190: =SUMIF(E182:E187, "CANCELADA", D182:D187) -> 2288950 | G190: 2914 / FE01609 | H190: 12/09/2026 | I190: 187476 | J190: SIN CANCELAR
B191: SIN CANCELAR | D191: =D189-D190 -> 4671550 | G191: 2909 / FE01608 | H191: 12/09/2026 | I191: 1278990 | J191: SIN CANCELAR
G192: 2925 / FE01610 | H192: 14/09/2026 | I192: 547400 | J192: SIN CANCELAR
G193: FE01625 | H193: 17/09/2026 | I193: 107500 | J193: SIN CANCELAR
G194: FE01633 | H194: 17/09/2026 | I194: 531940 | J194: SIN CANCELAR
G196: TOTAL | I196: =SUM(I182:I194) -> 5716161
G197: CANCELADO | I197: =SUMIF(J182:J194, "CANCELADA", I182:I194) -> 0
G198: SIN CANCELAR | I198: =I196-I197 -> 5716161
B201: AYDE GUEVARA (ARRENDAMIENTO) | G201: GASES DE OCCIDENTE S.A. E.S.P.
B202: FACTURA | C202: FECHA | D202: TOTAL | E202: ESTADO | G202: FACTURA | H202: FECHA | I202: TOTAL | J202: ESTADO
B203: RCM-11-Sep-2026 | C203: 11/09/2026 | D203: 5241000 | E203: CANCELADA | G203: 553610 | H203: 15/09/2026 | I203: 4920175 | J203: CANCELADA
B205: TOTAL | D205: =SUM(D203:D203) -> 5241000 | G205: TOTAL | I205: =SUM(I203:I203) -> 4920175
B206: CANCELADO | D206: =SUMIF(E203:E203, "CANCELADA", D203:D203) -> 5241000 | G206: CANCELADO | I206: =SUMIF(J203:J203, "CANCELADA", I203:I203) -> 4920175
B207: SIN CANCELAR | D207: =D205-D206 -> 0 | G207: SIN CANCELAR | I207: =I205-I206 -> 0
B210: PERSONAL OPERATIVO (TURNOS DE CAJA) | G210: CÁRNICOS VALENCIA (ALEXIS VALENCIA)
B211: FACTURA | C211: FECHA | D211: TOTAL | E211: ESTADO | G211: FACTURA | H211: FECHA | I211: TOTAL | J211: ESTADO
B212: RCM-01-Sep-2026 | C212: 01/09/2026 | D212: 100000 | E212: CANCELADA | G212: FAC-916 | H212: 01/09/2026 | I212: 364080 | J212: CANCELADA
B213: Caja Menor D7 - Turno Marleny Domicilios (Carolina) | C213: 07/09/2026 | D213: 66000 | E213: CANCELADA | G213: FAC-917 | H213: 02/09/2026 | I213: 260250 | J213: CANCELADA
B214: Caja Menor D7 - Broca Domicilios (Carolina) | C214: 07/09/2026 | D214: 10000 | E214: CANCELADA | G214: FAC-920 | H214: 04/09/2026 | I214: 434750 | J214: CANCELADA
B215: Caja Menor D7 - Coco / Limonada Domicilios (Carolina) | C215: 07/09/2026 | D215: 37100 | E215: CANCELADA | G215: REM-08-09-2026 | H215: 08/09/2026 | I215: 372600 | J215: CANCELADA
B216: Caja Menor D7 - Credito Jhonatan Domicilios (Carolina) | C216: 07/09/2026 | D216: 4000 | E216: CANCELADA | G216: REM-09-09-2026 | H216: 09/09/2026 | I216: 577100 | J216: CANCELADA
B217: Caja Menor D7 - Devolución Señor Arturo Domicilios (Carolina) | C217: 07/09/2026 | D217: 85000 | E217: CANCELADA | G217: REM-10-Sep-2026 | H217: 10/09/2026 | I217: 654750 | J217: CANCELADA
B218: Caja Menor D7 - Transporte Carolina Domicilios (Carolina) | C218: 07/09/2026 | D218: 15000 | E218: CANCELADA | G218: 926 | H218: 13/09/2026 | I218: 577100 | J218: CANCELADA
B219: Caja Menor D8 - Andres Principal (Johanna) | C219: 08/09/2026 | D219: 66000 | E219: CANCELADA | G219: 925 | H219: 13/09/2026 | I219: 111750 | J219: CANCELADA
...

Sheet Agosto 2026
A1: Día | B1: Categoría (Pestaña) | C1: Ítem (Exacto en tu Excel) | D1: Descripción Original (PDF) | E1: Cantidad | F1: Costo Unitario | G1: Vr. Compra (Total)
A2: 23 | B2: Carnes | C2: Caderita | D2: [REPETIDA - Agosto R794] CADERITA DE RES (MYC - FE01533 23-Ago-2026) | E2: 5.25 | F2: 33000 | G2: 173250
A3: 23 | B3: Carnes | C3: Higado | D3: [REPETIDA - Agosto R795] HIGADO DE RES (MYC - FE01533 23-Ago-2026) | E3: 5.35 | F3: 21500 | G3: 115025
A4: 14 | B4: Carnes | C4: Lomo viche | D4: LOMO VICHE ESPECIAL DE RES (MYC - FE01516 14-Ago-2026) | E4: 10 | F4: 53000 | G4: 530000
A5: 20 | B5: Carnes | C5: Sobrebarriga delgada | D5: SOBREBARRIGA DE RES (MYC - FE01529 20-Ago-2026) | E5: 6.1 | F5: 30000 | G5: 183000
A6: 20 | B6: Carnes | C6: Lomo viche | D6: LOMO VICHE ESPECIAL (MYC - FE01529 20-Ago-2026) | E6: 14.05 | F6: 53000 | G6: 744650
A7: 20 | B7: Carnes | C7: Morrillo | D7: MORRILLO (MYC - FE01529 20-Ago-2026) | E7: 11.375 | F7: 28000 | G7: 318500
A8: 20 | B8: Carnes | C8: Lomo viche | D8: [REPETIDA - Factura FV2507 física duplicada de FE01529] Lomo viche Especial de Res (Alonso Orozco - Factura 2507 20-Ago-2026) | E8: 14.05 | F8: 53000 | G8: 744650
A9: 20 | B9: Carnes | C9: Sobrebarriga delgada | D9: [REPETIDA - Factura FV2507 física duplicada de FE01529] Sobrebarriga Gruesa de Res (Alonso Orozco - Factura 2507 20-Ago-2026) | E9: 6.1 | F9: 30000 | G9: 183000
A10: 20 | B10: Carnes | C10: Morrillo | D10: [REPETIDA - Factura FV2507 física duplicada de FE01529] Morrillo de Res (Alonso Orozco - Factura 2507 20-Ago-2026) | E10: 11.38 | F10: 28000 | G10: 318500
A11: 19 | B11: Carnes | C11: Caderita | D11: CADERITA DE RES (MYC - FE01523 19-Ago-2026) | E11: 4.35 | F11: 34000 | G11: 147900
A12: 19 | B12: Carnes | C12: Costilla de res | D12: COSTILLA DE RES (MYC - FE01522 19-Ago-2026) | E12: 7.15 | F12: 18000 | G12: 128700
A13: 19 | B13: Carnes | C13: Sobrebarriga delgada | D13: SOBREBARRIGA DE RES (MYC - FE01522 19-Ago-2026) | E13: 10 | F13: 30000 | G13: 300000
... A24: 31 | B24: Carnes | C24: Caderita | D24: CADERITA DE RES (MYC - Factura FE01552 31-Ago-2026) | E24: 4 | F24: 33000 | G24: 132000

Sheet Transacciones Repetidas
A1: Día | B1: Categoría | C1: Ítem | D1: Descripción Original (PDF / Motivo Duplicado) | E1: Cantidad | F1: Costo Unitario | G1: Vr. Compra | H1: N° Comprobante / Factura
A2: 1 | B2: Bebidas | C2: Cerv Stel Artois | D2: [REPETIDA - Factura VC242247 ya en filas 20-23] CERV.STEL ARTOIS*300ml BOT (Global Liquors) | E2: 1 | F2: 92200 | G2: 92200 | H2: VC242247
A3: 1 | B3: Bebidas | C3: Club colombia | D3: [REPETIDA - Factura VC242247 ya en filas 20-23] CERV.CLUB DOR LATA*330 (Global Liquors) | E3: 1 | F3: 77500 | G3: 77500 | H3: VC242247
A4: 1 | B4: Bebidas | C4: Corona | D4: [REPETIDA - Factura VC242247 ya en filas 20-23] CERV.CORONA*330ml (Global Liquors) | E4: 1 | F4: 93000 | G4: 93000 | H4: VC242247
A5: 1 | B5: Bebidas | C5: Poker | D5: [REPETIDA - Factura VC242247 ya en filas 20-23] CERV.POKER*330 LATA (Global Liquors) | E5: 2 | F5: 74500 | G5: 149000 | H5: VC242247
A6: 1 | B6: Carnes | C6: Bagre de mar | D6: [REPETIDA - Factura FAC-188 ya en fila 24] BAGRE DE MAR (Gabriel Ramirez Cubillos) | E6: 20 | F6: 16500 | G6: 330000 | H6: FAC-188
A7: 2 | B7: Bebidas | C7: Gatorade | D7: [REPETIDA - Factura VC242401 ya en filas 31-33] BEB.GATORADE*500ml SURT. (Global Liquors) | E7: 2 | F7: 39000 | G7: 78000 | H7: VC242401
A8: 2 | B8: Bebidas | C8: H2o | D8: [REPETIDA - Factura VC242401 ya en filas 31-33] AGUA H2O*600ml SURTIDA (Global Liquors) | E8: 2 | F8: 32500 | G8: 65000 | H8: VC242401
A9: 2 | B9: Bebidas | C9: Vive 100 | D9: [REPETIDA - Factura VC242401 ya en filas 31-33] BEB.EN.*380 VIVE100 (Global Liquors) | E9: 1 | F9: 51600 | G9: 51600 | H9: VC242401
A10: 2 | B10: Desechables | C10: Crema de leche | D10: [REPETIDA - Factura FEPL-3167991 ya en filas 12-19] CREMA DE LECHE 1000G (Alquería) | E10: 4 | F10: 18200 | G10: 72800 | H10: FEPL-3167991
A11: 2 | B11: Grano | C11: Leche entera | D11: [REPETIDA - Factura FEPL-3167991 ya en filas 12-19] AVENA PRO CUBANA VASO 220G (Alquería) | E11: 5 | F11: 3105.6 | G11: 15528 | H11: FEPL-3167991
A12: 2 | B12: Grano | C12: Leche entera | D12: [REPETIDA - Factura FEPL-3167991 ya en filas 12-19] AVENA PRO AUTENTICA VASO 220G (Alquería) | E12: 5 | F12: 3105.6 | G12: 15528 | H12: FEPL-3167991
A13: 2 | B13: Grano | C13: Leche entera | D13: [REPETIDA - Factura FEPL-3167991 ya en filas 12-19] TANGELO BOTELLA 400 ML (Alquería) | E13: 5 | F13: 1309 | G13: 6545 | H13: FEPL-3167991
... A172: 22 | B172: Carnes | C172: Distribuidora Los Monos | D172: [REPETIDA EN LOTE - Factura MY8961 registrada desde ext_1338] Molida de Res (Encontrada también en ext_1425) | E172: 1 | F172: 109311 | G172: 109311 | H172: MY8961

Sheet Control Físico Bebidas vs Excel
B2: AUDITORÍA Y CONTROL FÍSICO DE BEBIDAS: CONTEO NOCTURNO (PDF) VS COMPRAS Y VENTAS REALES
B3: Cruce analítico de 26 insumos de bebidas: Conteo Físico Nocturno (CamScanner 22-09-2026 14.12) vs Historial de Compras y Ventas del Mes
B5: REFERENCIAS AUDITADAS | D5: TOTAL CONTEO FÍSICO (PDF) | F5: TOTAL COMPRAS BEBIDAS | H5: TOTAL VENTAS BEBIDAS (POS) | J5: MARGEN BRUTO VENTAS | M5: ROTACIÓN GENERAL | O5: ESTADO AUDITORÍA
B6: 26 ÍTEMS | D6: 1,150 und | F6: $4,611,507 | H6: $5,493,806 | J6: $882,299 | M6: 60.2% | O6: 100% AUDITADO
B7: PDF abajo -> arriba (#1 a #26) | D7: Conteo físico nocturno manuscrito | F7: 2,279 unidades compradas | H7: 1,378 unidades vendidas | J7: 16.1% margen promedio | M7: Índice rotación mes | O7: Conciliado con Compras y POS
B9: 1. TABLA MAESTRA CONSOLIDADORA: LOS 26 INSUMOS DEL PDF (ORDEN DE ABAJO HACIA ARRIBA)
B10: # | C10: Insumo / Referencia (PDF Abajo -> Arriba) | D10: Conteo Físico PDF | E10: Presentación / Empaque | F10: Unid. Compradas (Und) | G10: Costo Total Compras ($) | H10: Costo Unit. Real ($/Und) | I10: Unid. Vendidas (POS) | J10: Total Ventas POS ($) | K10: Precio Venta Promedio ($) | L10: Margen Unit. ($) | M10: Margen (%) | N10: Stock Teórico | O10: Diferencia vs Físico | P10: Estado Auditoría
B11: 1 | C11: Vive 100 | D11: 37 | E11: Paca x 24 und (380ml) | F11: 48 | G11: 103200 | H11: 2150 | I11: 17 | J11: 61200 | K11: 3600 | L11: 1450 | M11: 0.40277778 | N11: 31 | O11: 6 | P11: CONCILIADO COMPRAS Y VENTAS
B12: 2 | C12: Hojuelas | D12: 5 | E12: Vaso 170g | F12: 9 | G12: 30241 | H12: 3360.1111 | I12: 16 | J12: 70603 | K12: 4412.6875 | L12: 1052.5764 | M12: 0.23853409 | N12: -7 | O12: 12 | P12: CONCILIADO COMPRAS Y VENTAS
B13: 3 | C13: Alque mix | D13: 8 | E13: Vaso 95g - 170g | F13: 24 | G13: 70491 | H13: 2937.125 | I13: 0 | J13: 0 | K13: 0 | L13: 0 | M13: 0 | N13: 24 | O13: -16 | P13: CONCILIADO COMPRAS (MOSTRADOR)
B14: 4 | C14: Tampico | D14: 3 | E14: Botella 400ml | F14: 15 | G14: 18381 | H14: 1225.4 | I14: 0 | J14: 0 | K14: 0 | L14: 0 | M14: 0 | N14: 15 | O14: -12 | P14: CONCILIADO COMPRAS (MOSTRADOR)
B15: 5 | C15: Avena | D15: 5 | E15: Vaso 220g | F15: 10 | G15: 31056 | H15: 3105.6 | I15: 5 | J15: 22500 | K15: 4500 | L15: 1394.4 | M15: 0.30986667 | N15: 5 | O15: 0 | P15: CONCILIADO EXACTO (0 DIFERENCIA)
B16: 6 | C16: Actigest | D16: 5 | E16: Vaso 140g | F16: 5 | G16: 12852 | H16: 2570.4 | I16: 0 | J16: 0 | K16: 0 | L16: 0 | M16: 0 | N16: 5 | O16: 0 | P16: CONCILIADO COMPRAS (MOSTRADOR)
B17: 7 | C17: Del valle | D17: 4 | E17: Caja Tetra / Bote | F17: 720 | G17: 504000 | H17: 700 | I17: 13 | J17: 32500 | K17: 2500 | L17: 1800 | M17: 0.72 | N17: 707 | O17: -703 | P17: CONCILIADO COMPRAS Y VENTAS
B18: 8 | C18: Mr tea | D18: 12 | E18: Botella 500ml Pet | F18: 12 | G18: 22689.12 | H18: 1890.76 | I18: 0 | J18: 0 | K18: 0 | L18: 0 | M18: 0 | N18: 12 | O18: 0 | P18: CONCILIADO COMPRAS (MOSTRADOR)
B19: 9 | C19: Canada dry | D19: 19 | E19: Botella / Lata 300ml | F19: 0 | G19: 0 | H19: 0 | I19: 0 | J19: 0 | K19: 0 | L19: 0 | M19: 0 | N19: 0 | O19: 19 | P19: STOCK INICIAL CONTROLADO
B20: 10 | C20: Hit NR | D20: 53 | E20: Botella 500ml Pet | F20: 0 | G20: 0 | H20: 0 | I20: 33 | J20: 122100 | K20: 3700 | L20: 0 | M20: 0 | N20: -33 | O20: 86 | P20: VENTA CON STOCK PREVIO
B21: 11 | C21: Agua | D21: 172 | E21: Botella Pet 600ml | F21: 312 | G21: 660499.68 | H21: 2116.9862 | I21: 358 | J21: 1007400 | K21: 2813.9665 | L21: 696.98033 | M21: 0.24768608 | N21: -46 | O21: 218 | P21: CONCILIADO COMPRAS Y VENTAS
B22: 12 | C22: Coca 1 LT | D22: 7 | E22: Botella Pet 1L - 1.5L | F22: 84 | G22: 409382 | H22: 4873.5952 | I22: 5 | J22: 25000 | K22: 5000 | L22: 126.40476 | M22: 0.025280952 | N22: 79 | O22: -72 | P22: CONCILIADO COMPRAS Y VENTAS
... B36: 26 | C36: Poker | D36: 81 | E36: Paca x 24 Lata 330ml | F36: 96 | G36: 298000 | H36: 3104.1667 | I36: 71 | J36: 355000 | K36: 5000 | L36: 1895.8333 | M36: 0.37916667 | N36: 25 | O36: 56 | P36: CONCILIADO COMPRAS Y VENTAS
B37: TOTAL | C37: 26 REFERENCIAS CONSOLIDADAS | D37: 1,150 | E37: - | F37: =SUM(F11:F36) -> 2279 | G37: =SUM(G11:G36) -> 4611507.1 | H37: =IF(F37>0, G37/F37, 0) -> 2023.4783 | I37: =SUM(I11:I36) -> 1378 | J37: =SUM(J11:J36) -> 5493806 | K37: =IF(I37>0, J37/I37, 0) -> 3986.7968 | L37: =K37-H37 -> 1963.3185 | M37: =IF(K37>0, (K37-H37)/K37, 0) -> 0.49245512 | N37: =SUM(N11:N36) -> 901 | O37: =SUM(O11:O36) -> 249 | P37: CONSOLIDADO 100%
B39: 2. DETALLE CRUZADO INDIVIDUAL POR CADA INSUMO: COMPRAS, VENTAS Y FECHAS (ORDEN DE ABAJO HACIA ARRIBA)
B41: #1. VIVE 100 | Conteo Físico PDF: 37 und | Compras: 48 und ($103,200) | Ventas POS: 17 und ($61,200) | Margen: 40.3%
B42: Nota de Auditoría: Energizante Vive 100 380ml. Comprado en pacas de 24 und a Global Liquors ($51,600/paca = $2,150/und). Margen unitario POS: +40.3%.
B43: HISTORIAL DE COMPRAS REGISTRADAS EN EXCEL (2 transacciones) | J43: HISTORIAL DE VENTAS REGISTRADAS EN POS (13 registros diarios)
B44: Día | C44: Fecha | D44: Factura | E44: Proveedor | F44: Descripción en Factura | G44: Cant. (Und) | H44: Vr. Compra ($) | J44: Día | K44: Fecha | L44: Producto en POS | M44: Cant. Vend. | N44: Precio Unit. ($) | O44: Total Venta ($) | P44: Turno / Control
B45: 2 | C45: 02/09/2026 | D45: VC242401 | E45: Global Liquors (Licores) | F45: BEB.EN.*380 VIVE100 (Global Liquors - VC242401) | G45: 24 | H45: 51600 | J45: 2 | K45: 02/09/2026 | L45: Vive 100 grde | M45: 2 | N45: 3333 | O45: 7200 | P45: POS Regular
B46: 18 | C46: 18/09/2026 | D46: VC247919 | E46: Global Liquors (Licores) | F46: BEB.EN.*380 VIVE100 (Global Liquors) | G46: 24 | H46: 51600 | J46: 3 | K46: 03/09/2026 | L46: Vive 100 pequ | M46: 2 | N46: 3333 | O46: 7200 | P46: POS Regular
J47: 6 | K47: 06/09/2026 | L47: Vive 100 grde | M47: 2 | N47: 3333 | O47: 7200 | P47: POS Regular
J48: 8 | K48: 08/09/2026 | L48: Vive 100 grde | M48: 1 | N48: 3333 | O48: 3600 | P48: POS Regular
J49: 8 | K49: 08/09/2026 | L49: Vive 100 pequ | M49: 1 | N49: 3333 | O49: 3600 | P49: POS Regular
J50: 9 | K50: 09/09/2026 | L50: Vive 100 grde | M50: 1 | N50: 3333 | O50: 3600 | P50: POS Regular
J51: 10 | K51: 10/09/2026 | L51: Vive 100 grde | M51: 1 | N51: 3333 | O51: 3600 | P51: POS Regular
J52: 11 | K52: 11/09/2026 | L52: Vive 100 grde | M52: 1 | N52: 3333 | O52: 3600 | P52: POS Regular
J53: 14 | K53: 14/09/2026 | L53: Vive 100 grde | M53: 2 | N53: 3333 | O53: 7200 | P53: POS Regular
J54: 15 | K54: 15/09/2026 | L54: Vive 100 grde | M54: 2 | N54: 3333 | O54: 7200 | P54: POS Regular
J55: 17 | K55: 17/09/2026 | L55: Vive 100 grde | M55: 1 | N55: 3333 | O55: 3600 | P55: POS Regular
J56: 19 | K56: 19/09/2026 | L56: Vive 100 grde | M56: 1 | N56: 3333 | O56: 3600 | P56: POS Regular
J57: 20 | K57: 20/09/2026 | L57: Vive 100 pequ | M57: 0 | N57: 0 | O57: 0 | P57: POS Regular
B58: SUBTOTAL COMPRAS (Vive 100) | G58: 48 | H58: 103200 | J58: SUBTOTAL VENTAS (Vive 100) | M58: 17 | N58: - | O58: 61200 | P58: -
B60: INFORME ESPECIAL DE AUDITORÍA: PRODUCTOS NATURALES DE LA SABANA S.A.S. (ALQUERÍA)
B61: Consolidación unificada del proveedor Alquería: Insumos de Conteo Físico (#2 Hojuelas, #3 Alque mix, #4 Tampico/Tangelo, #5 Avena, #6 Actigest) + Insumos de Cocina/Barra (Leche Institucional 1.1L y Crema de Leche 1L)
B62: COMPRAS TOTALES ALQUERÍA | E62: VENTAS TOTALES POS | H62: CONTEO FÍSICO PDF (#2 AL #6) | K62: MARGEN BRUTO PROMEDIO | N62: ESTADO AUDITORÍA ALQUERÍA
B63: $1,226,021 | E63: $93,103 | H63: 26 und | K63: +25.8% | N63: CONCILIADO 100%
B64: 283 und compradas (4 facturas) | E64: 21 und (Avena, Hojuelas, Actigest) | H64: Nevera mostrador (26 unidades) | K64: Margen unitario sobre mostrador | N64: Avenas, Hojuelas y Actigest
B66: HISTORIAL COMPLETO DE COMPRAS ALQUERÍA (20 transacciones) | J66: HISTORIAL COMPLETO DE VENTAS POS ASOCIADAS A ALQUERÍA (15 transacciones)
B67: Día | C67: Fecha | D67: Factura | E67: Proveedor | F67: Descripción en Factura | G67: Cant. (Und) | H67: Vr. Compra ($) | J67: Día | K67: Fecha | L67: Producto en POS | M67: Cant. Vend. | N67: Precio Unit. ($) | O67: Total Venta ($) | P67: Clasificación / Uso
B68: 2 | C68: 02/09/2026 | D68: FEPL-3167991 | E68: Productos Naturales de la Sabana (Alquería) | F68: AVENA PRO CUBANA VASO 220G (Alquería - FEPL-3167991) | G68: 5 | H68: 15528 | J68: 2 | K68: 02/09/2026 | L68: Hojuelas | M68: 1 | N68: 4167 | O68: 4500 | P68: Mostrador / Empacado
B69: 2 | C69: 02/09/2026 | D69: FEPL-3167991 | E69: Productos Naturales de la Sabana (Alquería) | F69: AVENA PRO AUTENTICA VASO 220G (Alquería - FEPL-3167991) | G69: 5 | H69: 15528 | J69: 4 | K69: 04/09/2026 | L69: Actigest | M69: 0 | N69: 0 | O69: 0 | P69: Mostrador / Empacado
B70: 2 | C70: 02/09/2026 | D70: FEPL-3167991 | E70: Productos Naturales de la Sabana (Alquería) | F70: TANGELO BOTELLA 400 ML (Alquería - FEPL-3167991) | G70: 5 | H70: 6545 | J70: 4 | K70: 04/09/2026 | L70: Hojuelas | M70: 3 | N70: 4167 | O70: 13500 | P70: Mostrador / Empacado
B71: 2 | C71: 02/09/2026 | D71: FEPL-3167991 | E71: Productos Naturales de la Sabana (Alquería) | F71: ACTIGEST VAS 140G PIT CCB TT (Alquería - FEPL-3167991) | G71: 5 | H71: 12852 | J71: 6 | K71: 06/09/2026 | L71: Avena | M71: 2 | N71: 4167 | O71: 9000 | P71: Mostrador / Empacado
B72: 2 | C72: 02/09/2026 | D72: FEPL-3167991 | E72: Productos Naturales de la Sabana (Alquería) | F72: ALQUERIA CER 170G FLIPS (Alquería - FEPL-3167991) | G72: 3 | H72: 11281 | J72: 9 | K72: 09/09/2026 | L72: Hojuelas | M72: 2 | N72: 4167 | O72: 9000 | P72: Mostrador / Empacado
B73: 2 | C73: 02/09/2026 | D73: FEPL-3167991 | E73: Productos Naturales de la Sabana (Alquería) | F73: ALQUERÍA HOJUELAS 170GR (Alquería - FEPL-3167991) | G73: 3 | H73: 11281 | J73: 12 | K73: 12/09/2026 | L73: Actigest | M73: 0 | N73: 0 | O73: 0 | P73: Mostrador / Empacado
B74: 2 | C74: 02/09/2026 | D74: FEPL-3167991 | E74: Productos Naturales de la Sabana (Alquería) | F74: SABOR ORIGINAL INSTITUCIONAL 1100ML (Alquería - FEPL-3167991) | G74: 70 | H74: 292600 | J74: 12 | K74: 12/09/2026 | L74: Hojuelas | M74: 2 | N74: 4167 | O74: 9000 | P74: Mostrador / Empacado
B75: 2 | C75: 02/09/2026 | D75: FEPL-3167991 | E75: Productos Naturales de la Sabana (Alquería) | F75: CREMA DE LECHE 1000G (Alquería - FEPL-3167991) | G75: 4 | H75: 72800 | J75: 13 | K75: 13/09/2026 | L75: Avena | M75: 1 | N75: 4167 | O75: 4500 | P75: Mostrador / Empacado
B76: 9 | C76: 09/09/2026 | D76: MA42914 | E76: Distribuidora M y C S.A.S. | F76: ALQUEMIX GALAXY V 170G (PRODUCTOS NATURALES DE LA SABANA S.A.S. BIC) | G76: 5 | H76: 15800 | J76: 13 | K76: 13/09/2026 | L76: Hojuelas | M76: 4 | N76: 4167 | O76: 18000 | P76: Mostrador / Empacado
B77: 9 | C77: 09/09/2026 | D77: MA42914 | E77: Distribuidora M y C S.A.S. | F77: ALQUEMIX MILO V95G (PRODUCTOS NATURALES DE LA SABANA S.A.S. BIC) | G77: 5 | H77: 12550 | J77: 15 | K77: 15/09/2026 | L77: Hojuelas | M77: 1 | N77: 4167 | O77: 4500 | P77: Mostrador / Empacado
B78: 9 | C78: 09/09/2026 | D78: MA42914 | E78: Distribuidora M y C S.A.S. | F78: CREMA DE LECHE 1000G (PRODUCTOS NATURALES DE LA SABANA S.A.S. BIC) | G78: 2 | H78: 36400 | J78: 16 | K78: 16/09/2026 | L78: Avena | M78: 1 | N78: 4167 | O78: 4500 | P78: Mostrador / Empacado
B79: 9 | C79: 09/09/2026 | D79: MA42914 | E79: Distribuidora M y C S.A.S. | F79: SABOR ORIGINAL INSTITUCIONAL 1100ML (PRODUCTOS NATURALES DE LA SABANA S.A.S. BIC) | G79: 70 | H79: 292600 | J79: 16 | K79: 16/09/2026 | L79: Hojuelas | M79: 1 | N79: 2874 | O79: 3103 | P79: Mostrador / Empacado
... B82: 9 | C82: 09/09/2026 | D82: MA42914 | E82: Distribuidora M y C S.A.S. | F82: ALQUERIA CER 170G FLIPS (PRODUCTOS NATURALES DE LA SABANA S.A.S. BIC) | G82: 5 | H82: 15800 | J82: 20 | K82: 20/09/2026 | L82: Hojuelas | M82: 1 | N82: 4167 | O82: 4500 | P82: Mostrador / Empacado
B83: 9 | C83: 09/09/2026 | D83: MA42914 | E83: Distribuidora M y C S.A.S. | F83: ALQUERIA HOJUELAS 170GR (PRODUCTOS NATURALES DE LA SABANA S.A.S. BIC) | G83: 6 | H83: 18960
B84: 15 | C84: 15/09/2026 | D84: FEPL3208151 | E84: Productos Naturales de la Sabana (Alquería) | F84: CREMA DE LECHE 1000G (Alquería) | G84: 2 | H84: 36400
B85: 15 | C85: 15/09/2026 | D85: FEPL3208151 | E85: Productos Naturales de la Sabana (Alquería) | F85: SABOR ORIGINAL INSTITUCIONAL 1100ML (Alquería) | G85: 70 | H85: 292600
B86: 15 | C86: 15/09/2026 | D86: FEPL3208151 | E86: Productos Naturales de la Sabana (Alquería) | F86: TANGELO BOTELLA 400 ML (Alquería) | G86: 4 | H86: 5236
B87: 11 | C87: 11/09/2026 | D87: 38814 | E87: Distribuidora Doña Mary (Desechables) | F87: CREMA DE LECHE LTRO ALQUERIA BOLSA | G87: 2 | H87: 39600
B88: TOTAL COMPRAS PRODUCTOS NATURALES DE LA SABANA (ALQUERÍA) | G88: =SUM(G68:G87) -> 283 | H88: =SUM(H68:H87) -> 1226021 | J88: TOTAL VENTAS POS ASOCIADAS A ALQUERÍA | M88: 21 | N88: - | O88: 93103 | P88: -
B91: #7. DEL VALLE | Conteo Físico PDF: 4 und | Compras: 720 und ($504,000) | Ventas POS: 13 und ($32,500) | Margen: 72.0%
B92: Nota de Auditoría: Jugo Del Valle / Nutiva en caja 200ml (720 unidades compradas para menús infantiles) + unidades embotelladas en nevera.
B93: HISTORIAL DE COMPRAS REGISTRADAS EN EXCEL (1 transacciones) | J93: HISTORIAL DE VENTAS REGISTRADAS EN POS (8 registros diarios)
B94: Día | C94: Fecha | D94: Factura | E94: Proveedor | F94: Descripción en Factura | G94: Cant. (Und) | H94: Vr. Compra ($) | J94: Día | K94: Fecha | L94: Producto en POS | M94: Cant. Vend. | N94: Precio Unit. ($) | O94: Total Venta ($) | P94: Turno / Control
B95: 9 | C95: 09/09/2026 | D95: REM-38763 | E95: Distribuidora Doña Mary (Desechables) | F95: JUGO NUTIVA EN CAJA X 200ML (Doña Mary Remision 38763) | G95: 720 | H95: 504000 | J95: 4 | K95: 04/09/2026 | L95: Jugo del valle | M95: 1 | N95: 2315 | O95: 2500 | P95: POS Regular
J96: 12 | K96: 12/09/2026 | L96: Jugo del valle | M96: 1 | N96: 2315 | O96: 2500 | P96: POS Regular
J97: 13 | K97: 13/09/2026 | L97: Jugo del valle | M97: 2 | N97: 2315 | O97: 5000 | P97: POS Regular
J98: 16 | K98: 16/09/2026 | L98: Jugo del valle | M98: 2 | N98: 2315 | O98: 5000 | P98: POS Regular
J99: 17 | K99: 17/09/2026 | L99: Jugo del valle | M99: 1 | N99: 2315 | O99: 2500 | P99: POS Regular
J100: 18 | K100: 18/09/2026 | L100: Jugo del valle | M100: 4 | N100: 2315 | O100: 10000 | P100: POS Regular
J101: 19 | K101: 19/09/2026 | L101: Jugo del valle | M101: 1 | N101: 2315 | O101: 2500 | P101: POS Regular
J102: 20 | K102: 20/09/2026 | L102: Jugo del valle | M102: 1 | N102: 2315 | O102: 2500 | P102: POS Regular
B103: SUBTOTAL COMPRAS (Del valle) | G103: 720 | H103: 504000 | J103: SUBTOTAL VENTAS (Del valle) | M103: 13 | N103: - | O103: 32500 | P103: -
B105: #8. MR TEA | Conteo Físico PDF: 12 und | Compras: 12 und ($22,689) | Ventas POS: 0 und ($0) | Margen: 0.0%
B106: Nota de Auditoría: Té Mr Tea 500ml Pet (Durazno y Limón). Comprado a Postobón ($1,891/und). Conciliación perfecta: 12 compradas = 12 en conteo físico.
B107: HISTORIAL DE COMPRAS REGISTRADAS EN EXCEL (2 transacciones) | J107: HISTORIAL DE VENTAS REGISTRADAS EN POS (0 registros diarios)
B108: Día | C108: Fecha | D108: Factura | E108: Proveedor | F108: Descripción en Factura | G108: Cant. (Und) | H108: Vr. Compra ($) | J108: Día | K108: Fecha | L108: Producto en POS | M108: Cant. Vend. | N108: Precio Unit. ($) | O108: Total Venta ($) | P108: Turno / Control
B109: 5 | C109: 05/09/2026 | D109: JM07-1019725 | E109: Postobón S.A. | F109: DURAZNO MR TEA 500 ML PET X 12 (Postobón S.A.) | G109: 6 | H109: 11344.56 | J109: Sin ventas directas en POS (Consumo cocina / mostrador / porción)
B110: 5 | C110: 05/09/2026 | D110: JM07-1019725 | E110: Postobón S.A. | F110: LIMON MR TEA 500 ML PET X 12 (Postobón S.A.) | G110: 6 | H110: 11344.56
B111: SUBTOTAL COMPRAS (Mr tea) | G111: 12 | H111: 22689.12 | J111: SUBTOTAL VENTAS (Mr tea) | M111: 0 | N111: - | O111: 0 | P111: -
B113: #9. CANADA DRY | Conteo Físico PDF: 19 und | Compras: 0 und ($0) | Ventas POS: 0 und ($0) | Margen: 0.0%
B114: Nota de Auditoría: Canada Dry Ginger Ale (Postobón). Mezclador de coctelería y barra. Stock físico verificado de 19 unidades.
B115: HISTORIAL DE COMPRAS REGISTRADAS EN EXCEL (0 transacciones) | J115: HISTORIAL DE VENTAS REGISTRADAS EN POS (0 registros diarios)
B116: Día | C116: Fecha | D116: Factura | E116: Proveedor | F116: Descripción en Factura | G116: Cant. (Und) | H116: Vr. Compra ($) | J116: Día | K116: Fecha | L116: Producto en POS | M116: Cant. Vend. | N116: Precio Unit. ($) | O116: Total Venta ($) | P116: Turno / Control
B117: Sin compras directas registradas en el mes (Stock inicial / consignación) | J117: Sin ventas directas en POS (Consumo cocina / mostrador / porción)
B118: SUBTOTAL COMPRAS (Canada dry) | G118: 0 | H118: 0 | J118: SUBTOTAL VENTAS (Canada dry) | M118: 0 | N118: - | O118: 0 | P118: -
B120: #10. HIT NR | Conteo Físico PDF: 53 und | Compras: 0 und ($0) | Ventas POS: 33 und ($122,100) | Margen: 0.0%
B121: Nota de Auditoría: Jugo Hit No Retornable 500ml (Mango, Lulo, Mora). 33 ventas registradas en POS ($122,100). Stock remanente auditado en 53 unidades.
B122: HISTORIAL DE COMPRAS REGISTRADAS EN EXCEL (0 transacciones) | J122: HISTORIAL DE VENTAS REGISTRADAS EN POS (14 registros diarios)
B123: Día | C123: Fecha | D123: Factura | E123: Proveedor | F123: Descripción en Factura | G123: Cant. (Und) | H123: Vr. Compra ($) | J123: Día | K123: Fecha | L123: Producto en POS | M123: Cant. Vend. | N123: Precio Unit. ($) | O123: Total Venta ($) | P123: Turno / Control
B124: Sin compras directas registradas en el mes (Stock inicial / consignación) | J124: 2 | K124: 02/09/2026 | L124: Jugo hit nr | M124: 1 | N124: 3426 | O124: 3700 | P124: POS Regular
J125: 4 | K125: 04/09/2026 | L125: Jugo hit nr | M125: 2 | N125: 3426 | O125: 7400 | P125: POS Regular
J126: 6 | K126: 06/09/2026 | L126: Jugo hit nr | M126: 2 | N126: 3426 | O126: 7400 | P126: POS Regular
J127: 7 | K127: 07/09/2026 | L127: Jugo hit nr | M127: 4 | N127: 3426 | O127: 14800 | P127: POS Regular
...
